Workbook

Sheet SignalWatchlist
A1: SignalID | B1: SignalName | C1: SignalType | D1: ExpectedWindow | E1: Owner | F1: ExpectedDirection | G1: EstimatedImpact | H1: EvidenceSource | I1: Status | J1: Notes
A2: SIG-021 | B2: ATS guideline update discussion | C2: Regulatory | D2: ATS meeting | E2: Medical Affairs | F2: + | G2: High | H2: ATS conference | I2: Pending | J2: Guideline panel discussion expected
A3: SIG-022 | B3: Payer coverage expansion | C3: Commercial | D3: Next 6 months | E3: Market Access | F3: + | G3: Medium | H3: Payer policy updates | I3: Pending | J3: Monitoring policy bulletins
A4: SIG-023 | B4: Confirmatory trial interim data | C4: Clinical | D4: Q4 | E4: Clinical Team | F4: + | G4: High | H4: ClinicalTrials.gov | I4: Pending | J4: Interim analysis expected

Sheet ChangeLog
A1: Date | B1: SignalID | C1: SignalDescription | D1: Direction | E1: ProbabilityChange | F1: Interpretation | G1: Analyst
A2: 2026-05-12 | B2: SIG-010 | C2: ENCORE fatigue endpoint miss | D2: Negative | E2: -0.03 | F2: Minor reduction in adoption confidence | G2: Analyst
A3: 2026-06-03 | B3: SIG-014 | C3: Positive ATS panel commentary | D3: Positive | E3: 0.05 | F3: Improves guideline adoption probability | G3: Analyst
A4: 2026-03-15 | B4: V18 | C4: Inserted actor-reaction layer between signal structuring and probability engine. | D4: Preserved original V17 cockpit sheets; added CaseHeader, SignalRegister, Actors, ActorReactionMatrix, ActorAggregation, ProbabilityEngine, InterpretationLayer, and CalibrationLog.

Sheet WeeklyBrief
A1: CaseID | B1: CurrentProbability | C1: ChangeSinceLastReview | D1: TopDriver1 | E1: TopDriver2 | F1: TopDriver3 | G1: SignalsToMonitor | H1: NextDecisionCheckpoint | I1: PreparedBy | J1: Date
A2: ARK_FL_001 | B2: 0.42 | C2: +0.03 | D2: Guideline adoption probability | E2: Confirmatory clinical evidence | F2: Payer coverage expansion | G2: ATS guideline panel discussion | H2: ATS Annual Meeting | I2: CIOS Engine | J2: Auto-generated

Sheet FieldIntelligenceInbox
A1: FeedbackID | B1: Date | C1: Brand | D1: AudienceType | E1: Specialty | F1: Subspecialty | G1: Region | H1: SourceRole | I1: SourceName | J1: SignalCategory | K1: ObservedBarrier | L1: RawFieldFeedback | M1: BeliefShiftRisk | N1: MessageMismatchRisk | O1: AccessRisk | P1: CompetitiveRisk | Q1: UrgencyScore_1to5 | R1: CredibilityScore_1to5 | S1: FrequencyScore_1to5 | T1: PotentialImpact_1to5 | U1: TotalSignalScore | V1: CIOSSignalDirection | W1: SuggestedRoute | X1: PrimaryTargetPopulation | Y1: MIOSMessagePriority | Z1: OHOSObjectionPriority | AA1: FieldActionNeeded | AB1: Notes
A2: FB-001 | B2: 2026-03-13 | C2: ARIKAYCE | D2: HCP | E2: Pulmonology | F2: NTM-focused | G2: US South | H2: MSL | I2: Example KOL | J2: Clinical perception | K2: Culture conversion seen as less persuasive than symptom improvement | L2: Pulmonologists are asking for a more direct connection between microbiology and fatigue / functioning. | M2: 4 | N2: 5 | O2: 1 | P2: 1 | Q2: 5 | R2: 4 | S2: 3 | T2: 5 | U2: =SUM(Q2:T2) -> 17 | V2: Negative | W2: CIOS→MIOS+OHOS | X2: Pulmonology / community | Y2: High | Z2: High | AA2: Yes | AB2: Use symptom-bridge framing
A3: FB-002 | B3: 2026-03-13 | C3: ARIKAYCE | D3: HCP | E3: Infectious Disease | F3: Academic ID | G3: Northeast | H3: Sales | I3: Top account | J3: Competitive message | K3: Competitor perceived as easier to position because mechanism is simpler | L3: ID specialists are still persuaded by microbiology but want cleaner differentiation vs alternatives. | M3: 2 | N3: 3 | O3: 1 | P3: 4 | Q3: 3 | R3: 3 | S3: 2 | T3: 4 | U3: =SUM(Q3:T3) -> 12 | V3: Negative | W3: CIOS→OHOS | X3: Infectious Disease / academic | Y3: Medium | Z3: High | AA3: Yes | AB3: Differentiate on evidence depth
A4: FB-003 | B4: 2026-03-13 | C4: ARIKAYCE | D4: HCP | E4: Pulmonology | F4: General Pulm | G4: Midwest | H4: Sales | I4: Community account | J4: Access / workflow | K4: Diagnosis and referral pathway slowing consideration | L4: General pulmonologists need a simpler patient-identification story and referral confidence. | M4: 3 | N4: 4 | O4: 4 | P4: 1 | Q4: 4 | R4: 3 | S4: 4 | T4: 4 | U4: =SUM(Q4:T4) -> 15 | V4: Negative | W4: CIOS→MIOS | X4: Pulmonology / general | Y4: High | Z4: Medium | AA4: Yes | AB4: Simplify candidate-ID narrative

Sheet SegmentMessagingMatrix
A1: SegmentID | B1: AudienceType | C1: Specialty | D1: Subspecialty | E1: DecisionDriver1 | F1: DecisionDriver2 | G1: PreferredEvidenceType | H1: MessageEmphasis | I1: ProofNeed | J1: LikelyObjectionTheme | K1: OHOSResponseStyle | L1: FieldChannel | M1: PriorityRank
A2: SEG-001 | B2: HCP | C2: Pulmonology | D2: General Pulm | E2: Symptoms / function | F2: Simple patient identification | G2: Clinical outcomes + practical framing | H2: Symptom bridge + candidate identification | I2: Real-world practicality | J2: Referral complexity / unclear patient fit | K2: Simple, mechanism-to-practice | L2: Sales + MSL | M2: 1
A3: SEG-002 | B3: HCP | C3: Pulmonology | D3: NTM-focused | E3: Disease control | F3: Evidence depth | G3: Microbiology + clinical linkage | H3: Disease control → symptom/function | I3: Scientific linkage | J3: Need proof that endpoint matters clinically | K3: Evidence bridge with mechanistic logic | L3: MSL-led | M3: 2
A4: SEG-003 | B4: HCP | C4: Infectious Disease | D4: Academic ID | E4: Microbiology | F4: Differentiation | G4: Comparative evidence depth | H4: Evidence hierarchy + differentiation | I4: Study design rigor | J4: Alternative options easier to explain | K4: Structured objection ladder | L4: MSL-led | M4: 3

Sheet MessageUpdateRouter
A1: Field Intelligence Routing Engine
A3: FeedbackID | B3: TotalSignalScore | C3: SuggestedRoute | D3: PrimaryTargetPopulation | E3: MIOSMessagePriority | F3: OHOSObjectionPriority | G3: EscalationLevel | H3: RecommendedOwner | I3: RecommendedOutput | J3: FieldTeam
A4: =FieldIntelligenceInbox!A2 -> FB-001 | B4: =FieldIntelligenceInbox!U2 -> 17 | C4: =IF(B4="","",FieldIntelligenceInbox!W2) -> CIOS→MIOS+OHOS | D4: =IF(B4="","",FieldIntelligenceInbox!X2) -> Pulmonology / community | E4: =IF(B4="","",FieldIntelligenceInbox!Y2) -> High | F4: =IF(B4="","",FieldIntelligenceInbox!Z2) -> High | G4: =IF(B4="","",IF(B4>=16,"Urgent",IF(B4>=12,"High","Standard"))) -> Urgent | H4: =IF(B4="","",IF(C4="CIOS→MIOS+OHOS","Brand Strategy + Medical + Training",IF(C4="CIOS→MIOS","Medical Strategy",IF(C4="CIOS→OHOS","Field Strategy / Training","CIOS Review")))) -> Brand Strategy + Medical + Training | I4: =IF(B4="","",IF(C4="CIOS→MIOS+OHOS","Update core message + objection module + segment guidance",IF(C4="CIOS→MIOS","Update message architecture + segment narrative",IF(C4="CIOS→OHOS","Update objection ladder + response card","Review")))) -> Update core message + objection module + segment guidance | J4: =IF(B4="","",IF(LEFT(D4,11)="Pulmonology","Sales + MSL","MSL-led")) -> Sales + MSL
A5: =FieldIntelligenceInbox!A3 -> FB-002 | B5: =FieldIntelligenceInbox!U3 -> 12 | C5: =IF(B5="","",FieldIntelligenceInbox!W3) -> CIOS→OHOS | D5: =IF(B5="","",FieldIntelligenceInbox!X3) -> Infectious Disease / academic | E5: =IF(B5="","",FieldIntelligenceInbox!Y3) -> Medium | F5: =IF(B5="","",FieldIntelligenceInbox!Z3) -> High | G5: =IF(B5="","",IF(B5>=16,"Urgent",IF(B5>=12,"High","Standard"))) -> High | H5: =IF(B5="","",IF(C5="CIOS→MIOS+OHOS","Brand Strategy + Medical + Training",IF(C5="CIOS→MIOS","Medical Strategy",IF(C5="CIOS→OHOS","Field Strategy / Training","CIOS Review")))) -> Field Strategy / Training | I5: =IF(B5="","",IF(C5="CIOS→MIOS+OHOS","Update core message + objection module + segment guidance",IF(C5="CIOS→MIOS","Update message architecture + segment narrative",IF(C5="CIOS→OHOS","Update objection ladder + response card","Review")))) -> Update objection ladder + response card | J5: =IF(B5="","",IF(LEFT(D5,11)="Pulmonology","Sales + MSL","MSL-led")) -> MSL-led
A6: =FieldIntelligenceInbox!A4 -> FB-003 | B6: =FieldIntelligenceInbox!U4 -> 15 | C6: =IF(B6="","",FieldIntelligenceInbox!W4) -> CIOS→MIOS | D6: =IF(B6="","",FieldIntelligenceInbox!X4) -> Pulmonology / general | E6: =IF(B6="","",FieldIntelligenceInbox!Y4) -> High | F6: =IF(B6="","",FieldIntelligenceInbox!Z4) -> Medium | G6: =IF(B6="","",IF(B6>=16,"Urgent",IF(B6>=12,"High","Standard"))) -> High | H6: =IF(B6="","",IF(C6="CIOS→MIOS+OHOS","Brand Strategy + Medical + Training",IF(C6="CIOS→MIOS","Medical Strategy",IF(C6="CIOS→OHOS","Field Strategy / Training","CIOS Review")))) -> Medical Strategy | I6: =IF(B6="","",IF(C6="CIOS→MIOS+OHOS","Update core message + objection module + segment guidance",IF(C6="CIOS→MIOS","Update message architecture + segment narrative",IF(C6="CIOS→OHOS","Update objection ladder + response card","Review")))) -> Update message architecture + segment narrative | J6: =IF(B6="","",IF(LEFT(D6,11)="Pulmonology","Sales + MSL","MSL-led")) -> Sales + MSL
A7: =FieldIntelligenceInbox!A5 -> 0 | B7: =FieldIntelligenceInbox!U5 -> 0 | C7: =IF(B7="","",FieldIntelligenceInbox!W5) | D7: =IF(B7="","",FieldIntelligenceInbox!X5) | E7: =IF(B7="","",FieldIntelligenceInbox!Y5) | F7: =IF(B7="","",FieldIntelligenceInbox!Z5) | G7: =IF(B7="","",IF(B7>=16,"Urgent",IF(B7>=12,"High","Standard"))) | H7: =IF(B7="","",IF(C7="CIOS→MIOS+OHOS","Brand Strategy + Medical + Training",IF(C7="CIOS→MIOS","Medical Strategy",IF(C7="CIOS→OHOS","Field Strategy / Training","CIOS Review")))) | I7: =IF(B7="","",IF(C7="CIOS→MIOS+OHOS","Update core message + objection module + segment guidance",IF(C7="CIOS→MIOS","Update message architecture + segment narrative",IF(C7="CIOS→OHOS","Update objection ladder + response card","Review")))) | J7: =IF(B7="","",IF(LEFT(D7,11)="Pulmonology","Sales + MSL","MSL-led"))
A8: =FieldIntelligenceInbox!A6 -> 0 | B8: =FieldIntelligenceInbox!U6 -> 0 | C8: =IF(B8="","",FieldIntelligenceInbox!W6) | D8: =IF(B8="","",FieldIntelligenceInbox!X6) | E8: =IF(B8="","",FieldIntelligenceInbox!Y6) | F8: =IF(B8="","",FieldIntelligenceInbox!Z6) | G8: =IF(B8="","",IF(B8>=16,"Urgent",IF(B8>=12,"High","Standard"))) | H8: =IF(B8="","",IF(C8="CIOS→MIOS+OHOS","Brand Strategy + Medical + Training",IF(C8="CIOS→MIOS","Medical Strategy",IF(C8="CIOS→OHOS","Field Strategy / Training","CIOS Review")))) | I8: =IF(B8="","",IF(C8="CIOS→MIOS+OHOS","Update core message + objection module + segment guidance",IF(C8="CIOS→MIOS","Update message architecture + segment narrative",IF(C8="CIOS→OHOS","Update objection ladder + response card","Review")))) | J8: =IF(B8="","",IF(LEFT(D8,11)="Pulmonology","Sales + MSL","MSL-led"))
A9: =FieldIntelligenceInbox!A7 -> 0 | B9: =FieldIntelligenceInbox!U7 -> 0 | C9: =IF(B9="","",FieldIntelligenceInbox!W7) | D9: =IF(B9="","",FieldIntelligenceInbox!X7) | E9: =IF(B9="","",FieldIntelligenceInbox!Y7) | F9: =IF(B9="","",FieldIntelligenceInbox!Z7) | G9: =IF(B9="","",IF(B9>=16,"Urgent",IF(B9>=12,"High","Standard"))) | H9: =IF(B9="","",IF(C9="CIOS→MIOS+OHOS","Brand Strategy + Medical + Training",IF(C9="CIOS→MIOS","Medical Strategy",IF(C9="CIOS→OHOS","Field Strategy / Training","CIOS Review")))) | I9: =IF(B9="","",IF(C9="CIOS→MIOS+OHOS","Update core message + objection module + segment guidance",IF(C9="CIOS→MIOS","Update message architecture + segment narrative",IF(C9="CIOS→OHOS","Update objection ladder + response card","Review")))) | J9: =IF(B9="","",IF(LEFT(D9,11)="Pulmonology","Sales + MSL","MSL-led"))
A10: =FieldIntelligenceInbox!A8 -> 0 | B10: =FieldIntelligenceInbox!U8 -> 0 | C10: =IF(B10="","",FieldIntelligenceInbox!W8) | D10: =IF(B10="","",FieldIntelligenceInbox!X8) | E10: =IF(B10="","",FieldIntelligenceInbox!Y8) | F10: =IF(B10="","",FieldIntelligenceInbox!Z8) | G10: =IF(B10="","",IF(B10>=16,"Urgent",IF(B10>=12,"High","Standard"))) | H10: =IF(B10="","",IF(C10="CIOS→MIOS+OHOS","Brand Strategy + Medical + Training",IF(C10="CIOS→MIOS","Medical Strategy",IF(C10="CIOS→OHOS","Field Strategy / Training","CIOS Review")))) | I10: =IF(B10="","",IF(C10="CIOS→MIOS+OHOS","Update core message + objection module + segment guidance",IF(C10="CIOS→MIOS","Update message architecture + segment narrative",IF(C10="CIOS→OHOS","Update objection ladder + response card","Review")))) | J10: =IF(B10="","",IF(LEFT(D10,11)="Pulmonology","Sales + MSL","MSL-led"))
A11: =FieldIntelligenceInbox!A9 -> 0 | B11: =FieldIntelligenceInbox!U9 -> 0 | C11: =IF(B11="","",FieldIntelligenceInbox!W9) | D11: =IF(B11="","",FieldIntelligenceInbox!X9) | E11: =IF(B11="","",FieldIntelligenceInbox!Y9) | F11: =IF(B11="","",FieldIntelligenceInbox!Z9) | G11: =IF(B11="","",IF(B11>=16,"Urgent",IF(B11>=12,"High","Standard"))) | H11: =IF(B11="","",IF(C11="CIOS→MIOS+OHOS","Brand Strategy + Medical + Training",IF(C11="CIOS→MIOS","Medical Strategy",IF(C11="CIOS→OHOS","Field Strategy / Training","CIOS Review")))) | I11: =IF(B11="","",IF(C11="CIOS→MIOS+OHOS","Update core message + objection module + segment guidance",IF(C11="CIOS→MIOS","Update message architecture + segment narrative",IF(C11="CIOS→OHOS","Update objection ladder + response card","Review")))) | J11: =IF(B11="","",IF(LEFT(D11,11)="Pulmonology","Sales + MSL","MSL-led"))
A12: =FieldIntelligenceInbox!A10 -> 0 | B12: =FieldIntelligenceInbox!U10 -> 0 | C12: =IF(B12="","",FieldIntelligenceInbox!W10) | D12: =IF(B12="","",FieldIntelligenceInbox!X10) | E12: =IF(B12="","",FieldIntelligenceInbox!Y10) | F12: =IF(B12="","",FieldIntelligenceInbox!Z10) | G12: =IF(B12="","",IF(B12>=16,"Urgent",IF(B12>=12,"High","Standard"))) | H12: =IF(B12="","",IF(C12="CIOS→MIOS+OHOS","Brand Strategy + Medical + Training",IF(C12="CIOS→MIOS","Medical Strategy",IF(C12="CIOS→OHOS","Field Strategy / Training","CIOS Review")))) | I12: =IF(B12="","",IF(C12="CIOS→MIOS+OHOS","Update core message + objection module + segment guidance",IF(C12="CIOS→MIOS","Update message architecture + segment narrative",IF(C12="CIOS→OHOS","Update objection ladder + response card","Review")))) | J12: =IF(B12="","",IF(LEFT(D12,11)="Pulmonology","Sales + MSL","MSL-led"))
A13: =FieldIntelligenceInbox!A11 -> 0 | B13: =FieldIntelligenceInbox!U11 -> 0 | C13: =IF(B13="","",FieldIntelligenceInbox!W11) | D13: =IF(B13="","",FieldIntelligenceInbox!X11) | E13: =IF(B13="","",FieldIntelligenceInbox!Y11) | F13: =IF(B13="","",FieldIntelligenceInbox!Z11) | G13: =IF(B13="","",IF(B13>=16,"Urgent",IF(B13>=12,"High","Standard"))) | H13: =IF(B13="","",IF(C13="CIOS→MIOS+OHOS","Brand Strategy + Medical + Training",IF(C13="CIOS→MIOS","Medical Strategy",IF(C13="CIOS→OHOS","Field Strategy / Training","CIOS Review")))) | I13: =IF(B13="","",IF(C13="CIOS→MIOS+OHOS","Update core message + objection module + segment guidance",IF(C13="CIOS→MIOS","Update message architecture + segment narrative",IF(C13="CIOS→OHOS","Update objection ladder + response card","Review")))) | J13: =IF(B13="","",IF(LEFT(D13,11)="Pulmonology","Sales + MSL","MSL-led"))

Sheet FieldGuidanceOutput
A1: Field Guidance Output
A3: Latest high-priority feedback | D3: MIOS implication
A4: =FieldIntelligenceInbox!L2 -> Pulmonologists are asking for a more direct connection between microbiology and fatigue / functioning. | D4: Update message hierarchy, proof sequence, and segment-specific belief bridge.
A6: Primary target population | B6: =FieldIntelligenceInbox!X2 -> Pulmonology / community | D6: OHOS implication
A7: Recommended route | B7: =FieldIntelligenceInbox!W2 -> CIOS→MIOS+OHOS | D7: Refine objection modules and response cards for the affected segment.
A8: Escalation level | B8: =MessageUpdateRouter!G4 -> Urgent
A9: Recommended owner | B9: =MessageUpdateRouter!H4 -> Brand Strategy + Medical + Training | D9: Sales / MSL implication
D10: Deploy differentiated talk tracks by specialty and subspecialty; monitor recurrence in next cycle.
A11: Updated field direction
A12: 1. Anchor the discussion in the segment's dominant decision driver.
A13: 2. Bridge evidence to the clinical endpoint that the segment finds meaningful.
A14: 3. Use the objection ladder only after the segment-specific framing is established.
A15: 4. Escalate recurring objections with high signal scores into OHOS within the same review cycle.

Sheet SalesGuidance
A1: Segment | B1: What to lead with | C1: What to avoid | D1: Proof asset to use | E1: Call objective | F1: Escalate if...
A2: Pulmonology / community | B2: Symptoms, function, simpler patient identification | C2: Opening with endpoint jargon alone | D2: Practical patient-fit aid | E2: Create confidence in candidate identification | F2: same objection appears across 3+ accounts
A3: Pulmonology / NTM-focused | B3: Disease control linked to patient meaning | C3: Oversimplifying evidence depth | D3: Mechanistic bridge + outcomes detail | E3: Strengthen belief that endpoint matters clinically | F3: clinical skepticism intensifies
A4: Infectious Disease / academic | B4: Evidence depth and differentiation | C4: Over-indexing on broad symptom language | D4: Evidence hierarchy summary | E4: Defend scientific distinctiveness | F4: comparative objection persists

Sheet MSLGuidance
A1: Segment | B1: Scientific angle | C1: Core bridge | D1: Likely challenge | E1: MSL response mode | F1: Evidence follow-up needed
A2: Pulmonology / NTM-focused | B2: Microbiology to clinical meaning | C2: Disease control → symptom/function | D2: Endpoint clinical relevance | E2: Mechanism + evidence bridge | F2: Yes
A3: Infectious Disease / academic | B3: Comparative evidence architecture | C3: Endpoint rigor → treatment confidence | D3: Alternative options easier to explain | E3: Structured scientific differentiation | F3: Yes
A4: Pulmonology / general | B4: Patient identification and referral logic | C4: Candidate clarity → treatment confidence | D4: Workflow burden | E4: Practical scientific framing | F4: Maybe

Sheet DeploymentTracker
A1: Closed-Loop Deployment Tracker
A3: DeploymentID | B3: FeedbackID | C3: Brand | D3: Segment | E3: Account | F3: FieldTeam | G3: RecommendedOutput | H3: DeploymentDate | I3: DeploymentType | J3: MessageVersion | K3: OHOSModuleVersion | L3: MIOSUpdateFlag | M3: Owner | N3: Status | O3: ReviewDate | P3: ObservationWindow_Days | Q3: PreObjectionRate | R3: PostObjectionRate | S3: PreAccessFriction | T3: PostAccessFriction | U3: PreEngagementScore | V3: PostEngagementScore | W3: ObjectionChange | X3: AccessFrictionChange | Y3: EngagementChange | Z3: NetFieldImprovement | AA3: EscalateBackToCIOS
A4: DEP-001 | B4: FB-001 | C4: ARIKAYCE | D4: Pulmonology / community | E4: Community Pulm Account A | F4: Sales + MSL | G4: Update core message + objection module + segment guidance | H4: 2026-03-20 | I4: Message + training | J4: MSG-v2 | K4: OHOS-v2 | L4: Yes | M4: Brand Strategy | N4: Live | O4: 2026-04-20 | P4: 30 | Q4: 0.6 | R4: 0.4 | S4: 0.5 | T4: 0.35 | U4: 3 | V4: 4 | W4: =R4-Q4 -> -0.2 | X4: =T4-S4 -> -0.15 | Y4: =V4-U4 -> 1 | Z4: =-(W4+X4)+Y4 -> 1.35 | AA4: =IF(Z4>0.4,"No","Yes") -> No
A5: DEP-002 | B5: FB-002 | C5: ARIKAYCE | D5: Infectious Disease / academic | E5: Academic ID Center | F5: MSL-led | G5: Update objection ladder + response card | H5: 2026-03-22 | I5: Scientific objection update | J5: MSG-v2 | K5: OHOS-v3 | L5: No | M5: Field Strategy | N5: Live | O5: 2026-04-22 | P5: 30 | Q5: 0.55 | R5: 0.48 | S5: 0.3 | T5: 0.28 | U5: 3.2 | V5: 3.8 | W5: =R5-Q5 -> -0.07 | X5: =T5-S5 -> -0.02 | Y5: =V5-U5 -> 0.6 | Z5: =-(W5+X5)+Y5 -> 0.69 | AA5: =IF(Z5>0.4,"No","Yes") -> No
A6: DEP-003 | B6: FB-003 | C6: ARIKAYCE | D6: Pulmonology / general | E6: General Pulm Network B | F6: Sales + MSL | G6: Update message architecture + segment narrative | H6: 2026-03-25 | I6: Message simplification | J6: MSG-v3 | K6: OHOS-v3 | L6: Yes | M6: Medical Strategy | N6: Planned | O6: 2026-04-25 | P6: 30 | Q6: 0.5 | R6: 0.5 | S6: 0.65 | T6: 0.65 | U6: 2.8 | V6: 2.8 | W6: =R6-Q6 -> 0 | X6: =T6-S6 -> 0 | Y6: =V6-U6 -> 0 | Z6: =-(W6+X6)+Y6 -> 0 | AA6: =IF(Z6>0.4,"No","Yes") -> Yes

Sheet SegmentOutcomeTracker
A1: Segment Outcome Tracker
A3: Segment | B3: Deployments | C3: AvgPreObjectionRate | D3: AvgPostObjectionRate | E3: AvgPreAccessFriction | F3: AvgPostAccessFriction | G3: AvgPreEngagement | H3: AvgPostEngagement | I3: AvgObjectionChange | J3: AvgAccessChange | K3: AvgEngagementChange | L3: AvgNetFieldImprovement | M3: Interpretation
A4: Pulmonology / community | B4: =COUNTIF(DeploymentTracker!D:D,A4) -> 1 | C4: =IF(B4=0,"",SUMIF(DeploymentTracker!D:D,A4,DeploymentTracker!Q:Q)/B4) -> 0.6 | D4: =IF(B4=0,"",SUMIF(DeploymentTracker!D:D,A4,DeploymentTracker!R:R)/B4) -> 0.4 | E4: =IF(B4=0,"",SUMIF(DeploymentTracker!D:D,A4,DeploymentTracker!S:S)/B4) -> 0.5 | F4: =IF(B4=0,"",SUMIF(DeploymentTracker!D:D,A4,DeploymentTracker!T:T)/B4) -> 0.35 | G4: =IF(B4=0,"",SUMIF(DeploymentTracker!D:D,A4,DeploymentTracker!U:U)/B4) -> 3 | H4: =IF(B4=0,"",SUMIF(DeploymentTracker!D:D,A4,DeploymentTracker!V:V)/B4) -> 4 | I4: =IF(B4=0,"",SUMIF(DeploymentTracker!D:D,A4,DeploymentTracker!W:W)/B4) -> -0.2 | J4: =IF(B4=0,"",SUMIF(DeploymentTracker!D:D,A4,DeploymentTracker!X:X)/B4) -> -0.15 | K4: =IF(B4=0,"",SUMIF(DeploymentTracker!D:D,A4,DeploymentTracker!Y:Y)/B4) -> 1 | L4: =IF(B4=0,"",SUMIF(DeploymentTracker!D:D,A4,DeploymentTracker!Z:Z)/B4) -> 1.35 | M4: =IF(L4="","",IF(L4>0.4,"Improving strongly",IF(L4>0.15,"Improving modestly","Limited movement"))) -> Improving strongly
A5: Infectious Disease / academic | B5: =COUNTIF(DeploymentTracker!D:D,A5) -> 1 | C5: =IF(B5=0,"",SUMIF(DeploymentTracker!D:D,A5,DeploymentTracker!Q:Q)/B5) -> 0.55 | D5: =IF(B5=0,"",SUMIF(DeploymentTracker!D:D,A5,DeploymentTracker!R:R)/B5) -> 0.48 | E5: =IF(B5=0,"",SUMIF(DeploymentTracker!D:D,A5,DeploymentTracker!S:S)/B5) -> 0.3 | F5: =IF(B5=0,"",SUMIF(DeploymentTracker!D:D,A5,DeploymentTracker!T:T)/B5) -> 0.28 | G5: =IF(B5=0,"",SUMIF(DeploymentTracker!D:D,A5,DeploymentTracker!U:U)/B5) -> 3.2 | H5: =IF(B5=0,"",SUMIF(DeploymentTracker!D:D,A5,DeploymentTracker!V:V)/B5) -> 3.8 | I5: =IF(B5=0,"",SUMIF(DeploymentTracker!D:D,A5,DeploymentTracker!W:W)/B5) -> -0.07 | J5: =IF(B5=0,"",SUMIF(DeploymentTracker!D:D,A5,DeploymentTracker!X:X)/B5) -> -0.02 | K5: =IF(B5=0,"",SUMIF(DeploymentTracker!D:D,A5,DeploymentTracker!Y:Y)/B5) -> 0.6 | L5: =IF(B5=0,"",SUMIF(DeploymentTracker!D:D,A5,DeploymentTracker!Z:Z)/B5) -> 0.69 | M5: =IF(L5="","",IF(L5>0.4,"Improving strongly",IF(L5>0.15,"Improving modestly","Limited movement"))) -> Improving strongly
A6: Pulmonology / general | B6: =COUNTIF(DeploymentTracker!D:D,A6) -> 1 | C6: =IF(B6=0,"",SUMIF(DeploymentTracker!D:D,A6,DeploymentTracker!Q:Q)/B6) -> 0.5 | D6: =IF(B6=0,"",SUMIF(DeploymentTracker!D:D,A6,DeploymentTracker!R:R)/B6) -> 0.5 | E6: =IF(B6=0,"",SUMIF(DeploymentTracker!D:D,A6,DeploymentTracker!S:S)/B6) -> 0.65 | F6: =IF(B6=0,"",SUMIF(DeploymentTracker!D:D,A6,DeploymentTracker!T:T)/B6) -> 0.65 | G6: =IF(B6=0,"",SUMIF(DeploymentTracker!D:D,A6,DeploymentTracker!U:U)/B6) -> 2.8 | H6: =IF(B6=0,"",SUMIF(DeploymentTracker!D:D,A6,DeploymentTracker!V:V)/B6) -> 2.8 | I6: =IF(B6=0,"",SUMIF(DeploymentTracker!D:D,A6,DeploymentTracker!W:W)/B6) -> 0 | J6: =IF(B6=0,"",SUMIF(DeploymentTracker!D:D,A6,DeploymentTracker!X:X)/B6) -> 0 | K6: =IF(B6=0,"",SUMIF(DeploymentTracker!D:D,A6,DeploymentTracker!Y:Y)/B6) -> 0 | L6: =IF(B6=0,"",SUMIF(DeploymentTracker!D:D,A6,DeploymentTracker!Z:Z)/B6) -> 0 | M6: =IF(L6="","",IF(L6>0.4,"Improving strongly",IF(L6>0.15,"Improving modestly","Limited movement"))) -> Limited movement

Sheet AccountFeedbackLoop
A1: Account Feedback Loop
A3: Account | B3: Segment | C3: LatestDeploymentID | D3: Status | E3: PreObjectionRate | F3: PostObjectionRate | G3: PreAccessFriction | H3: PostAccessFriction | I3: PreEngagement | J3: PostEngagement | K3: NetFieldImprovement | L3: RecommendedNextMove | M3: SendBackToMIOS | N3: SendBackToOHOS | O3: FollowUpOwner
A4: Community Pulm Account A | B4: Pulmonology / community | C4: =DeploymentTracker!A4 -> DEP-001 | D4: =DeploymentTracker!N4 -> Live | E4: =DeploymentTracker!Q4 -> 0.6 | F4: =DeploymentTracker!R4 -> 0.4 | G4: =DeploymentTracker!S4 -> 0.5 | H4: =DeploymentTracker!T4 -> 0.35 | I4: =DeploymentTracker!U4 -> 3 | J4: =DeploymentTracker!V4 -> 4 | K4: =DeploymentTracker!Z4 -> 1.35 | L4: =IF(K4="","",IF(K4>0.4,"Scale current approach",IF(K4>0.15,"Refine and re-test","Rework message and objection strategy"))) -> Scale current approach | M4: =IF(K4="","",IF(AND(K4<=0.15,E4-F4<0.1),"Yes","No")) -> No | N4: =IF(K4="","",IF(AND(K4<=0.15,G4-H4<0.05),"Yes","No")) -> No | O4: =IF(B4="","",IF(LEFT(B4,11)="Pulmonology","Sales + MSL","MSL-led")) -> Sales + MSL
A5: Academic ID Center | B5: Infectious Disease / academic | C5: =DeploymentTracker!A5 -> DEP-002 | D5: =DeploymentTracker!N5 -> Live | E5: =DeploymentTracker!Q5 -> 0.55 | F5: =DeploymentTracker!R5 -> 0.48 | G5: =DeploymentTracker!S5 -> 0.3 | H5: =DeploymentTracker!T5 -> 0.28 | I5: =DeploymentTracker!U5 -> 3.2 | J5: =DeploymentTracker!V5 -> 3.8 | K5: =DeploymentTracker!Z5 -> 0.69 | L5: =IF(K5="","",IF(K5>0.4,"Scale current approach",IF(K5>0.15,"Refine and re-test","Rework message and objection strategy"))) -> Scale current approach | M5: =IF(K5="","",IF(AND(K5<=0.15,E5-F5<0.1),"Yes","No")) -> No | N5: =IF(K5="","",IF(AND(K5<=0.15,G5-H5<0.05),"Yes","No")) -> No | O5: =IF(B5="","",IF(LEFT(B5,11)="Pulmonology","Sales + MSL","MSL-led")) -> MSL-led
A6: General Pulm Network B | B6: Pulmonology / general | C6: =DeploymentTracker!A6 -> DEP-003 | D6: =DeploymentTracker!N6 -> Planned | E6: =DeploymentTracker!Q6 -> 0.5 | F6: =DeploymentTracker!R6 -> 0.5 | G6: =DeploymentTracker!S6 -> 0.65 | H6: =DeploymentTracker!T6 -> 0.65 | I6: =DeploymentTracker!U6 -> 2.8 | J6: =DeploymentTracker!V6 -> 2.8 | K6: =DeploymentTracker!Z6 -> 0 | L6: =IF(K6="","",IF(K6>0.4,"Scale current approach",IF(K6>0.15,"Refine and re-test","Rework message and objection strategy"))) -> Rework message and objection strategy | M6: =IF(K6="","",IF(AND(K6<=0.15,E6-F6<0.1),"Yes","No")) -> Yes | N6: =IF(K6="","",IF(AND(K6<=0.15,G6-H6<0.05),"Yes","No")) -> Yes | O6: =IF(B6="","",IF(LEFT(B6,11)="Pulmonology","Sales + MSL","MSL-led")) -> Sales + MSL

Sheet ClosedLoopDashboard
A1: Closed-Loop Deployment Dashboard
A3: Live deployments | B3: =COUNTIF(DeploymentTracker!N:N,"Live") -> 2 | D3: System reading
A4: Planned deployments | B4: =COUNTIF(DeploymentTracker!N:N,"Planned") -> 1 | D4: =IF(B5>0.25,"Deployed updates are reducing friction in at least part of the field.","Field changes are not yet producing strong movement.") -> Deployed updates are reducing friction in at least part of the field.
A5: Average net field improvement | B5: =AVERAGE(DeploymentTracker!Z:Z) -> 0.68
A6: Accounts to send back to MIOS | B6: =COUNTIF(AccountFeedbackLoop!M:M,"Yes") -> 1 | D6: What to do next
A7: Accounts to send back to OHOS | B7: =COUNTIF(AccountFeedbackLoop!N:N,"Yes") -> 1 | D7: =IF(B6+B7>0,"Re-route weak-performing accounts to MIOS/OHOS review this cycle.","Continue scaled deployment and monitor repeat objections.") -> Re-route weak-performing accounts to MIOS/OHOS review this cycle.
A8: Segments improving strongly | B8: =COUNTIF(SegmentOutcomeTracker!M:M,"Improving strongly") -> 2
A10: Segment | B10: Avg Net Improvement | C10: Interpretation
A11: =SegmentOutcomeTracker!A4 -> Pulmonology / community | B11: =SegmentOutcomeTracker!L4 -> 1.35 | C11: =SegmentOutcomeTracker!M4 -> Improving strongly
A12: =SegmentOutcomeTracker!A5 -> Infectious Disease / academic | B12: =SegmentOutcomeTracker!L5 -> 0.69 | C12: =SegmentOutcomeTracker!M5 -> Improving strongly
A13: =SegmentOutcomeTracker!A6 -> Pulmonology / general | B13: =SegmentOutcomeTracker!L6 -> 0 | C13: =SegmentOutcomeTracker!M6 -> Limited movement
A16: Account | B16: Next Move | C16: Back to MIOS | D16: Back to OHOS
A17: =AccountFeedbackLoop!A4 -> Community Pulm Account A | B17: =AccountFeedbackLoop!L4 -> Scale current approach | C17: =AccountFeedbackLoop!M4 -> No | D17: =AccountFeedbackLoop!N4 -> No
A18: =AccountFeedbackLoop!A5 -> Academic ID Center | B18: =AccountFeedbackLoop!L5 -> Scale current approach | C18: =AccountFeedbackLoop!M5 -> No | D18: =AccountFeedbackLoop!N5 -> No
A19: =AccountFeedbackLoop!A6 -> General Pulm Network B | B19: =AccountFeedbackLoop!L6 -> Rework message and objection strategy | C19: =AccountFeedbackLoop!M6 -> Yes | D19: =AccountFeedbackLoop!N6 -> Yes

Sheet DeploymentInstructions
A1: Closed-Loop Deployment Instructions
A3: 1. Add new deployed changes to DeploymentTracker after message or objection updates go live.
A4: 2. Record pre- and post-deployment objection rate, access friction, and engagement score by account.
A5: 3. Review SegmentOutcomeTracker to see whether the updated message is working by specialty/subspecialty.
A6: 4. Review AccountFeedbackLoop to identify where the update should be sent back to MIOS or OHOS.
A7: 5. Use ClosedLoopDashboard as the leadership summary to show whether field change is reducing friction.
A8: 6. Architectural rule: CIOS detects and scores change; MIOS updates message architecture; OHOS updates objection response; field teams execute and measure.

Sheet SourceMonitorConfig
A1: Automation Layer - Source Monitor Configuration
A3: SourceID | B3: SourceType | C3: SourceName | D3: CoverageFocus | E3: MonitorFrequency | F3: TriggerPattern | G3: ExpectedSignalType | H3: DefaultBrand | I3: DefaultRoute | J3: Priority | K3: Active
A4: SRC-001 | B4: Literature | C4: PubMed | D4: Clinical / medical evidence | E4: Weekly | F4: new trial|meta-analysis|safety|guideline | G4: Clinical | H4: ARIKAYCE | I4: CIOS→MIOS | J4: 1 | K4: Yes
A5: SRC-002 | B5: Trials | C5: ClinicalTrials.gov | D5: Trial status and readouts | E5: Weekly | F5: recruiting complete|interim|primary completion|results posted | G5: Clinical | H5: ARIKAYCE | I5: CIOS | J5: 1 | K5: Yes
A6: SRC-003 | B6: Conference | C6: Medical congress abstracts | D6: Abstracts and presentations | E6: Weekly | F6: late-breaker|abstract|poster|oral presentation | G6: Clinical perception | H6: ARIKAYCE | I6: CIOS→MIOS | J6: 2 | K6: Yes
A7: SRC-004 | B7: Commercial | C7: Press releases / earnings / payer bulletins | D7: Market access and competition | E7: Weekly | F7: coverage|launch|label|guidance|commercial update | G7: Commercial | H7: ARIKAYCE | I7: CIOS→OHOS | J7: 2 | K7: Yes
A8: SRC-005 | B8: Field | C8: MSL / sales / KOL notes | D8: Field resistance and adoption barriers | E8: Weekly | F8: objection recurring|workflow|patient fit|comparative challenge | G8: Field intelligence | H8: ARIKAYCE | I8: CIOS→MIOS+OHOS | J8: 1 | K8: Yes

Sheet CandidateSignalQueue
A1: Candidate Signal Queue
A3: CandidateID | B3: DateDetected | C3: SourceID | D3: SourceName | E3: Brand | F3: RawSourceType | G3: Headline | H3: RawObservation | I3: ProposedSignalCategory | J3: ProposedDirection | K3: Urgency_1to5 | L3: Credibility_1to5 | M3: Frequency_1to5 | N3: PotentialImpact_1to5 | O3: AutomationPriorityScore | P3: SuggestedRoute | Q3: TargetSegment | R3: AnalystStatus | S3: AnalystDecision | T3: ValidationNotes | U3: ValidatedSignalID
A4: CS-001 | B4: 2026-03-13 | C4: SRC-001 | D4: PubMed | E4: ARIKAYCE | F4: Literature | G4: New publication emphasizes patient-relevant outcomes linkage | H4: A new publication appears to strengthen the bridge between microbiology and function. | I4: Clinical evidence | J4: Positive | K4: 4 | L4: 5 | M4: 2 | N4: 4 | O4: =SUM(K4:N4) -> 15 | P4: CIOS→MIOS | Q4: Pulmonology / NTM-focused | R4: Queued
A5: CS-002 | B5: 2026-03-13 | C5: SRC-005 | D5: Field notes | E5: ARIKAYCE | F5: Field | G5: Community pulmonologists still unclear on patient-fit | H5: Multiple accounts continue to ask for a simpler identification and referral story. | I5: Field intelligence | J5: Negative | K5: 4 | L5: 4 | M5: 4 | N5: 4 | O5: =SUM(K5:N5) -> 16 | P5: CIOS→MIOS+OHOS | Q5: Pulmonology / community | R5: Queued
A6: CS-003 | B6: 2026-03-13 | C6: SRC-004 | D6: Payer bulletin | E6: ARIKAYCE | F6: Commercial | G6: Coverage update may lower access friction in selected plans | H6: Emerging coverage shift could reduce reimbursement obstacles in target accounts. | I6: Access / commercial | J6: Positive | K6: 3 | L6: 4 | M6: 2 | N6: 5 | O6: =SUM(K6:N6) -> 14 | P6: CIOS→OHOS | Q6: Pulmonology / general | R6: Queued

Sheet SignalNormalization
A1: Signal Normalization Workbench
A3: CandidateID | B3: Brand | C3: Headline | D3: NormalizedSignalDescription | E3: SignalType | F3: Direction | G3: StrengthScore_1to5 | H3: ReliabilityScore_1to5 | I3: LikelihoodRatio | J3: SuggestedLinkedSystem | K3: TargetPopulation | L3: ProposedOwner | M3: ReadyForRegister
A4: =CandidateSignalQueue!A4 -> CS-001 | B4: =CandidateSignalQueue!E4 -> ARIKAYCE | C4: =CandidateSignalQueue!G4 -> New publication emphasizes patient-relevant outcomes linkage | D4: =IF(A4="","",CandidateSignalQueue!H4) -> A new publication appears to strengthen the bridge between microbiology and function. | E4: =IF(A4="","",CandidateSignalQueue!I4) -> Clinical evidence | F4: =IF(A4="","",CandidateSignalQueue!J4) -> Positive | G4: =IF(A4="","",ROUND(CandidateSignalQueue!N4/1,0)) -> 4 | H4: =IF(A4="","",ROUND(CandidateSignalQueue!L4/1,0)) -> 5 | I4: =IF(A4="","",IF(F4="Positive",1+(G4*0.08),1-(G4*0.08))) -> 1.32 | J4: =IF(A4="","",CandidateSignalQueue!P4) -> CIOS→MIOS | K4: =IF(A4="","",CandidateSignalQueue!Q4) -> Pulmonology / NTM-focused | L4: =IF(A4="","",IF(J4="CIOS→MIOS+OHOS","Brand Strategy + Medical + Training",IF(J4="CIOS→MIOS","Medical Strategy",IF(J4="CIOS→OHOS","Field Strategy / Training","CIOS Review")))) -> Medical Strategy | M4: =IF(A4="","",IF(CandidateSignalQueue!S4="Validate","Yes","No")) -> No
A5: =CandidateSignalQueue!A5 -> CS-002 | B5: =CandidateSignalQueue!E5 -> ARIKAYCE | C5: =CandidateSignalQueue!G5 -> Community pulmonologists still unclear on patient-fit | D5: =IF(A5="","",CandidateSignalQueue!H5) -> Multiple accounts continue to ask for a simpler identification and referral story. | E5: =IF(A5="","",CandidateSignalQueue!I5) -> Field intelligence | F5: =IF(A5="","",CandidateSignalQueue!J5) -> Negative | G5: =IF(A5="","",ROUND(CandidateSignalQueue!N5/1,0)) -> 4 | H5: =IF(A5="","",ROUND(CandidateSignalQueue!L5/1,0)) -> 4 | I5: =IF(A5="","",IF(F5="Positive",1+(G5*0.08),1-(G5*0.08))) -> 0.68 | J5: =IF(A5="","",CandidateSignalQueue!P5) -> CIOS→MIOS+OHOS | K5: =IF(A5="","",CandidateSignalQueue!Q5) -> Pulmonology / community | L5: =IF(A5="","",IF(J5="CIOS→MIOS+OHOS","Brand Strategy + Medical + Training",IF(J5="CIOS→MIOS","Medical Strategy",IF(J5="CIOS→OHOS","Field Strategy / Training","CIOS Review")))) -> Brand Strategy + Medical + Training | M5: =IF(A5="","",IF(CandidateSignalQueue!S5="Validate","Yes","No")) -> No
A6: =CandidateSignalQueue!A6 -> CS-003 | B6: =CandidateSignalQueue!E6 -> ARIKAYCE | C6: =CandidateSignalQueue!G6 -> Coverage update may lower access friction in selected plans | D6: =IF(A6="","",CandidateSignalQueue!H6) -> Emerging coverage shift could reduce reimbursement obstacles in target accounts. | E6: =IF(A6="","",CandidateSignalQueue!I6) -> Access / commercial | F6: =IF(A6="","",CandidateSignalQueue!J6) -> Positive | G6: =IF(A6="","",ROUND(CandidateSignalQueue!N6/1,0)) -> 5 | H6: =IF(A6="","",ROUND(CandidateSignalQueue!L6/1,0)) -> 4 | I6: =IF(A6="","",IF(F6="Positive",1+(G6*0.08),1-(G6*0.08))) -> 1.4 | J6: =IF(A6="","",CandidateSignalQueue!P6) -> CIOS→OHOS | K6: =IF(A6="","",CandidateSignalQueue!Q6) -> Pulmonology / general | L6: =IF(A6="","",IF(J6="CIOS→MIOS+OHOS","Brand Strategy + Medical + Training",IF(J6="CIOS→MIOS","Medical Strategy",IF(J6="CIOS→OHOS","Field Strategy / Training","CIOS Review")))) -> Field Strategy / Training | M6: =IF(A6="","",IF(CandidateSignalQueue!S6="Validate","Yes","No")) -> No
A7: =CandidateSignalQueue!A7 -> 0 | B7: =CandidateSignalQueue!E7 -> 0 | C7: =CandidateSignalQueue!G7 -> 0 | D7: =IF(A7="","",CandidateSignalQueue!H7) | E7: =IF(A7="","",CandidateSignalQueue!I7) | F7: =IF(A7="","",CandidateSignalQueue!J7) | G7: =IF(A7="","",ROUND(CandidateSignalQueue!N7/1,0)) | H7: =IF(A7="","",ROUND(CandidateSignalQueue!L7/1,0)) | I7: =IF(A7="","",IF(F7="Positive",1+(G7*0.08),1-(G7*0.08))) | J7: =IF(A7="","",CandidateSignalQueue!P7) | K7: =IF(A7="","",CandidateSignalQueue!Q7) | L7: =IF(A7="","",IF(J7="CIOS→MIOS+OHOS","Brand Strategy + Medical + Training",IF(J7="CIOS→MIOS","Medical Strategy",IF(J7="CIOS→OHOS","Field Strategy / Training","CIOS Review")))) | M7: =IF(A7="","",IF(CandidateSignalQueue!S7="Validate","Yes","No"))
A8: =CandidateSignalQueue!A8 -> 0 | B8: =CandidateSignalQueue!E8 -> 0 | C8: =CandidateSignalQueue!G8 -> 0 | D8: =IF(A8="","",CandidateSignalQueue!H8) | E8: =IF(A8="","",CandidateSignalQueue!I8) | F8: =IF(A8="","",CandidateSignalQueue!J8) | G8: =IF(A8="","",ROUND(CandidateSignalQueue!N8/1,0)) | H8: =IF(A8="","",ROUND(CandidateSignalQueue!L8/1,0)) | I8: =IF(A8="","",IF(F8="Positive",1+(G8*0.08),1-(G8*0.08))) | J8: =IF(A8="","",CandidateSignalQueue!P8) | K8: =IF(A8="","",CandidateSignalQueue!Q8) | L8: =IF(A8="","",IF(J8="CIOS→MIOS+OHOS","Brand Strategy + Medical + Training",IF(J8="CIOS→MIOS","Medical Strategy",IF(J8="CIOS→OHOS","Field Strategy / Training","CIOS Review")))) | M8: =IF(A8="","",IF(CandidateSignalQueue!S8="Validate","Yes","No"))
A9: =CandidateSignalQueue!A9 -> 0 | B9: =CandidateSignalQueue!E9 -> 0 | C9: =CandidateSignalQueue!G9 -> 0 | D9: =IF(A9="","",CandidateSignalQueue!H9) | E9: =IF(A9="","",CandidateSignalQueue!I9) | F9: =IF(A9="","",CandidateSignalQueue!J9) | G9: =IF(A9="","",ROUND(CandidateSignalQueue!N9/1,0)) | H9: =IF(A9="","",ROUND(CandidateSignalQueue!L9/1,0)) | I9: =IF(A9="","",IF(F9="Positive",1+(G9*0.08),1-(G9*0.08))) | J9: =IF(A9="","",CandidateSignalQueue!P9) | K9: =IF(A9="","",CandidateSignalQueue!Q9) | L9: =IF(A9="","",IF(J9="CIOS→MIOS+OHOS","Brand Strategy + Medical + Training",IF(J9="CIOS→MIOS","Medical Strategy",IF(J9="CIOS→OHOS","Field Strategy / Training","CIOS Review")))) | M9: =IF(A9="","",IF(CandidateSignalQueue!S9="Validate","Yes","No"))
A10: =CandidateSignalQueue!A10 -> 0 | B10: =CandidateSignalQueue!E10 -> 0 | C10: =CandidateSignalQueue!G10 -> 0 | D10: =IF(A10="","",CandidateSignalQueue!H10) | E10: =IF(A10="","",CandidateSignalQueue!I10) | F10: =IF(A10="","",CandidateSignalQueue!J10) | G10: =IF(A10="","",ROUND(CandidateSignalQueue!N10/1,0)) | H10: =IF(A10="","",ROUND(CandidateSignalQueue!L10/1,0)) | I10: =IF(A10="","",IF(F10="Positive",1+(G10*0.08),1-(G10*0.08))) | J10: =IF(A10="","",CandidateSignalQueue!P10) | K10: =IF(A10="","",CandidateSignalQueue!Q10) | L10: =IF(A10="","",IF(J10="CIOS→MIOS+OHOS","Brand Strategy + Medical + Training",IF(J10="CIOS→MIOS","Medical Strategy",IF(J10="CIOS→OHOS","Field Strategy / Training","CIOS Review")))) | M10: =IF(A10="","",IF(CandidateSignalQueue!S10="Validate","Yes","No"))
A11: =CandidateSignalQueue!A11 -> 0 | B11: =CandidateSignalQueue!E11 -> 0 | C11: =CandidateSignalQueue!G11 -> 0 | D11: =IF(A11="","",CandidateSignalQueue!H11) | E11: =IF(A11="","",CandidateSignalQueue!I11) | F11: =IF(A11="","",CandidateSignalQueue!J11) | G11: =IF(A11="","",ROUND(CandidateSignalQueue!N11/1,0)) | H11: =IF(A11="","",ROUND(CandidateSignalQueue!L11/1,0)) | I11: =IF(A11="","",IF(F11="Positive",1+(G11*0.08),1-(G11*0.08))) | J11: =IF(A11="","",CandidateSignalQueue!P11) | K11: =IF(A11="","",CandidateSignalQueue!Q11) | L11: =IF(A11="","",IF(J11="CIOS→MIOS+OHOS","Brand Strategy + Medical + Training",IF(J11="CIOS→MIOS","Medical Strategy",IF(J11="CIOS→OHOS","Field Strategy / Training","CIOS Review")))) | M11: =IF(A11="","",IF(CandidateSignalQueue!S11="Validate","Yes","No"))
A12: =CandidateSignalQueue!A12 -> 0 | B12: =CandidateSignalQueue!E12 -> 0 | C12: =CandidateSignalQueue!G12 -> 0 | D12: =IF(A12="","",CandidateSignalQueue!H12) | E12: =IF(A12="","",CandidateSignalQueue!I12) | F12: =IF(A12="","",CandidateSignalQueue!J12) | G12: =IF(A12="","",ROUND(CandidateSignalQueue!N12/1,0)) | H12: =IF(A12="","",ROUND(CandidateSignalQueue!L12/1,0)) | I12: =IF(A12="","",IF(F12="Positive",1+(G12*0.08),1-(G12*0.08))) | J12: =IF(A12="","",CandidateSignalQueue!P12) | K12: =IF(A12="","",CandidateSignalQueue!Q12) | L12: =IF(A12="","",IF(J12="CIOS→MIOS+OHOS","Brand Strategy + Medical + Training",IF(J12="CIOS→MIOS","Medical Strategy",IF(J12="CIOS→OHOS","Field Strategy / Training","CIOS Review")))) | M12: =IF(A12="","",IF(CandidateSignalQueue!S12="Validate","Yes","No"))
A13: =CandidateSignalQueue!A13 -> 0 | B13: =CandidateSignalQueue!E13 -> 0 | C13: =CandidateSignalQueue!G13 -> 0 | D13: =IF(A13="","",CandidateSignalQueue!H13) | E13: =IF(A13="","",CandidateSignalQueue!I13) | F13: =IF(A13="","",CandidateSignalQueue!J13) | G13: =IF(A13="","",ROUND(CandidateSignalQueue!N13/1,0)) | H13: =IF(A13="","",ROUND(CandidateSignalQueue!L13/1,0)) | I13: =IF(A13="","",IF(F13="Positive",1+(G13*0.08),1-(G13*0.08))) | J13: =IF(A13="","",CandidateSignalQueue!P13) | K13: =IF(A13="","",CandidateSignalQueue!Q13) | L13: =IF(A13="","",IF(J13="CIOS→MIOS+OHOS","Brand Strategy + Medical + Training",IF(J13="CIOS→MIOS","Medical Strategy",IF(J13="CIOS→OHOS","Field Strategy / Training","CIOS Review")))) | M13: =IF(A13="","",IF(CandidateSignalQueue!S13="Validate","Yes","No"))

Sheet ValidationWorkbench
A1: Analyst Validation Workbench
A3: CandidateID | B3: Headline | C3: PriorityScore | D3: SuggestedRoute | E3: SignalType | F3: Direction | G3: LikelihoodRatio | H3: ReadyForRegister | I3: ValidationDecision | J3: RegisterSignalID | K3: SendToMIOS | L3: SendToOHOS | M3: Comments
A4: =SignalNormalization!A4 -> CS-001 | B4: =SignalNormalization!C4 -> New publication emphasizes patient-relevant outcomes linkage | C4: =CandidateSignalQueue!O4 -> 15 | D4: =SignalNormalization!J4 -> CIOS→MIOS | E4: =SignalNormalization!E4 -> Clinical evidence | F4: =SignalNormalization!F4 -> Positive | G4: =SignalNormalization!I4 -> 1.32 | H4: =SignalNormalization!M4 -> No | J4: =IF(I4="Approve","SIG-AUTO-"&TEXT(ROW()-3,"000"),"") | K4: =IF(I4="Approve",IF(OR(D4="CIOS→MIOS",D4="CIOS→MIOS+OHOS"),"Yes","No"),"") | L4: =IF(I4="Approve",IF(OR(D4="CIOS→OHOS",D4="CIOS→MIOS+OHOS"),"Yes","No"),"")
A5: =SignalNormalization!A5 -> CS-002 | B5: =SignalNormalization!C5 -> Community pulmonologists still unclear on patient-fit | C5: =CandidateSignalQueue!O5 -> 16 | D5: =SignalNormalization!J5 -> CIOS→MIOS+OHOS | E5: =SignalNormalization!E5 -> Field intelligence | F5: =SignalNormalization!F5 -> Negative | G5: =SignalNormalization!I5 -> 0.68 | H5: =SignalNormalization!M5 -> No | J5: =IF(I5="Approve","SIG-AUTO-"&TEXT(ROW()-3,"000"),"") | K5: =IF(I5="Approve",IF(OR(D5="CIOS→MIOS",D5="CIOS→MIOS+OHOS"),"Yes","No"),"") | L5: =IF(I5="Approve",IF(OR(D5="CIOS→OHOS",D5="CIOS→MIOS+OHOS"),"Yes","No"),"")
A6: =SignalNormalization!A6 -> CS-003 | B6: =SignalNormalization!C6 -> Coverage update may lower access friction in selected plans | C6: =CandidateSignalQueue!O6 -> 14 | D6: =SignalNormalization!J6 -> CIOS→OHOS | E6: =SignalNormalization!E6 -> Access / commercial | F6: =SignalNormalization!F6 -> Positive | G6: =SignalNormalization!I6 -> 1.4 | H6: =SignalNormalization!M6 -> No | J6: =IF(I6="Approve","SIG-AUTO-"&TEXT(ROW()-3,"000"),"") | K6: =IF(I6="Approve",IF(OR(D6="CIOS→MIOS",D6="CIOS→MIOS+OHOS"),"Yes","No"),"") | L6: =IF(I6="Approve",IF(OR(D6="CIOS→OHOS",D6="CIOS→MIOS+OHOS"),"Yes","No"),"")
A7: =SignalNormalization!A7 -> 0 | B7: =SignalNormalization!C7 -> 0 | C7: =CandidateSignalQueue!O7 -> 0 | D7: =SignalNormalization!J7 | E7: =SignalNormalization!E7 | F7: =SignalNormalization!F7 | G7: =SignalNormalization!I7 | H7: =SignalNormalization!M7 | J7: =IF(I7="Approve","SIG-AUTO-"&TEXT(ROW()-3,"000"),"") | K7: =IF(I7="Approve",IF(OR(D7="CIOS→MIOS",D7="CIOS→MIOS+OHOS"),"Yes","No"),"") | L7: =IF(I7="Approve",IF(OR(D7="CIOS→OHOS",D7="CIOS→MIOS+OHOS"),"Yes","No"),"")
A8: =SignalNormalization!A8 -> 0 | B8: =SignalNormalization!C8 -> 0 | C8: =CandidateSignalQueue!O8 -> 0 | D8: =SignalNormalization!J8 | E8: =SignalNormalization!E8 | F8: =SignalNormalization!F8 | G8: =SignalNormalization!I8 | H8: =SignalNormalization!M8 | J8: =IF(I8="Approve","SIG-AUTO-"&TEXT(ROW()-3,"000"),"") | K8: =IF(I8="Approve",IF(OR(D8="CIOS→MIOS",D8="CIOS→MIOS+OHOS"),"Yes","No"),"") | L8: =IF(I8="Approve",IF(OR(D8="CIOS→OHOS",D8="CIOS→MIOS+OHOS"),"Yes","No"),"")
A9: =SignalNormalization!A9 -> 0 | B9: =SignalNormalization!C9 -> 0 | C9: =CandidateSignalQueue!O9 -> 0 | D9: =SignalNormalization!J9 | E9: =SignalNormalization!E9 | F9: =SignalNormalization!F9 | G9: =SignalNormalization!I9 | H9: =SignalNormalization!M9 | J9: =IF(I9="Approve","SIG-AUTO-"&TEXT(ROW()-3,"000"),"") | K9: =IF(I9="Approve",IF(OR(D9="CIOS→MIOS",D9="CIOS→MIOS+OHOS"),"Yes","No"),"") | L9: =IF(I9="Approve",IF(OR(D9="CIOS→OHOS",D9="CIOS→MIOS+OHOS"),"Yes","No"),"")
A10: =SignalNormalization!A10 -> 0 | B10: =SignalNormalization!C10 -> 0 | C10: =CandidateSignalQueue!O10 -> 0 | D10: =SignalNormalization!J10 | E10: =SignalNormalization!E10 | F10: =SignalNormalization!F10 | G10: =SignalNormalization!I10 | H10: =SignalNormalization!M10 | J10: =IF(I10="Approve","SIG-AUTO-"&TEXT(ROW()-3,"000"),"") | K10: =IF(I10="Approve",IF(OR(D10="CIOS→MIOS",D10="CIOS→MIOS+OHOS"),"Yes","No"),"") | L10: =IF(I10="Approve",IF(OR(D10="CIOS→OHOS",D10="CIOS→MIOS+OHOS"),"Yes","No"),"")
A11: =SignalNormalization!A11 -> 0 | B11: =SignalNormalization!C11 -> 0 | C11: =CandidateSignalQueue!O11 -> 0 | D11: =SignalNormalization!J11 | E11: =SignalNormalization!E11 | F11: =SignalNormalization!F11 | G11: =SignalNormalization!I11 | H11: =SignalNormalization!M11 | J11: =IF(I11="Approve","SIG-AUTO-"&TEXT(ROW()-3,"000"),"") | K11: =IF(I11="Approve",IF(OR(D11="CIOS→MIOS",D11="CIOS→MIOS+OHOS"),"Yes","No"),"") | L11: =IF(I11="Approve",IF(OR(D11="CIOS→OHOS",D11="CIOS→MIOS+OHOS"),"Yes","No"),"")
A12: =SignalNormalization!A12 -> 0 | B12: =SignalNormalization!C12 -> 0 | C12: =CandidateSignalQueue!O12 -> 0 | D12: =SignalNormalization!J12 | E12: =SignalNormalization!E12 | F12: =SignalNormalization!F12 | G12: =SignalNormalization!I12 | H12: =SignalNormalization!M12 | J12: =IF(I12="Approve","SIG-AUTO-"&TEXT(ROW()-3,"000"),"") | K12: =IF(I12="Approve",IF(OR(D12="CIOS→MIOS",D12="CIOS→MIOS+OHOS"),"Yes","No"),"") | L12: =IF(I12="Approve",IF(OR(D12="CIOS→OHOS",D12="CIOS→MIOS+OHOS"),"Yes","No"),"")
A13: =SignalNormalization!A13 -> 0 | B13: =SignalNormalization!C13 -> 0 | C13: =CandidateSignalQueue!O13 -> 0 | D13: =SignalNormalization!J13 | E13: =SignalNormalization!E13 | F13: =SignalNormalization!F13 | G13: =SignalNormalization!I13 | H13: =SignalNormalization!M13 | J13: =IF(I13="Approve","SIG-AUTO-"&TEXT(ROW()-3,"000"),"") | K13: =IF(I13="Approve",IF(OR(D13="CIOS→MIOS",D13="CIOS→MIOS+OHOS"),"Yes","No"),"") | L13: =IF(I13="Approve",IF(OR(D13="CIOS→OHOS",D13="CIOS→MIOS+OHOS"),"Yes","No"),"")

Sheet RegisterPush
A1: Validated Signal Register Push
A3: RegisterSignalID | B3: CandidateID | C3: Brand | D3: SignalDescription | E3: SignalType | F3: Direction | G3: StrengthScore | H3: ReliabilityScore | I3: LikelihoodRatio | J3: Route | K3: TargetPopulation | L3: MIOSFlag | M3: OHOSFlag | N3: ReadyForManualCopy
A4: =IF(ValidationWorkbench!I4="Approve",ValidationWorkbench!J4,"") | B4: =ValidationWorkbench!A4 -> CS-001 | C4: =SignalNormalization!B4 -> ARIKAYCE | D4: =SignalNormalization!D4 -> A new publication appears to strengthen the bridge between microbiology and function. | E4: =SignalNormalization!E4 -> Clinical evidence | F4: =SignalNormalization!F4 -> Positive | G4: =SignalNormalization!G4 -> 4 | H4: =SignalNormalization!H4 -> 5 | I4: =SignalNormalization!I4 -> 1.32 | J4: =SignalNormalization!J4 -> CIOS→MIOS | K4: =SignalNormalization!K4 -> Pulmonology / NTM-focused | L4: =ValidationWorkbench!K4 | M4: =ValidationWorkbench!L4 | N4: =IF(A4<>"","Yes","")
A5: =IF(ValidationWorkbench!I5="Approve",ValidationWorkbench!J5,"") | B5: =ValidationWorkbench!A5 -> CS-002 | C5: =SignalNormalization!B5 -> ARIKAYCE | D5: =SignalNormalization!D5 -> Multiple accounts continue to ask for a simpler identification and referral story. | E5: =SignalNormalization!E5 -> Field intelligence | F5: =SignalNormalization!F5 -> Negative | G5: =SignalNormalization!G5 -> 4 | H5: =SignalNormalization!H5 -> 4 | I5: =SignalNormalization!I5 -> 0.68 | J5: =SignalNormalization!J5 -> CIOS→MIOS+OHOS | K5: =SignalNormalization!K5 -> Pulmonology / community | L5: =ValidationWorkbench!K5 | M5: =ValidationWorkbench!L5 | N5: =IF(A5<>"","Yes","")
A6: =IF(ValidationWorkbench!I6="Approve",ValidationWorkbench!J6,"") | B6: =ValidationWorkbench!A6 -> CS-003 | C6: =SignalNormalization!B6 -> ARIKAYCE | D6: =SignalNormalization!D6 -> Emerging coverage shift could reduce reimbursement obstacles in target accounts. | E6: =SignalNormalization!E6 -> Access / commercial | F6: =SignalNormalization!F6 -> Positive | G6: =SignalNormalization!G6 -> 5 | H6: =SignalNormalization!H6 -> 4 | I6: =SignalNormalization!I6 -> 1.4 | J6: =SignalNormalization!J6 -> CIOS→OHOS | K6: =SignalNormalization!K6 -> Pulmonology / general | L6: =ValidationWorkbench!K6 | M6: =ValidationWorkbench!L6 | N6: =IF(A6<>"","Yes","")
A7: =IF(ValidationWorkbench!I7="Approve",ValidationWorkbench!J7,"") | B7: =ValidationWorkbench!A7 -> 0 | C7: =SignalNormalization!B7 -> 0 | D7: =SignalNormalization!D7 | E7: =SignalNormalization!E7 | F7: =SignalNormalization!F7 | G7: =SignalNormalization!G7 | H7: =SignalNormalization!H7 | I7: =SignalNormalization!I7 | J7: =SignalNormalization!J7 | K7: =SignalNormalization!K7 | L7: =ValidationWorkbench!K7 | M7: =ValidationWorkbench!L7 | N7: =IF(A7<>"","Yes","")
A8: =IF(ValidationWorkbench!I8="Approve",ValidationWorkbench!J8,"") | B8: =ValidationWorkbench!A8 -> 0 | C8: =SignalNormalization!B8 -> 0 | D8: =SignalNormalization!D8 | E8: =SignalNormalization!E8 | F8: =SignalNormalization!F8 | G8: =SignalNormalization!G8 | H8: =SignalNormalization!H8 | I8: =SignalNormalization!I8 | J8: =SignalNormalization!J8 | K8: =SignalNormalization!K8 | L8: =ValidationWorkbench!K8 | M8: =ValidationWorkbench!L8 | N8: =IF(A8<>"","Yes","")
A9: =IF(ValidationWorkbench!I9="Approve",ValidationWorkbench!J9,"") | B9: =ValidationWorkbench!A9 -> 0 | C9: =SignalNormalization!B9 -> 0 | D9: =SignalNormalization!D9 | E9: =SignalNormalization!E9 | F9: =SignalNormalization!F9 | G9: =SignalNormalization!G9 | H9: =SignalNormalization!H9 | I9: =SignalNormalization!I9 | J9: =SignalNormalization!J9 | K9: =SignalNormalization!K9 | L9: =ValidationWorkbench!K9 | M9: =ValidationWorkbench!L9 | N9: =IF(A9<>"","Yes","")
A10: =IF(ValidationWorkbench!I10="Approve",ValidationWorkbench!J10,"") | B10: =ValidationWorkbench!A10 -> 0 | C10: =SignalNormalization!B10 -> 0 | D10: =SignalNormalization!D10 | E10: =SignalNormalization!E10 | F10: =SignalNormalization!F10 | G10: =SignalNormalization!G10 | H10: =SignalNormalization!H10 | I10: =SignalNormalization!I10 | J10: =SignalNormalization!J10 | K10: =SignalNormalization!K10 | L10: =ValidationWorkbench!K10 | M10: =ValidationWorkbench!L10 | N10: =IF(A10<>"","Yes","")
A11: =IF(ValidationWorkbench!I11="Approve",ValidationWorkbench!J11,"") | B11: =ValidationWorkbench!A11 -> 0 | C11: =SignalNormalization!B11 -> 0 | D11: =SignalNormalization!D11 | E11: =SignalNormalization!E11 | F11: =SignalNormalization!F11 | G11: =SignalNormalization!G11 | H11: =SignalNormalization!H11 | I11: =SignalNormalization!I11 | J11: =SignalNormalization!J11 | K11: =SignalNormalization!K11 | L11: =ValidationWorkbench!K11 | M11: =ValidationWorkbench!L11 | N11: =IF(A11<>"","Yes","")
A12: =IF(ValidationWorkbench!I12="Approve",ValidationWorkbench!J12,"") | B12: =ValidationWorkbench!A12 -> 0 | C12: =SignalNormalization!B12 -> 0 | D12: =SignalNormalization!D12 | E12: =SignalNormalization!E12 | F12: =SignalNormalization!F12 | G12: =SignalNormalization!G12 | H12: =SignalNormalization!H12 | I12: =SignalNormalization!I12 | J12: =SignalNormalization!J12 | K12: =SignalNormalization!K12 | L12: =ValidationWorkbench!K12 | M12: =ValidationWorkbench!L12 | N12: =IF(A12<>"","Yes","")
A13: =IF(ValidationWorkbench!I13="Approve",ValidationWorkbench!J13,"") | B13: =ValidationWorkbench!A13 -> 0 | C13: =SignalNormalization!B13 -> 0 | D13: =SignalNormalization!D13 | E13: =SignalNormalization!E13 | F13: =SignalNormalization!F13 | G13: =SignalNormalization!G13 | H13: =SignalNormalization!H13 | I13: =SignalNormalization!I13 | J13: =SignalNormalization!J13 | K13: =SignalNormalization!K13 | L13: =ValidationWorkbench!K13 | M13: =ValidationWorkbench!L13 | N13: =IF(A13<>"","Yes","")

Sheet AutomationDashboard
A1: Automation Layer Dashboard
A3: Queued candidates | B3: =COUNTIF(CandidateSignalQueue!R:R,"Queued") -> 3 | D3: System reading
A4: In review | B4: =COUNTIF(CandidateSignalQueue!R:R,"In Review") -> 0 | D4: =IF(B5+B6>0,"Automation queue is being filtered through analyst review before register entry.","No review activity yet.") -> No review activity yet.
A5: Approved | B5: =COUNTIF(ValidationWorkbench!I:I,"Approve") -> 0
A6: Rejected | B6: =COUNTIF(ValidationWorkbench!I:I,"Reject") -> 0 | D6: Next action
A7: Escalated | B7: =COUNTIF(ValidationWorkbench!I:I,"Escalate") -> 0 | D7: =IF(B8>0,"Copy approved rows from RegisterPush into SignalRegister / MIOS / OHOS workflow.","Continue reviewing queued candidates.") -> Continue reviewing queued candidates.
A8: Ready for SignalRegister | B8: =COUNTIF(RegisterPush!N:N,"Yes") -> 0
A10: Top candidate | B10: Priority | C10: Route | D10: Analyst decision
A11: =CandidateSignalQueue!A4 -> CS-001 | B11: =CandidateSignalQueue!O4 -> 15 | C11: =CandidateSignalQueue!P4 -> CIOS→MIOS | D11: =ValidationWorkbench!I4 -> 0
A12: =CandidateSignalQueue!A5 -> CS-002 | B12: =CandidateSignalQueue!O5 -> 16 | C12: =CandidateSignalQueue!P5 -> CIOS→MIOS+OHOS | D12: =ValidationWorkbench!I5 -> 0
A13: =CandidateSignalQueue!A6 -> CS-003 | B13: =CandidateSignalQueue!O6 -> 14 | C13: =CandidateSignalQueue!P6 -> CIOS→OHOS | D13: =ValidationWorkbench!I6 -> 0
A14: =CandidateSignalQueue!A7 -> 0 | B14: =CandidateSignalQueue!O7 -> 0 | C14: =CandidateSignalQueue!P7 -> 0 | D14: =ValidationWorkbench!I7 -> 0
A15: =CandidateSignalQueue!A8 -> 0 | B15: =CandidateSignalQueue!O8 -> 0 | C15: =CandidateSignalQueue!P8 -> 0 | D15: =ValidationWorkbench!I8 -> 0

Sheet AutomationInstructions
A1: Automation Layer Instructions
A3: 1. Configure monitored sources in SourceMonitorConfig by source type, trigger patterns, and route.
A4: 2. Add machine-detected candidate observations into CandidateSignalQueue.
A5: 3. Use SignalNormalization to convert raw observations into structured signal fields.
A6: 4. Analyst reviews the normalized candidates in ValidationWorkbench and marks Approve / Reject / Escalate / Hold.
A7: 5. Approved candidates populate RegisterPush and can be copied into CIOS SignalRegister and routed to MIOS / OHOS.
A8: 6. Architectural rule: automation proposes candidate signals; humans validate before they affect the core engine.
A9: 7. This keeps CIOS deterministic while still allowing scalable signal intake.

Sheet Cockpit_Home
A1: CaseID | B1: StrategicQuestion | C1: OutcomeDefinition | D1: TimeHorizon | E1: CurrentProbability | F1: ConfidenceLevel | G1: LastUpdate
A2: =CaseHeader!B4 -> CASE-001 | B2: =CaseHeader!B5 -> Will the monitored brand move closer to target adoption given the current validated signal set? | C2: =CaseHeader!B6 -> Net probability that the target outcome becomes more likely after signal validation and actor-response translation. | D2: =CaseHeader!B7 -> 12 months | E2: =ProbabilityEngine!B9 -> 0.59946999 | F2: =ProbabilityEngine!B10 -> High | G2: =CaseHeader!B13 -> 46096
A4: V18 upgrade | B4: Actor-reaction layer inserted between signal structuring and core probability update.
A5: Pharma tuning | B5: Actor logic now adapts by specialty profile, payer environment, guideline leverage, competitor profile, and target-population keywords.
A6: V19 upgrade | B6: Specialty-specific actor sets now swap the active actor composition by therapeutic context while preserving the same probability engine.

Sheet CaseHeader
A1: CIOS V18 Case Header
A3: Field | B3: Value
A4: CaseID | B4: CASE-001
A5: StrategicQuestion | B5: Will the monitored brand move closer to target adoption given the current validated signal set?
A6: OutcomeDefinition | B6: Net probability that the target outcome becomes more likely after signal validation and actor-response translation.
A7: TimeHorizon | B7: 12 months
A8: PriorProbability | B8: 0.45
A9: CurrentProbability | B9: =ProbabilityEngine!B9 -> 0.59946999
A10: ConfidenceLevel | B10: =ProbabilityEngine!B10 -> High
A11: SignalCount | B11: =COUNTIF(SignalRegister!A4:A33,"<>") -> 30
A12: PrimaryBrand | B12: =IFERROR(INDEX(SignalRegister!C4:C33,MATCH(TRUE(),INDEX(SignalRegister!C4:C33<>"",0),0)),"") -> ARIKAYCE
A13: LastUpdate | B13: =TODAY() -> 46096
A14: TopSupportiveActor | B14: =ActorAggregation!B10 -> Academic KOLs
A15: TopConstrainingActor | B15: =ActorAggregation!B11 -> Competitor Counteraction
A16: PrimarySpecialtyProfile | B16: General
A17: PayerEnvironment | B17: Balanced
A18: GuidelineLeverage | B18: Medium
A19: CompetitorProfile | B19: Entrenched standard of care
A21: UpgradeNote | B21: V19 adds specialty-specific actor sets while preserving the V18 actor-reaction and probability architecture.
A22: ActiveActorSet | B22: =B16 -> General

Sheet SignalRegister
A1: CIOS V18 Signal Register
A3: SignalID | B3: CandidateID | C3: Brand | D3: SignalDescription | E3: SignalType | F3: Direction | G3: StrengthScore | H3: ReliabilityScore | I3: LikelihoodRatio | J3: Route | K3: TargetPopulation | L3: MIOSFlag | M3: OHOSFlag | N3: WeightedSignalScore | O3: ActorAdjustedImpact | P3: ActiveLikelihoodRatio | Q3: AbsoluteImpact
A4: =IF(RegisterPush!B4="","",IF(RegisterPush!A4<>"",RegisterPush!A4,RegisterPush!B4)) -> CS-001 | B4: =IF(RegisterPush!B4="","",RegisterPush!B4) -> CS-001 | C4: =IF(RegisterPush!B4="","",RegisterPush!C4) -> ARIKAYCE | D4: =IF(RegisterPush!B4="","",RegisterPush!D4) -> A new publication appears to strengthen the bridge between microbiology and function. | E4: =IF(RegisterPush!B4="","",RegisterPush!E4) -> Clinical evidence | F4: =IF(RegisterPush!B4="","",RegisterPush!F4) -> Positive | G4: =IF(RegisterPush!B4="","",RegisterPush!G4) -> 4 | H4: =IF(RegisterPush!B4="","",RegisterPush!H4) -> 5 | I4: =IF(RegisterPush!B4="","",RegisterPush!I4) -> 1.32 | J4: =IF(RegisterPush!B4="","",RegisterPush!J4) -> CIOS→MIOS | K4: =IF(RegisterPush!B4="","",RegisterPush!K4) -> Pulmonology / NTM-focused | L4: =IF(B4="","",IF(RegisterPush!L4<>"",RegisterPush!L4,IF(OR(J4="CIOS→MIOS",J4="CIOS→MIOS+OHOS"),"Yes","No"))) -> Yes | M4: =IF(B4="","",IF(RegisterPush!M4<>"",RegisterPush!M4,IF(OR(J4="CIOS→OHOS",J4="CIOS→MIOS+OHOS"),"Yes","No"))) -> No | N4: =IF(B4="","",G4*H4) -> 20 | O4: =IF(B4="","",ActorReactionMatrix!M4) -> 0.74808375 | P4: =IF(B4="",1,IF(I4="",1,I4)) -> 1.32 | Q4: =IF(B4="","",ABS(O4)) -> 0.74808375
A5: =IF(RegisterPush!B5="","",IF(RegisterPush!A5<>"",RegisterPush!A5,RegisterPush!B5)) -> CS-002 | B5: =IF(RegisterPush!B5="","",RegisterPush!B5) -> CS-002 | C5: =IF(RegisterPush!B5="","",RegisterPush!C5) -> ARIKAYCE | D5: =IF(RegisterPush!B5="","",RegisterPush!D5) -> Multiple accounts continue to ask for a simpler identification and referral story. | E5: =IF(RegisterPush!B5="","",RegisterPush!E5) -> Field intelligence | F5: =IF(RegisterPush!B5="","",RegisterPush!F5) -> Negative | G5: =IF(RegisterPush!B5="","",RegisterPush!G5) -> 4 | H5: =IF(RegisterPush!B5="","",RegisterPush!H5) -> 4 | I5: =IF(RegisterPush!B5="","",RegisterPush!I5) -> 0.68 | J5: =IF(RegisterPush!B5="","",RegisterPush!J5) -> CIOS→MIOS+OHOS | K5: =IF(RegisterPush!B5="","",RegisterPush!K5) -> Pulmonology / community | L5: =IF(B5="","",IF(RegisterPush!L5<>"",RegisterPush!L5,IF(OR(J5="CIOS→MIOS",J5="CIOS→MIOS+OHOS"),"Yes","No"))) -> Yes | M5: =IF(B5="","",IF(RegisterPush!M5<>"",RegisterPush!M5,IF(OR(J5="CIOS→OHOS",J5="CIOS→MIOS+OHOS"),"Yes","No"))) -> Yes | N5: =IF(B5="","",G5*H5) -> 16 | O5: =IF(B5="","",ActorReactionMatrix!M5) -> -0.67531251 | P5: =IF(B5="",1,IF(I5="",1,I5)) -> 0.68 | Q5: =IF(B5="","",ABS(O5)) -> 0.67531251
A6: =IF(RegisterPush!B6="","",IF(RegisterPush!A6<>"",RegisterPush!A6,RegisterPush!B6)) -> CS-003 | B6: =IF(RegisterPush!B6="","",RegisterPush!B6) -> CS-003 | C6: =IF(RegisterPush!B6="","",RegisterPush!C6) -> ARIKAYCE | D6: =IF(RegisterPush!B6="","",RegisterPush!D6) -> Emerging coverage shift could reduce reimbursement obstacles in target accounts. | E6: =IF(RegisterPush!B6="","",RegisterPush!E6) -> Access / commercial | F6: =IF(RegisterPush!B6="","",RegisterPush!F6) -> Positive | G6: =IF(RegisterPush!B6="","",RegisterPush!G6) -> 5 | H6: =IF(RegisterPush!B6="","",RegisterPush!H6) -> 4 | I6: =IF(RegisterPush!B6="","",RegisterPush!I6) -> 1.4 | J6: =IF(RegisterPush!B6="","",RegisterPush!J6) -> CIOS→OHOS | K6: =IF(RegisterPush!B6="","",RegisterPush!K6) -> Pulmonology / general | L6: =IF(B6="","",IF(RegisterPush!L6<>"",RegisterPush!L6,IF(OR(J6="CIOS→MIOS",J6="CIOS→MIOS+OHOS"),"Yes","No"))) -> No | M6: =IF(B6="","",IF(RegisterPush!M6<>"",RegisterPush!M6,IF(OR(J6="CIOS→OHOS",J6="CIOS→MIOS+OHOS"),"Yes","No"))) -> Yes | N6: =IF(B6="","",G6*H6) -> 20 | O6: =IF(B6="","",ActorReactionMatrix!M6) -> 0.67820157 | P6: =IF(B6="",1,IF(I6="",1,I6)) -> 1.4 | Q6: =IF(B6="","",ABS(O6)) -> 0.67820157
A7: =IF(RegisterPush!B7="","",IF(RegisterPush!A7<>"",RegisterPush!A7,RegisterPush!B7)) -> 0 | B7: =IF(RegisterPush!B7="","",RegisterPush!B7) -> 0 | C7: =IF(RegisterPush!B7="","",RegisterPush!C7) -> 0 | D7: =IF(RegisterPush!B7="","",RegisterPush!D7) | E7: =IF(RegisterPush!B7="","",RegisterPush!E7) | F7: =IF(RegisterPush!B7="","",RegisterPush!F7) | G7: =IF(RegisterPush!B7="","",RegisterPush!G7) | H7: =IF(RegisterPush!B7="","",RegisterPush!H7) | I7: =IF(RegisterPush!B7="","",RegisterPush!I7) | J7: =IF(RegisterPush!B7="","",RegisterPush!J7) | K7: =IF(RegisterPush!B7="","",RegisterPush!K7) | L7: =IF(B7="","",IF(RegisterPush!L7<>"",RegisterPush!L7,IF(OR(J7="CIOS→MIOS",J7="CIOS→MIOS+OHOS"),"Yes","No"))) -> No | M7: =IF(B7="","",IF(RegisterPush!M7<>"",RegisterPush!M7,IF(OR(J7="CIOS→OHOS",J7="CIOS→MIOS+OHOS"),"Yes","No"))) -> No | N7: =IF(B7="","",G7*H7) -> #VALUE! | O7: =IF(B7="","",ActorReactionMatrix!M7) -> 0 | P7: =IF(B7="",1,IF(I7="",1,I7)) -> 1 | Q7: =IF(B7="","",ABS(O7)) -> 0
A8: =IF(RegisterPush!B8="","",IF(RegisterPush!A8<>"",RegisterPush!A8,RegisterPush!B8)) -> 0 | B8: =IF(RegisterPush!B8="","",RegisterPush!B8) -> 0 | C8: =IF(RegisterPush!B8="","",RegisterPush!C8) -> 0 | D8: =IF(RegisterPush!B8="","",RegisterPush!D8) | E8: =IF(RegisterPush!B8="","",RegisterPush!E8) | F8: =IF(RegisterPush!B8="","",RegisterPush!F8) | G8: =IF(RegisterPush!B8="","",RegisterPush!G8) | H8: =IF(RegisterPush!B8="","",RegisterPush!H8) | I8: =IF(RegisterPush!B8="","",RegisterPush!I8) | J8: =IF(RegisterPush!B8="","",RegisterPush!J8) | K8: =IF(RegisterPush!B8="","",RegisterPush!K8) | L8: =IF(B8="","",IF(RegisterPush!L8<>"",RegisterPush!L8,IF(OR(J8="CIOS→MIOS",J8="CIOS→MIOS+OHOS"),"Yes","No"))) -> No | M8: =IF(B8="","",IF(RegisterPush!M8<>"",RegisterPush!M8,IF(OR(J8="CIOS→OHOS",J8="CIOS→MIOS+OHOS"),"Yes","No"))) -> No | N8: =IF(B8="","",G8*H8) -> #VALUE! | O8: =IF(B8="","",ActorReactionMatrix!M8) -> 0 | P8: =IF(B8="",1,IF(I8="",1,I8)) -> 1 | Q8: =IF(B8="","",ABS(O8)) -> 0
A9: =IF(RegisterPush!B9="","",IF(RegisterPush!A9<>"",RegisterPush!A9,RegisterPush!B9)) -> 0 | B9: =IF(RegisterPush!B9="","",RegisterPush!B9) -> 0 | C9: =IF(RegisterPush!B9="","",RegisterPush!C9) -> 0 | D9: =IF(RegisterPush!B9="","",RegisterPush!D9) | E9: =IF(RegisterPush!B9="","",RegisterPush!E9) | F9: =IF(RegisterPush!B9="","",RegisterPush!F9) | G9: =IF(RegisterPush!B9="","",RegisterPush!G9) | H9: =IF(RegisterPush!B9="","",RegisterPush!H9) | I9: =IF(RegisterPush!B9="","",RegisterPush!I9) | J9: =IF(RegisterPush!B9="","",RegisterPush!J9) | K9: =IF(RegisterPush!B9="","",RegisterPush!K9) | L9: =IF(B9="","",IF(RegisterPush!L9<>"",RegisterPush!L9,IF(OR(J9="CIOS→MIOS",J9="CIOS→MIOS+OHOS"),"Yes","No"))) -> No | M9: =IF(B9="","",IF(RegisterPush!M9<>"",RegisterPush!M9,IF(OR(J9="CIOS→OHOS",J9="CIOS→MIOS+OHOS"),"Yes","No"))) -> No | N9: =IF(B9="","",G9*H9) -> #VALUE! | O9: =IF(B9="","",ActorReactionMatrix!M9) -> 0 | P9: =IF(B9="",1,IF(I9="",1,I9)) -> 1 | Q9: =IF(B9="","",ABS(O9)) -> 0
A10: =IF(RegisterPush!B10="","",IF(RegisterPush!A10<>"",RegisterPush!A10,RegisterPush!B10)) -> 0 | B10: =IF(RegisterPush!B10="","",RegisterPush!B10) -> 0 | C10: =IF(RegisterPush!B10="","",RegisterPush!C10) -> 0 | D10: =IF(RegisterPush!B10="","",RegisterPush!D10) | E10: =IF(RegisterPush!B10="","",RegisterPush!E10) | F10: =IF(RegisterPush!B10="","",RegisterPush!F10) | G10: =IF(RegisterPush!B10="","",RegisterPush!G10) | H10: =IF(RegisterPush!B10="","",RegisterPush!H10) | I10: =IF(RegisterPush!B10="","",RegisterPush!I10) | J10: =IF(RegisterPush!B10="","",RegisterPush!J10) | K10: =IF(RegisterPush!B10="","",RegisterPush!K10) | L10: =IF(B10="","",IF(RegisterPush!L10<>"",RegisterPush!L10,IF(OR(J10="CIOS→MIOS",J10="CIOS→MIOS+OHOS"),"Yes","No"))) -> No | M10: =IF(B10="","",IF(RegisterPush!M10<>"",RegisterPush!M10,IF(OR(J10="CIOS→OHOS",J10="CIOS→MIOS+OHOS"),"Yes","No"))) -> No | N10: =IF(B10="","",G10*H10) -> #VALUE! | O10: =IF(B10="","",ActorReactionMatrix!M10) -> 0 | P10: =IF(B10="",1,IF(I10="",1,I10)) -> 1 | Q10: =IF(B10="","",ABS(O10)) -> 0
A11: =IF(RegisterPush!B11="","",IF(RegisterPush!A11<>"",RegisterPush!A11,RegisterPush!B11)) -> 0 | B11: =IF(RegisterPush!B11="","",RegisterPush!B11) -> 0 | C11: =IF(RegisterPush!B11="","",RegisterPush!C11) -> 0 | D11: =IF(RegisterPush!B11="","",RegisterPush!D11) | E11: =IF(RegisterPush!B11="","",RegisterPush!E11) | F11: =IF(RegisterPush!B11="","",RegisterPush!F11) | G11: =IF(RegisterPush!B11="","",RegisterPush!G11) | H11: =IF(RegisterPush!B11="","",RegisterPush!H11) | I11: =IF(RegisterPush!B11="","",RegisterPush!I11) | J11: =IF(RegisterPush!B11="","",RegisterPush!J11) | K11: =IF(RegisterPush!B11="","",RegisterPush!K11) | L11: =IF(B11="","",IF(RegisterPush!L11<>"",RegisterPush!L11,IF(OR(J11="CIOS→MIOS",J11="CIOS→MIOS+OHOS"),"Yes","No"))) -> No | M11: =IF(B11="","",IF(RegisterPush!M11<>"",RegisterPush!M11,IF(OR(J11="CIOS→OHOS",J11="CIOS→MIOS+OHOS"),"Yes","No"))) -> No | N11: =IF(B11="","",G11*H11) -> #VALUE! | O11: =IF(B11="","",ActorReactionMatrix!M11) -> 0 | P11: =IF(B11="",1,IF(I11="",1,I11)) -> 1 | Q11: =IF(B11="","",ABS(O11)) -> 0
A12: =IF(RegisterPush!B12="","",IF(RegisterPush!A12<>"",RegisterPush!A12,RegisterPush!B12)) -> 0 | B12: =IF(RegisterPush!B12="","",RegisterPush!B12) -> 0 | C12: =IF(RegisterPush!B12="","",RegisterPush!C12) -> 0 | D12: =IF(RegisterPush!B12="","",RegisterPush!D12) | E12: =IF(RegisterPush!B12="","",RegisterPush!E12) | F12: =IF(RegisterPush!B12="","",RegisterPush!F12) | G12: =IF(RegisterPush!B12="","",RegisterPush!G12) | H12: =IF(RegisterPush!B12="","",RegisterPush!H12) | I12: =IF(RegisterPush!B12="","",RegisterPush!I12) | J12: =IF(RegisterPush!B12="","",RegisterPush!J12) | K12: =IF(RegisterPush!B12="","",RegisterPush!K12) | L12: =IF(B12="","",IF(RegisterPush!L12<>"",RegisterPush!L12,IF(OR(J12="CIOS→MIOS",J12="CIOS→MIOS+OHOS"),"Yes","No"))) -> No | M12: =IF(B12="","",IF(RegisterPush!M12<>"",RegisterPush!M12,IF(OR(J12="CIOS→OHOS",J12="CIOS→MIOS+OHOS"),"Yes","No"))) -> No | N12: =IF(B12="","",G12*H12) -> #VALUE! | O12: =IF(B12="","",ActorReactionMatrix!M12) -> 0 | P12: =IF(B12="",1,IF(I12="",1,I12)) -> 1 | Q12: =IF(B12="","",ABS(O12)) -> 0
A13: =IF(RegisterPush!B13="","",IF(RegisterPush!A13<>"",RegisterPush!A13,RegisterPush!B13)) -> 0 | B13: =IF(RegisterPush!B13="","",RegisterPush!B13) -> 0 | C13: =IF(RegisterPush!B13="","",RegisterPush!C13) -> 0 | D13: =IF(RegisterPush!B13="","",RegisterPush!D13) | E13: =IF(RegisterPush!B13="","",RegisterPush!E13) | F13: =IF(RegisterPush!B13="","",RegisterPush!F13) | G13: =IF(RegisterPush!B13="","",RegisterPush!G13) | H13: =IF(RegisterPush!B13="","",RegisterPush!H13) | I13: =IF(RegisterPush!B13="","",RegisterPush!I13) | J13: =IF(RegisterPush!B13="","",RegisterPush!J13) | K13: =IF(RegisterPush!B13="","",RegisterPush!K13) | L13: =IF(B13="","",IF(RegisterPush!L13<>"",RegisterPush!L13,IF(OR(J13="CIOS→MIOS",J13="CIOS→MIOS+OHOS"),"Yes","No"))) -> No | M13: =IF(B13="","",IF(RegisterPush!M13<>"",RegisterPush!M13,IF(OR(J13="CIOS→OHOS",J13="CIOS→MIOS+OHOS"),"Yes","No"))) -> No | N13: =IF(B13="","",G13*H13) -> #VALUE! | O13: =IF(B13="","",ActorReactionMatrix!M13) -> 0 | P13: =IF(B13="",1,IF(I13="",1,I13)) -> 1 | Q13: =IF(B13="","",ABS(O13)) -> 0
A14: =IF(RegisterPush!B14="","",IF(RegisterPush!A14<>"",RegisterPush!A14,RegisterPush!B14)) | B14: =IF(RegisterPush!B14="","",RegisterPush!B14) | C14: =IF(RegisterPush!B14="","",RegisterPush!C14) | D14: =IF(RegisterPush!B14="","",RegisterPush!D14) | E14: =IF(RegisterPush!B14="","",RegisterPush!E14) | F14: =IF(RegisterPush!B14="","",RegisterPush!F14) | G14: =IF(RegisterPush!B14="","",RegisterPush!G14) | H14: =IF(RegisterPush!B14="","",RegisterPush!H14) | I14: =IF(RegisterPush!B14="","",RegisterPush!I14) | J14: =IF(RegisterPush!B14="","",RegisterPush!J14) | K14: =IF(RegisterPush!B14="","",RegisterPush!K14) | L14: =IF(B14="","",IF(RegisterPush!L14<>"",RegisterPush!L14,IF(OR(J14="CIOS→MIOS",J14="CIOS→MIOS+OHOS"),"Yes","No"))) | M14: =IF(B14="","",IF(RegisterPush!M14<>"",RegisterPush!M14,IF(OR(J14="CIOS→OHOS",J14="CIOS→MIOS+OHOS"),"Yes","No"))) | N14: =IF(B14="","",G14*H14) | O14: =IF(B14="","",ActorReactionMatrix!M14) | P14: =IF(B14="",1,IF(I14="",1,I14)) -> 1 | Q14: =IF(B14="","",ABS(O14))
A15: =IF(RegisterPush!B15="","",IF(RegisterPush!A15<>"",RegisterPush!A15,RegisterPush!B15)) | B15: =IF(RegisterPush!B15="","",RegisterPush!B15) | C15: =IF(RegisterPush!B15="","",RegisterPush!C15) | D15: =IF(RegisterPush!B15="","",RegisterPush!D15) | E15: =IF(RegisterPush!B15="","",RegisterPush!E15) | F15: =IF(RegisterPush!B15="","",RegisterPush!F15) | G15: =IF(RegisterPush!B15="","",RegisterPush!G15) | H15: =IF(RegisterPush!B15="","",RegisterPush!H15) | I15: =IF(RegisterPush!B15="","",RegisterPush!I15) | J15: =IF(RegisterPush!B15="","",RegisterPush!J15) | K15: =IF(RegisterPush!B15="","",RegisterPush!K15) | L15: =IF(B15="","",IF(RegisterPush!L15<>"",RegisterPush!L15,IF(OR(J15="CIOS→MIOS",J15="CIOS→MIOS+OHOS"),"Yes","No"))) | M15: =IF(B15="","",IF(RegisterPush!M15<>"",RegisterPush!M15,IF(OR(J15="CIOS→OHOS",J15="CIOS→MIOS+OHOS"),"Yes","No"))) | N15: =IF(B15="","",G15*H15) | O15: =IF(B15="","",ActorReactionMatrix!M15) | P15: =IF(B15="",1,IF(I15="",1,I15)) -> 1 | Q15: =IF(B15="","",ABS(O15))
... A33: =IF(RegisterPush!B33="","",IF(RegisterPush!A33<>"",RegisterPush!A33,RegisterPush!B33)) | B33: =IF(RegisterPush!B33="","",RegisterPush!B33) | C33: =IF(RegisterPush!B33="","",RegisterPush!C33) | D33: =IF(RegisterPush!B33="","",RegisterPush!D33) | E33: =IF(RegisterPush!B33="","",RegisterPush!E33) | F33: =IF(RegisterPush!B33="","",RegisterPush!F33) | G33: =IF(RegisterPush!B33="","",RegisterPush!G33) | H33: =IF(RegisterPush!B33="","",RegisterPush!H33) | I33: =IF(RegisterPush!B33="","",RegisterPush!I33) | J33: =IF(RegisterPush!B33="","",RegisterPush!J33) | K33: =IF(RegisterPush!B33="","",RegisterPush!K33) | L33: =IF(B33="","",IF(RegisterPush!L33<>"",RegisterPush!L33,IF(OR(J33="CIOS→MIOS",J33="CIOS→MIOS+OHOS"),"Yes","No"))) | M33: =IF(B33="","",IF(RegisterPush!M33<>"",RegisterPush!M33,IF(OR(J33="CIOS→OHOS",J33="CIOS→MIOS+OHOS"),"Yes","No"))) | N33: =IF(B33="","",G33*H33) | O33: =IF(B33="","",ActorReactionMatrix!M33) | P33: =IF(B33="",1,IF(I33="",1,I33)) -> 1 | Q33: =IF(B33="","",ABS(O33))

Sheet Actors
A1: CIOS V19 Actor Configuration
A3: Actor | B3: InfluenceWeight | C3: PositiveResponseFactor | D3: NegativeResponseFactor | E3: OutcomeOrientation | F3: RoleInSystem | G3: BaseInfluenceWeight | H3: SpecialtyModifier | I3: PayerModifier | J3: GuidelineModifier | K3: CompetitorModifier | L3: RawWeight | O3: BasePositiveResponseFactor | P3: BaseNegativeResponseFactor | Q3: CanonicalActor
A4: =IFERROR(INDEX(SpecialtyActorSets!$C$4:$C$45,MATCH(1,(SpecialtyActorSets!$A$4:$A$45=CaseHeader!$B$16)*(SpecialtyActorSets!$B$4:$B$45=1),0)),"") -> Academic KOLs | B4: =IFERROR(L4/SUM($L$4:$L$9),G4) -> 0.20368574 | C4: =O4*(1+IF(AND($Q4="Guideline Bodies",CaseHeader!$B$18="High"),0.1,IF(AND($Q4="Guideline Bodies",CaseHeader!$B$18="Low"),-0.1,0)))*(1+IF(AND($Q4="Payers / Access",CaseHeader!$B$17="Commercial-heavy"),0.06,IF(AND($Q4="Payers / Access",CaseHeader!$B$17="Medicaid-heavy"),-0.03,0)))*(1+IF(AND($Q4="Community Physicians",CaseHeader!$B$19="Entrenched standard of care"),-0.05,0))*(1+IF(AND($Q4="Competitor Counteraction",OR(CaseHeader!$B$19="Aggressive branded competitor",CaseHeader!$B$19="Crowded class / multiple competitors")),0.08,0)) -> 1.15 | D4: =P4*(1+IF(AND($Q4="Guideline Bodies",CaseHeader!$B$18="High"),-0.05,IF(AND($Q4="Guideline Bodies",CaseHeader!$B$18="Low"),0.05,0)))*(1+IF(AND($Q4="Payers / Access",CaseHeader!$B$17="Medicaid-heavy"),0.06,IF(AND($Q4="Payers / Access",CaseHeader!$B$17="Commercial-heavy"),0.03,0)))*(1+IF(AND($Q4="Community Physicians",CaseHeader!$B$19="Entrenched standard of care"),0.08,0))*(1+IF(AND($Q4="Competitor Counteraction",OR(CaseHeader!$B$19="Aggressive branded competitor",CaseHeader!$B$19="Crowded class / multiple competitors")),0.1,IF(AND($Q4="Competitor Counteraction",CaseHeader!$B$19="Whitespace / limited direct competition"),-0.08,0))) -> 0.88 | E4: =IFERROR(INDEX(SpecialtyActorSets!$I$4:$I$45,MATCH(1,(SpecialtyActorSets!$A$4:$A$45=CaseHeader!$B$16)*(SpecialtyActorSets!$B$4:$B$45=1),0)),1) -> 1 | F4: =IFERROR(INDEX(SpecialtyActorSets!$E$4:$E$45,MATCH(1,(SpecialtyActorSets!$A$4:$A$45=CaseHeader!$B$16)*(SpecialtyActorSets!$B$4:$B$45=1),0)),"") -> Cross-specialty scientific validators and early adopters. | G4: =IFERROR(INDEX(SpecialtyActorSets!$F$4:$F$45,MATCH(1,(SpecialtyActorSets!$A$4:$A$45=CaseHeader!$B$16)*(SpecialtyActorSets!$B$4:$B$45=1),0)),0) -> 0.2 | H4: =IFERROR(INDEX(PharmaLogic!$B$4:$G$10,MATCH(CaseHeader!$B$16,PharmaLogic!$A$4:$A$10,0),MATCH($Q4,PharmaLogic!$B$3:$G$3,0)),1) -> 1 | I4: =IFERROR(INDEX(PharmaLogic!$B$15:$G$19,MATCH(CaseHeader!$B$17,PharmaLogic!$A$15:$A$19,0),MATCH($Q4,PharmaLogic!$B$14:$G$14,0)),1) -> 1 | J4: =IFERROR(INDEX(PharmaLogic!$B$24:$G$26,MATCH(CaseHeader!$B$18,PharmaLogic!$A$24:$A$26,0),MATCH($Q4,PharmaLogic!$B$23:$G$23,0)),1) -> 1 | K4: =IFERROR(INDEX(PharmaLogic!$B$31:$G$35,MATCH(CaseHeader!$B$19,PharmaLogic!$A$31:$A$35,0),MATCH($Q4,PharmaLogic!$B$30:$G$30,0)),1) -> 1.05 | L4: =G4*H4*I4*J4*K4 -> 0.21 | O4: =IFERROR(INDEX(SpecialtyActorSets!$G$4:$G$45,MATCH(1,(SpecialtyActorSets!$A$4:$A$45=CaseHeader!$B$16)*(SpecialtyActorSets!$B$4:$B$45=1),0)),1) -> 1.15 | P4: =IFERROR(INDEX(SpecialtyActorSets!$H$4:$H$45,MATCH(1,(SpecialtyActorSets!$A$4:$A$45=CaseHeader!$B$16)*(SpecialtyActorSets!$B$4:$B$45=1),0)),1) -> 0.88 | Q4: =IFERROR(INDEX(SpecialtyActorSets!$D$4:$D$45,MATCH(1,(SpecialtyActorSets!$A$4:$A$45=CaseHeader!$B$16)*(SpecialtyActorSets!$B$4:$B$45=1),0)),"") -> Academic KOLs
A5: =IFERROR(INDEX(SpecialtyActorSets!$C$4:$C$45,MATCH(1,(SpecialtyActorSets!$A$4:$A$45=CaseHeader!$B$16)*(SpecialtyActorSets!$B$4:$B$45=2),0)),"") -> Community Physicians | B5: =IFERROR(L5/SUM($L$4:$L$9),G5) -> 0.22114452 | C5: =O5*(1+IF(AND($Q5="Guideline Bodies",CaseHeader!$B$18="High"),0.1,IF(AND($Q5="Guideline Bodies",CaseHeader!$B$18="Low"),-0.1,0)))*(1+IF(AND($Q5="Payers / Access",CaseHeader!$B$17="Commercial-heavy"),0.06,IF(AND($Q5="Payers / Access",CaseHeader!$B$17="Medicaid-heavy"),-0.03,0)))*(1+IF(AND($Q5="Community Physicians",CaseHeader!$B$19="Entrenched standard of care"),-0.05,0))*(1+IF(AND($Q5="Competitor Counteraction",OR(CaseHeader!$B$19="Aggressive branded competitor",CaseHeader!$B$19="Crowded class / multiple competitors")),0.08,0)) -> 0.9025 | D5: =P5*(1+IF(AND($Q5="Guideline Bodies",CaseHeader!$B$18="High"),-0.05,IF(AND($Q5="Guideline Bodies",CaseHeader!$B$18="Low"),0.05,0)))*(1+IF(AND($Q5="Payers / Access",CaseHeader!$B$17="Medicaid-heavy"),0.06,IF(AND($Q5="Payers / Access",CaseHeader!$B$17="Commercial-heavy"),0.03,0)))*(1+IF(AND($Q5="Community Physicians",CaseHeader!$B$19="Entrenched standard of care"),0.08,0))*(1+IF(AND($Q5="Competitor Counteraction",OR(CaseHeader!$B$19="Aggressive branded competitor",CaseHeader!$B$19="Crowded class / multiple competitors")),0.1,IF(AND($Q5="Competitor Counteraction",CaseHeader!$B$19="Whitespace / limited direct competition"),-0.08,0))) -> 1.188 | E5: =IFERROR(INDEX(SpecialtyActorSets!$I$4:$I$45,MATCH(1,(SpecialtyActorSets!$A$4:$A$45=CaseHeader!$B$16)*(SpecialtyActorSets!$B$4:$B$45=2),0)),1) -> 1 | F5: =IFERROR(INDEX(SpecialtyActorSets!$E$4:$E$45,MATCH(1,(SpecialtyActorSets!$A$4:$A$45=CaseHeader!$B$16)*(SpecialtyActorSets!$B$4:$B$45=2),0)),"") -> Broad treating base whose behavior determines real-world conversion. | G5: =IFERROR(INDEX(SpecialtyActorSets!$F$4:$F$45,MATCH(1,(SpecialtyActorSets!$A$4:$A$45=CaseHeader!$B$16)*(SpecialtyActorSets!$B$4:$B$45=2),0)),0) -> 0.24 | H5: =IFERROR(INDEX(PharmaLogic!$B$4:$G$10,MATCH(CaseHeader!$B$16,PharmaLogic!$A$4:$A$10,0),MATCH($Q5,PharmaLogic!$B$3:$G$3,0)),1) -> 1 | I5: =IFERROR(INDEX(PharmaLogic!$B$15:$G$19,MATCH(CaseHeader!$B$17,PharmaLogic!$A$15:$A$19,0),MATCH($Q5,PharmaLogic!$B$14:$G$14,0)),1) -> 1 | J5: =IFERROR(INDEX(PharmaLogic!$B$24:$G$26,MATCH(CaseHeader!$B$18,PharmaLogic!$A$24:$A$26,0),MATCH($Q5,PharmaLogic!$B$23:$G$23,0)),1) -> 1 | K5: =IFERROR(INDEX(PharmaLogic!$B$31:$G$35,MATCH(CaseHeader!$B$19,PharmaLogic!$A$31:$A$35,0),MATCH($Q5,PharmaLogic!$B$30:$G$30,0)),1) -> 0.95 | L5: =G5*H5*I5*J5*K5 -> 0.228 | O5: =IFERROR(INDEX(SpecialtyActorSets!$G$4:$G$45,MATCH(1,(SpecialtyActorSets!$A$4:$A$45=CaseHeader!$B$16)*(SpecialtyActorSets!$B$4:$B$45=2),0)),1) -> 0.95 | P5: =IFERROR(INDEX(SpecialtyActorSets!$H$4:$H$45,MATCH(1,(SpecialtyActorSets!$A$4:$A$45=CaseHeader!$B$16)*(SpecialtyActorSets!$B$4:$B$45=2),0)),1) -> 1.1 | Q5: =IFERROR(INDEX(SpecialtyActorSets!$D$4:$D$45,MATCH(1,(SpecialtyActorSets!$A$4:$A$45=CaseHeader!$B$16)*(SpecialtyActorSets!$B$4:$B$45=2),0)),"") -> Community Physicians
A6: =IFERROR(INDEX(SpecialtyActorSets!$C$4:$C$45,MATCH(1,(SpecialtyActorSets!$A$4:$A$45=CaseHeader!$B$16)*(SpecialtyActorSets!$B$4:$B$45=3),0)),"") -> Specialty Extenders / PCPs | B6: =IFERROR(L6/SUM($L$4:$L$9),G6) -> 0.11639185 | C6: =O6*(1+IF(AND($Q6="Guideline Bodies",CaseHeader!$B$18="High"),0.1,IF(AND($Q6="Guideline Bodies",CaseHeader!$B$18="Low"),-0.1,0)))*(1+IF(AND($Q6="Payers / Access",CaseHeader!$B$17="Commercial-heavy"),0.06,IF(AND($Q6="Payers / Access",CaseHeader!$B$17="Medicaid-heavy"),-0.03,0)))*(1+IF(AND($Q6="Community Physicians",CaseHeader!$B$19="Entrenched standard of care"),-0.05,0))*(1+IF(AND($Q6="Competitor Counteraction",OR(CaseHeader!$B$19="Aggressive branded competitor",CaseHeader!$B$19="Crowded class / multiple competitors")),0.08,0)) -> 0.85 | D6: =P6*(1+IF(AND($Q6="Guideline Bodies",CaseHeader!$B$18="High"),-0.05,IF(AND($Q6="Guideline Bodies",CaseHeader!$B$18="Low"),0.05,0)))*(1+IF(AND($Q6="Payers / Access",CaseHeader!$B$17="Medicaid-heavy"),0.06,IF(AND($Q6="Payers / Access",CaseHeader!$B$17="Commercial-heavy"),0.03,0)))*(1+IF(AND($Q6="Community Physicians",CaseHeader!$B$19="Entrenched standard of care"),0.08,0))*(1+IF(AND($Q6="Competitor Counteraction",OR(CaseHeader!$B$19="Aggressive branded competitor",CaseHeader!$B$19="Crowded class / multiple competitors")),0.1,IF(AND($Q6="Competitor Counteraction",CaseHeader!$B$19="Whitespace / limited direct competition"),-0.08,0))) -> 1.05 | E6: =IFERROR(INDEX(SpecialtyActorSets!$I$4:$I$45,MATCH(1,(SpecialtyActorSets!$A$4:$A$45=CaseHeader!$B$16)*(SpecialtyActorSets!$B$4:$B$45=3),0)),1) -> 1 | F6: =IFERROR(INDEX(SpecialtyActorSets!$E$4:$E$45,MATCH(1,(SpecialtyActorSets!$A$4:$A$45=CaseHeader!$B$16)*(SpecialtyActorSets!$B$4:$B$45=3),0)),"") -> Secondary prescribers or extenders who amplify practical uptake. | G6: =IFERROR(INDEX(SpecialtyActorSets!$F$4:$F$45,MATCH(1,(SpecialtyActorSets!$A$4:$A$45=CaseHeader!$B$16)*(SpecialtyActorSets!$B$4:$B$45=3),0)),0) -> 0.12 | H6: =IFERROR(INDEX(PharmaLogic!$B$4:$G$10,MATCH(CaseHeader!$B$16,PharmaLogic!$A$4:$A$10,0),MATCH($Q6,PharmaLogic!$B$3:$G$3,0)),1) -> 1 | I6: =IFERROR(INDEX(PharmaLogic!$B$15:$G$19,MATCH(CaseHeader!$B$17,PharmaLogic!$A$15:$A$19,0),MATCH($Q6,PharmaLogic!$B$14:$G$14,0)),1) -> 1 | J6: =IFERROR(INDEX(PharmaLogic!$B$24:$G$26,MATCH(CaseHeader!$B$18,PharmaLogic!$A$24:$A$26,0),MATCH($Q6,PharmaLogic!$B$23:$G$23,0)),1) -> 1 | K6: =IFERROR(INDEX(PharmaLogic!$B$31:$G$35,MATCH(CaseHeader!$B$19,PharmaLogic!$A$31:$A$35,0),MATCH($Q6,PharmaLogic!$B$30:$G$30,0)),1) -> 1 | L6: =G6*H6*I6*J6*K6 -> 0.12 | O6: =IFERROR(INDEX(SpecialtyActorSets!$G$4:$G$45,MATCH(1,(SpecialtyActorSets!$A$4:$A$45=CaseHeader!$B$16)*(SpecialtyActorSets!$B$4:$B$45=3),0)),1) -> 0.85 | P6: =IFERROR(INDEX(SpecialtyActorSets!$H$4:$H$45,MATCH(1,(SpecialtyActorSets!$A$4:$A$45=CaseHeader!$B$16)*(SpecialtyActorSets!$B$4:$B$45=3),0)),1) -> 1.05 | Q6: =IFERROR(INDEX(SpecialtyActorSets!$D$4:$D$45,MATCH(1,(SpecialtyActorSets!$A$4:$A$45=CaseHeader!$B$16)*(SpecialtyActorSets!$B$4:$B$45=3),0)),"") -> Health Systems
A7: =IFERROR(INDEX(SpecialtyActorSets!$C$4:$C$45,MATCH(1,(SpecialtyActorSets!$A$4:$A$45=CaseHeader!$B$16)*(SpecialtyActorSets!$B$4:$B$45=4),0)),"") -> Payers / Access | B7: =IFERROR(L7/SUM($L$4:$L$9),G7) -> 0.18331717 | C7: =O7*(1+IF(AND($Q7="Guideline Bodies",CaseHeader!$B$18="High"),0.1,IF(AND($Q7="Guideline Bodies",CaseHeader!$B$18="Low"),-0.1,0)))*(1+IF(AND($Q7="Payers / Access",CaseHeader!$B$17="Commercial-heavy"),0.06,IF(AND($Q7="Payers / Access",CaseHeader!$B$17="Medicaid-heavy"),-0.03,0)))*(1+IF(AND($Q7="Community Physicians",CaseHeader!$B$19="Entrenched standard of care"),-0.05,0))*(1+IF(AND($Q7="Competitor Counteraction",OR(CaseHeader!$B$19="Aggressive branded competitor",CaseHeader!$B$19="Crowded class / multiple competitors")),0.08,0)) -> 0.8 | D7: =P7*(1+IF(AND($Q7="Guideline Bodies",CaseHeader!$B$18="High"),-0.05,IF(AND($Q7="Guideline Bodies",CaseHeader!$B$18="Low"),0.05,0)))*(1+IF(AND($Q7="Payers / Access",CaseHeader!$B$17="Medicaid-heavy"),0.06,IF(AND($Q7="Payers / Access",CaseHeader!$B$17="Commercial-heavy"),0.03,0)))*(1+IF(AND($Q7="Community Physicians",CaseHeader!$B$19="Entrenched standard of care"),0.08,0))*(1+IF(AND($Q7="Competitor Counteraction",OR(CaseHeader!$B$19="Aggressive branded competitor",CaseHeader!$B$19="Crowded class / multiple competitors")),0.1,IF(AND($Q7="Competitor Counteraction",CaseHeader!$B$19="Whitespace / limited direct competition"),-0.08,0))) -> 1.2 | E7: =IFERROR(INDEX(SpecialtyActorSets!$I$4:$I$45,MATCH(1,(SpecialtyActorSets!$A$4:$A$45=CaseHeader!$B$16)*(SpecialtyActorSets!$B$4:$B$45=4),0)),1) -> 1 | F7: =IFERROR(INDEX(SpecialtyActorSets!$E$4:$E$45,MATCH(1,(SpecialtyActorSets!$A$4:$A$45=CaseHeader!$B$16)*(SpecialtyActorSets!$B$4:$B$45=4),0)),"") -> Coverage and reimbursement gatekeepers. | G7: =IFERROR(INDEX(SpecialtyActorSets!$F$4:$F$45,MATCH(1,(SpecialtyActorSets!$A$4:$A$45=CaseHeader!$B$16)*(SpecialtyActorSets!$B$4:$B$45=4),0)),0) -> 0.18 | H7: =IFERROR(INDEX(PharmaLogic!$B$4:$G$10,MATCH(CaseHeader!$B$16,PharmaLogic!$A$4:$A$10,0),MATCH($Q7,PharmaLogic!$B$3:$G$3,0)),1) -> 1 | I7: =IFERROR(INDEX(PharmaLogic!$B$15:$G$19,MATCH(CaseHeader!$B$17,PharmaLogic!$A$15:$A$19,0),MATCH($Q7,PharmaLogic!$B$14:$G$14,0)),1) -> 1 | J7: =IFERROR(INDEX(PharmaLogic!$B$24:$G$26,MATCH(CaseHeader!$B$18,PharmaLogic!$A$24:$A$26,0),MATCH($Q7,PharmaLogic!$B$23:$G$23,0)),1) -> 1 | K7: =IFERROR(INDEX(PharmaLogic!$B$31:$G$35,MATCH(CaseHeader!$B$19,PharmaLogic!$A$31:$A$35,0),MATCH($Q7,PharmaLogic!$B$30:$G$30,0)),1) -> 1.05 | L7: =G7*H7*I7*J7*K7 -> 0.189 | O7: =IFERROR(INDEX(SpecialtyActorSets!$G$4:$G$45,MATCH(1,(SpecialtyActorSets!$A$4:$A$45=CaseHeader!$B$16)*(SpecialtyActorSets!$B$4:$B$45=4),0)),1) -> 0.8 | P7: =IFERROR(INDEX(SpecialtyActorSets!$H$4:$H$45,MATCH(1,(SpecialtyActorSets!$A$4:$A$45=CaseHeader!$B$16)*(SpecialtyActorSets!$B$4:$B$45=4),0)),1) -> 1.2 | Q7: =IFERROR(INDEX(SpecialtyActorSets!$D$4:$D$45,MATCH(1,(SpecialtyActorSets!$A$4:$A$45=CaseHeader!$B$16)*(SpecialtyActorSets!$B$4:$B$45=4),0)),"") -> Payers / Access
A8: =IFERROR(INDEX(SpecialtyActorSets!$C$4:$C$45,MATCH(1,(SpecialtyActorSets!$A$4:$A$45=CaseHeader!$B$16)*(SpecialtyActorSets!$B$4:$B$45=5),0)),"") -> Guideline / Society Bodies | B8: =IFERROR(L8/SUM($L$4:$L$9),G8) -> 0.13579049 | C8: =O8*(1+IF(AND($Q8="Guideline Bodies",CaseHeader!$B$18="High"),0.1,IF(AND($Q8="Guideline Bodies",CaseHeader!$B$18="Low"),-0.1,0)))*(1+IF(AND($Q8="Payers / Access",CaseHeader!$B$17="Commercial-heavy"),0.06,IF(AND($Q8="Payers / Access",CaseHeader!$B$17="Medicaid-heavy"),-0.03,0)))*(1+IF(AND($Q8="Community Physicians",CaseHeader!$B$19="Entrenched standard of care"),-0.05,0))*(1+IF(AND($Q8="Competitor Counteraction",OR(CaseHeader!$B$19="Aggressive branded competitor",CaseHeader!$B$19="Crowded class / multiple competitors")),0.08,0)) -> 1.25 | D8: =P8*(1+IF(AND($Q8="Guideline Bodies",CaseHeader!$B$18="High"),-0.05,IF(AND($Q8="Guideline Bodies",CaseHeader!$B$18="Low"),0.05,0)))*(1+IF(AND($Q8="Payers / Access",CaseHeader!$B$17="Medicaid-heavy"),0.06,IF(AND($Q8="Payers / Access",CaseHeader!$B$17="Commercial-heavy"),0.03,0)))*(1+IF(AND($Q8="Community Physicians",CaseHeader!$B$19="Entrenched standard of care"),0.08,0))*(1+IF(AND($Q8="Competitor Counteraction",OR(CaseHeader!$B$19="Aggressive branded competitor",CaseHeader!$B$19="Crowded class / multiple competitors")),0.1,IF(AND($Q8="Competitor Counteraction",CaseHeader!$B$19="Whitespace / limited direct competition"),-0.08,0))) -> 0.9 | E8: =IFERROR(INDEX(SpecialtyActorSets!$I$4:$I$45,MATCH(1,(SpecialtyActorSets!$A$4:$A$45=CaseHeader!$B$16)*(SpecialtyActorSets!$B$4:$B$45=5),0)),1) -> 1 | F8: =IFERROR(INDEX(SpecialtyActorSets!$E$4:$E$45,MATCH(1,(SpecialtyActorSets!$A$4:$A$45=CaseHeader!$B$16)*(SpecialtyActorSets!$B$4:$B$45=5),0)),"") -> Formal recommendation-setting organizations. | G8: =IFERROR(INDEX(SpecialtyActorSets!$F$4:$F$45,MATCH(1,(SpecialtyActorSets!$A$4:$A$45=CaseHeader!$B$16)*(SpecialtyActorSets!$B$4:$B$45=5),0)),0) -> 0.14 | H8: =IFERROR(INDEX(PharmaLogic!$B$4:$G$10,MATCH(CaseHeader!$B$16,PharmaLogic!$A$4:$A$10,0),MATCH($Q8,PharmaLogic!$B$3:$G$3,0)),1) -> 1 | I8: =IFERROR(INDEX(PharmaLogic!$B$15:$G$19,MATCH(CaseHeader!$B$17,PharmaLogic!$A$15:$A$19,0),MATCH($Q8,PharmaLogic!$B$14:$G$14,0)),1) -> 1 | J8: =IFERROR(INDEX(PharmaLogic!$B$24:$G$26,MATCH(CaseHeader!$B$18,PharmaLogic!$A$24:$A$26,0),MATCH($Q8,PharmaLogic!$B$23:$G$23,0)),1) -> 1 | K8: =IFERROR(INDEX(PharmaLogic!$B$31:$G$35,MATCH(CaseHeader!$B$19,PharmaLogic!$A$31:$A$35,0),MATCH($Q8,PharmaLogic!$B$30:$G$30,0)),1) -> 1 | L8: =G8*H8*I8*J8*K8 -> 0.14 | O8: =IFERROR(INDEX(SpecialtyActorSets!$G$4:$G$45,MATCH(1,(SpecialtyActorSets!$A$4:$A$45=CaseHeader!$B$16)*(SpecialtyActorSets!$B$4:$B$45=5),0)),1) -> 1.25 | P8: =IFERROR(INDEX(SpecialtyActorSets!$H$4:$H$45,MATCH(1,(SpecialtyActorSets!$A$4:$A$45=CaseHeader!$B$16)*(SpecialtyActorSets!$B$4:$B$45=5),0)),1) -> 0.9 | Q8: =IFERROR(INDEX(SpecialtyActorSets!$D$4:$D$45,MATCH(1,(SpecialtyActorSets!$A$4:$A$45=CaseHeader!$B$16)*(SpecialtyActorSets!$B$4:$B$45=5),0)),"") -> Guideline Bodies
A9: =IFERROR(INDEX(SpecialtyActorSets!$C$4:$C$45,MATCH(1,(SpecialtyActorSets!$A$4:$A$45=CaseHeader!$B$16)*(SpecialtyActorSets!$B$4:$B$45=6),0)),"") -> Competitor Counteraction | B9: =IFERROR(L9/SUM($L$4:$L$9),G9) -> 0.13967022 | C9: =O9*(1+IF(AND($Q9="Guideline Bodies",CaseHeader!$B$18="High"),0.1,IF(AND($Q9="Guideline Bodies",CaseHeader!$B$18="Low"),-0.1,0)))*(1+IF(AND($Q9="Payers / Access",CaseHeader!$B$17="Commercial-heavy"),0.06,IF(AND($Q9="Payers / Access",CaseHeader!$B$17="Medicaid-heavy"),-0.03,0)))*(1+IF(AND($Q9="Community Physicians",CaseHeader!$B$19="Entrenched standard of care"),-0.05,0))*(1+IF(AND($Q9="Competitor Counteraction",OR(CaseHeader!$B$19="Aggressive branded competitor",CaseHeader!$B$19="Crowded class / multiple competitors")),0.08,0)) -> 0.9 | D9: =P9*(1+IF(AND($Q9="Guideline Bodies",CaseHeader!$B$18="High"),-0.05,IF(AND($Q9="Guideline Bodies",CaseHeader!$B$18="Low"),0.05,0)))*(1+IF(AND($Q9="Payers / Access",CaseHeader!$B$17="Medicaid-heavy"),0.06,IF(AND($Q9="Payers / Access",CaseHeader!$B$17="Commercial-heavy"),0.03,0)))*(1+IF(AND($Q9="Community Physicians",CaseHeader!$B$19="Entrenched standard of care"),0.08,0))*(1+IF(AND($Q9="Competitor Counteraction",OR(CaseHeader!$B$19="Aggressive branded competitor",CaseHeader!$B$19="Crowded class / multiple competitors")),0.1,IF(AND($Q9="Competitor Counteraction",CaseHeader!$B$19="Whitespace / limited direct competition"),-0.08,0))) -> 1.12 | E9: =IFERROR(INDEX(SpecialtyActorSets!$I$4:$I$45,MATCH(1,(SpecialtyActorSets!$A$4:$A$45=CaseHeader!$B$16)*(SpecialtyActorSets!$B$4:$B$45=6),0)),1) -> -1 | F9: =IFERROR(INDEX(SpecialtyActorSets!$E$4:$E$45,MATCH(1,(SpecialtyActorSets!$A$4:$A$45=CaseHeader!$B$16)*(SpecialtyActorSets!$B$4:$B$45=6),0)),"") -> Counter-detailing, access defense, and class-noise response. | G9: =IFERROR(INDEX(SpecialtyActorSets!$F$4:$F$45,MATCH(1,(SpecialtyActorSets!$A$4:$A$45=CaseHeader!$B$16)*(SpecialtyActorSets!$B$4:$B$45=6),0)),0) -> 0.12 | H9: =IFERROR(INDEX(PharmaLogic!$B$4:$G$10,MATCH(CaseHeader!$B$16,PharmaLogic!$A$4:$A$10,0),MATCH($Q9,PharmaLogic!$B$3:$G$3,0)),1) -> 1 | I9: =IFERROR(INDEX(PharmaLogic!$B$15:$G$19,MATCH(CaseHeader!$B$17,PharmaLogic!$A$15:$A$19,0),MATCH($Q9,PharmaLogic!$B$14:$G$14,0)),1) -> 1 | J9: =IFERROR(INDEX(PharmaLogic!$B$24:$G$26,MATCH(CaseHeader!$B$18,PharmaLogic!$A$24:$A$26,0),MATCH($Q9,PharmaLogic!$B$23:$G$23,0)),1) -> 1 | K9: =IFERROR(INDEX(PharmaLogic!$B$31:$G$35,MATCH(CaseHeader!$B$19,PharmaLogic!$A$31:$A$35,0),MATCH($Q9,PharmaLogic!$B$30:$G$30,0)),1) -> 1.2 | L9: =G9*H9*I9*J9*K9 -> 0.144 | O9: =IFERROR(INDEX(SpecialtyActorSets!$G$4:$G$45,MATCH(1,(SpecialtyActorSets!$A$4:$A$45=CaseHeader!$B$16)*(SpecialtyActorSets!$B$4:$B$45=6),0)),1) -> 0.9 | P9: =IFERROR(INDEX(SpecialtyActorSets!$H$4:$H$45,MATCH(1,(SpecialtyActorSets!$A$4:$A$45=CaseHeader!$B$16)*(SpecialtyActorSets!$B$4:$B$45=6),0)),1) -> 1.12 | Q9: =IFERROR(INDEX(SpecialtyActorSets!$D$4:$D$45,MATCH(1,(SpecialtyActorSets!$A$4:$A$45=CaseHeader!$B$16)*(SpecialtyActorSets!$B$4:$B$45=6),0)),"") -> Competitor Counteraction

Sheet PharmaLogic
A1: Specialty Profile Modifiers | J1: Signal-Type Actor Multipliers
A3: SpecialtyProfile | B3: Academic KOLs | C3: Community Physicians | D3: Payers / Access | E3: Guideline Bodies | F3: Health Systems | G3: Competitor Counteraction | J3: SignalType | K3: Academic KOLs | L3: Community Physicians | M3: Payers / Access | N3: Guideline Bodies | O3: Health Systems | P3: Competitor Counteraction
A4: General | B4: 1 | C4: 1 | D4: 1 | E4: 1 | F4: 1 | G4: 1 | J4: Clinical evidence | K4: 1.2 | L4: 1 | M4: 0.95 | N4: 1.1 | O4: 0.95 | P4: 0.9
A5: Pulmonology / rare disease | B5: 1.15 | C5: 1.05 | D5: 0.95 | E5: 1.1 | F5: 1 | G5: 0.95 | J5: Field intelligence | K5: 0.95 | L5: 1.15 | M5: 1 | N5: 0.9 | O5: 1 | P5: 1
A6: Cardiology / mixed specialist | B6: 0.95 | C6: 1.15 | D6: 1.1 | E6: 1 | F6: 1.05 | G6: 1.05 | J6: Access / commercial | K6: 0.9 | L6: 0.95 | M6: 1.25 | N6: 0.95 | O6: 1.05 | P6: 1
A7: Oncology / academic-led | B7: 1.2 | C7: 0.95 | D7: 1.05 | E7: 1 | F7: 1 | G7: 1.1 | J7: Guideline / policy | K7: 1.05 | L7: 0.95 | M7: 1 | N7: 1.35 | O7: 1 | P7: 0.95
A8: Dermatology / community-led | B8: 0.9 | C8: 1.2 | D8: 1 | E8: 0.95 | F8: 1 | G8: 1.05 | J8: Safety / tolerability | K8: 1.1 | L8: 1.2 | M8: 1.05 | N8: 1 | O8: 1 | P8: 0.95
A9: Psychiatry / access-sensitive | B9: 0.9 | C9: 1.1 | D9: 1.2 | E9: 0.95 | F9: 1 | G9: 1.05 | J9: Operational / deployment | K9: 0.9 | L9: 1 | M9: 0.95 | N9: 0.9 | O9: 1.25 | P9: 1
A10: Infectious disease / guideline-led | B10: 1.05 | C10: 0.95 | D10: 1 | E10: 1.2 | F10: 1 | G10: 0.95 | J10: Competitive | K10: 0.95 | L10: 1 | M10: 1 | N10: 0.9 | O10: 0.95 | P10: 1.35
J11: HEOR / economic | K11: 0.95 | L11: 0.95 | M11: 1.2 | N11: 1 | O11: 1 | P11: 1
A12: Payer Environment Modifiers | J12: KOL sentiment | K12: 1.3 | L12: 0.95 | M12: 0.9 | N12: 1 | O12: 0.95 | P12: 0.9
J13: Patient / demand | K13: 0.9 | L13: 1.05 | M13: 0.95 | N13: 0.9 | O13: 1 | P13: 0.95
A14: PayerEnvironment | B14: Academic KOLs | C14: Community Physicians | D14: Payers / Access | E14: Guideline Bodies | F14: Health Systems | G14: Competitor Counteraction | J14: Outcomes / PRO | K14: 1.1 | L14: 1.1 | M14: 0.95 | N14: 1 | O14: 0.95 | P14: 0.9
A15: Balanced | B15: 1 | C15: 1 | D15: 1 | E15: 1 | F15: 1 | G15: 1 | J15: Unmapped | K15: 1 | L15: 1 | M15: 1 | N15: 1 | O15: 1 | P15: 1
A16: Commercial-heavy | B16: 0.95 | C16: 1 | D16: 1.15 | E16: 0.95 | F16: 1 | G16: 1.05
A17: Medicare-heavy | B17: 0.95 | C17: 1 | D17: 1.1 | E17: 1.05 | F17: 1 | G17: 1 | J17: Population / Description Keyword Multipliers
A18: Medicaid-heavy | B18: 0.9 | C18: 0.95 | D18: 1.2 | E18: 1 | F18: 1.05 | G18: 1
A19: Integrated delivery / IDN | B19: 0.95 | C19: 1 | D19: 1.05 | E19: 1 | F19: 1.2 | G19: 1 | J19: Keyword | K19: Academic KOLs | L19: Community Physicians | M19: Payers / Access | N19: Guideline Bodies | O19: Health Systems | P19: Competitor Counteraction
J20: academic | K20: 1.2 | L20: 0.95 | M20: 1 | N20: 1.1 | O20: 0.95 | P20: 0.95
A21: Guideline Leverage Modifiers | J21: kol | K21: 1.2 | L21: 0.95 | M21: 0.95 | N21: 1.05 | O21: 0.95 | P21: 0.95
J22: community | K22: 0.95 | L22: 1.2 | M22: 1 | N22: 0.95 | O22: 1 | P22: 1
A23: GuidelineLeverage | B23: Academic KOLs | C23: Community Physicians | D23: Payers / Access | E23: Guideline Bodies | F23: Health Systems | G23: Competitor Counteraction | J23: specialist | K23: 1.05 | L23: 1.1 | M23: 0.95 | N23: 1 | O23: 0.95 | P23: 1
A24: Low | B24: 0.95 | C24: 1.05 | D24: 1 | E24: 0.8 | F24: 1 | G24: 1 | J24: primary care | K24: 0.9 | L24: 1.15 | M24: 1 | N24: 0.9 | O24: 1 | P24: 1
A25: Medium | B25: 1 | C25: 1 | D25: 1 | E25: 1 | F25: 1 | G25: 1 | J25: payer | K25: 0.9 | L25: 0.95 | M25: 1.25 | N25: 0.95 | O25: 1 | P25: 1
A26: High | B26: 1.05 | C26: 0.95 | D26: 1 | E26: 1.25 | F26: 1 | G26: 0.95 | J26: access | K26: 0.9 | L26: 0.95 | M26: 1.25 | N26: 0.95 | O26: 1 | P26: 1
J27: formulary | K27: 0.9 | L27: 0.95 | M27: 1.3 | N27: 1 | O27: 1 | P27: 1
A28: Competitor Profile Modifiers | J28: guideline | K28: 1.05 | L28: 0.95 | M28: 1 | N28: 1.3 | O28: 0.95 | P28: 0.95
J29: hospital | K29: 0.95 | L29: 1 | M29: 1 | N29: 0.95 | O29: 1.2 | P29: 1
A30: CompetitorProfile | B30: Academic KOLs | C30: Community Physicians | D30: Payers / Access | E30: Guideline Bodies | F30: Health Systems | G30: Competitor Counteraction | J30: health system | K30: 0.95 | L30: 1 | M30: 1 | N30: 0.95 | O30: 1.2 | P30: 1
A31: Whitespace / limited direct competition | B31: 1 | C31: 1 | D31: 0.95 | E31: 1 | F31: 1 | G31: 0.8 | J31: idn | K31: 0.95 | L31: 1 | M31: 1 | N31: 0.95 | O31: 1.25 | P31: 1
A32: Entrenched standard of care | B32: 1.05 | C32: 0.95 | D32: 1.05 | E32: 1 | F32: 1 | G32: 1.2 | J32: pulmonology | K32: 1.1 | L32: 1.05 | M32: 0.95 | N32: 1.05 | O32: 1 | P32: 0.95
A33: Aggressive branded competitor | B33: 1 | C33: 0.95 | D33: 1 | E33: 1 | F33: 1 | G33: 1.25 | J33: cardiology | K33: 0.95 | L33: 1.1 | M33: 1.1 | N33: 1 | O33: 1.05 | P33: 1.05
A34: Generic erosion risk | B34: 0.95 | C34: 0.95 | D34: 1.1 | E34: 0.95 | F34: 1 | G34: 1.15 | J34: oncology | K34: 1.15 | L34: 0.95 | M34: 1 | N34: 1 | O34: 1 | P34: 1.1
A35: Crowded class / multiple competitors | B35: 1 | C35: 0.95 | D35: 1.05 | E35: 1 | F35: 1 | G35: 1.2 | J35: dermatology | K35: 0.9 | L35: 1.15 | M35: 1 | N35: 0.95 | O35: 1 | P35: 1.05
J36: psychiatry | K36: 0.9 | L36: 1.05 | M36: 1.15 | N36: 0.95 | O36: 1 | P36: 1.05
J37: infectious disease | K37: 1.05 | L37: 0.95 | M37: 1 | N37: 1.15 | O37: 1 | P37: 0.95
J38: competitor | K38: 0.95 | L38: 1 | M38: 1 | N38: 0.95 | O38: 0.95 | P38: 1.25
J39: generic | K39: 0.95 | L39: 0.95 | M39: 1.1 | N39: 0.95 | O39: 0.95 | P39: 1.25
J40: launch | K40: 1 | L40: 1 | M40: 1 | N40: 1 | O40: 1 | P40: 1.15
J41: switch | K41: 0.95 | L41: 1.05 | M41: 1 | N41: 0.95 | O41: 1 | P41: 1.1

Sheet SpecialtyActorSets
A1: CIOS V19 Specialty Actor Sets
A3: PrimarySpecialtyProfile | B3: ActorSlot | C3: DisplayActor | D3: CanonicalActor | E3: RoleInSystem | F3: BaseInfluenceWeight | G3: BasePositiveResponseFactor | H3: BaseNegativeResponseFactor | I3: OutcomeOrientation
A4: General | B4: 1 | C4: Academic KOLs | D4: Academic KOLs | E4: Cross-specialty scientific validators and early adopters. | F4: 0.2 | G4: 1.15 | H4: 0.88 | I4: 1
A5: General | B5: 2 | C5: Community Physicians | D5: Community Physicians | E5: Broad treating base whose behavior determines real-world conversion. | F5: 0.24 | G5: 0.95 | H5: 1.1 | I5: 1
A6: General | B6: 3 | C6: Specialty Extenders / PCPs | D6: Health Systems | E6: Secondary prescribers or extenders who amplify practical uptake. | F6: 0.12 | G6: 0.85 | H6: 1.05 | I6: 1
A7: General | B7: 4 | C7: Payers / Access | D7: Payers / Access | E7: Coverage and reimbursement gatekeepers. | F7: 0.18 | G7: 0.8 | H7: 1.2 | I7: 1
A8: General | B8: 5 | C8: Guideline / Society Bodies | D8: Guideline Bodies | E8: Formal recommendation-setting organizations. | F8: 0.14 | G8: 1.25 | H8: 0.9 | I8: 1
A9: General | B9: 6 | C9: Competitor Counteraction | D9: Competitor Counteraction | E9: Counter-detailing, access defense, and class-noise response. | F9: 0.12 | G9: 0.9 | H9: 1.12 | I9: -1
A10: Pulmonology / rare disease | B10: 1 | C10: Academic Pulmonologists | D10: Academic KOLs | E10: Reference-center pulmonologists and rare-disease KOLs shaping standards. | F10: 0.24 | G10: 1.2 | H10: 0.85 | I10: 1
A11: Pulmonology / rare disease | B11: 2 | C11: Community Pulmonologists | D11: Community Physicians | E11: Office and hospital pulmonologists who determine scale. | F11: 0.24 | G11: 0.95 | H11: 1.08 | I11: 1
A12: Pulmonology / rare disease | B12: 3 | C12: ID / Bronchiectasis Specialists | D12: Guideline Bodies | E12: Subspecialty experts influencing treatment algorithms and referral logic. | F12: 0.12 | G12: 1.1 | H12: 0.92 | I12: 1
A13: Pulmonology / rare disease | B13: 4 | C13: Payers / Access | D13: Payers / Access | E13: Coverage and prior-authorization gatekeepers. | F13: 0.15 | G13: 0.82 | H13: 1.18 | I13: 1
A14: Pulmonology / rare disease | B14: 5 | C14: Reference Centers / Health Systems | D14: Health Systems | E14: Centers of excellence and integrated systems controlling implementation. | F14: 0.13 | G14: 0.9 | H14: 1.05 | I14: 1
A15: Pulmonology / rare disease | B15: 6 | C15: Competitor Counteraction | D15: Competitor Counteraction | E15: Alternative regimens or entrenched management patterns resisting change. | F15: 0.12 | G15: 0.88 | H15: 1.1 | I15: -1
... A45: Infectious disease / guideline-led | B45: 6 | C45: Competitor Counteraction | D45: Competitor Counteraction | E45: Incumbent regimens and conservative treatment norms resisting movement. | F45: 0.12 | G45: 0.9 | H45: 1.1 | I45: -1
A47: How to use | B47: Select CaseHeader!B16. The six active actors in Actors, ActorReactionMatrix, ActorAggregation, and InterpretationLayer will switch to the actor set mapped to that specialty profile.
A48: Design rule | B48: The engine remains specialty-agnostic. Only actor composition, labels, roles, and base response assumptions change by specialty.

Sheet ActorReactionMatrix
A1: CIOS V19 Actor Reaction Matrix
A3: SignalID | B3: SignalDescription | C3: Direction | D3: Strength | E3: Reliability | F3: LikelihoodRatio | G3: =Actors!A4 -> Academic KOLs | H3: =Actors!A5 -> Community Physicians | I3: =Actors!A6 -> Specialty Extenders / PCPs | J3: =Actors!A7 -> Payers / Access | K3: =Actors!A8 -> Guideline / Society Bodies | L3: =Actors!A9 -> Competitor Counteraction | M3: WeightedActorReaction | N3: SignalType | O3: TargetPopulation | P3: AcademicMultiplier | Q3: CommunityMultiplier | R3: PayerMultiplier | S3: GuidelineMultiplier | T3: HealthSystemMultiplier | U3: CompetitorMultiplier
A4: =SignalRegister!A4 -> CS-001 | B4: =SignalRegister!D4 -> A new publication appears to strengthen the bridge between microbiology and function. | C4: =SignalRegister!F4 -> Positive | D4: =SignalRegister!G4 -> 4 | E4: =SignalRegister!H4 -> 5 | F4: =SignalRegister!I4 -> 1.32 | G4: =IF($A4="","",IF($C4="Positive",1,-1)*((N($D4)+N($E4))/(2*5))*IF($C4="Positive",Actors!$C$4,Actors!$D$4)*Actors!$E$4*$P4) -> 1.3662 | H4: =IF($A4="","",IF($C4="Positive",1,-1)*((N($D4)+N($E4))/(2*5))*IF($C4="Positive",Actors!$C$5,Actors!$D$5)*Actors!$E$5*$Q4) -> 0.8528625 | I4: =IF($A4="","",IF($C4="Positive",1,-1)*((N($D4)+N($E4))/(2*5))*IF($C4="Positive",Actors!$C$6,Actors!$D$6)*Actors!$E$6*$R4) -> 0.6904125 | J4: =IF($A4="","",IF($C4="Positive",1,-1)*((N($D4)+N($E4))/(2*5))*IF($C4="Positive",Actors!$C$7,Actors!$D$7)*Actors!$E$7*$S4) -> 0.8316 | K4: =IF($A4="","",IF($C4="Positive",1,-1)*((N($D4)+N($E4))/(2*5))*IF($C4="Positive",Actors!$C$8,Actors!$D$8)*Actors!$E$8*$T4) -> 1.06875 | L4: =IF($A4="","",IF($C4="Positive",1,-1)*((N($D4)+N($E4))/(2*5))*IF($C4="Positive",Actors!$C$9,Actors!$D$9)*Actors!$E$9*$U4) -> -0.69255 | M4: =IF(A4="","",G4*Actors!$B$4+H4*Actors!$B$5+I4*Actors!$B$6+J4*Actors!$B$7+K4*Actors!$B$8+L4*Actors!$B$9) -> 0.74808375 | N4: =SignalRegister!E4 -> Clinical evidence | O4: =SignalRegister!K4 -> Pulmonology / NTM-focused | P4: =IF($A4="","",MIN(1.6,IFERROR(INDEX(PharmaLogic!$K$4:$K$15,MATCH($N4,PharmaLogic!$J$4:$J$15,0)),1)*(1+SUMPRODUCT(--ISNUMBER(SEARCH(PharmaLogic!$J$20:$J$41,LOWER($O4&" "&$B4))),PharmaLogic!$K$20:$K$41-1)))) -> 1.32 | Q4: =IF($A4="","",MIN(1.6,IFERROR(INDEX(PharmaLogic!$L$4:$L$15,MATCH($N4,PharmaLogic!$J$4:$J$15,0)),1)*(1+SUMPRODUCT(--ISNUMBER(SEARCH(PharmaLogic!$J$20:$J$41,LOWER($O4&" "&$B4))),PharmaLogic!$L$20:$L$41-1)))) -> 1.05 | R4: =IF($A4="","",MIN(1.6,IFERROR(INDEX(PharmaLogic!$M$4:$M$15,MATCH($N4,PharmaLogic!$J$4:$J$15,0)),1)*(1+SUMPRODUCT(--ISNUMBER(SEARCH(PharmaLogic!$J$20:$J$41,LOWER($O4&" "&$B4))),PharmaLogic!$M$20:$M$41-1)))) -> 0.9025 | S4: =IF($A4="","",MIN(1.6,IFERROR(INDEX(PharmaLogic!$N$4:$N$15,MATCH($N4,PharmaLogic!$J$4:$J$15,0)),1)*(1+SUMPRODUCT(--ISNUMBER(SEARCH(PharmaLogic!$J$20:$J$41,LOWER($O4&" "&$B4))),PharmaLogic!$N$20:$N$41-1)))) -> 1.155 | T4: =IF($A4="","",MIN(1.6,IFERROR(INDEX(PharmaLogic!$O$4:$O$15,MATCH($N4,PharmaLogic!$J$4:$J$15,0)),1)*(1+SUMPRODUCT(--ISNUMBER(SEARCH(PharmaLogic!$J$20:$J$41,LOWER($O4&" "&$B4))),PharmaLogic!$O$20:$O$41-1)))) -> 0.95 | U4: =IF($A4="","",MIN(1.6,IFERROR(INDEX(PharmaLogic!$P$4:$P$15,MATCH($N4,PharmaLogic!$J$4:$J$15,0)),1)*(1+SUMPRODUCT(--ISNUMBER(SEARCH(PharmaLogic!$J$20:$J$41,LOWER($O4&" "&$B4))),PharmaLogic!$P$20:$P$41-1)))) -> 0.855
A5: =SignalRegister!A5 -> CS-002 | B5: =SignalRegister!D5 -> Multiple accounts continue to ask for a simpler identification and referral story. | C5: =SignalRegister!F5 -> Negative | D5: =SignalRegister!G5 -> 4 | E5: =SignalRegister!H5 -> 4 | F5: =SignalRegister!I5 -> 0.68 | G5: =IF($A5="","",IF($C5="Positive",1,-1)*((N($D5)+N($E5))/(2*5))*IF($C5="Positive",Actors!$C$4,Actors!$D$4)*Actors!$E$4*$P5) -> -0.70224 | H5: =IF($A5="","",IF($C5="Positive",1,-1)*((N($D5)+N($E5))/(2*5))*IF($C5="Positive",Actors!$C$5,Actors!$D$5)*Actors!$E$5*$Q5) -> -1.3662 | I5: =IF($A5="","",IF($C5="Positive",1,-1)*((N($D5)+N($E5))/(2*5))*IF($C5="Positive",Actors!$C$6,Actors!$D$6)*Actors!$E$6*$R5) -> -0.798 | J5: =IF($A5="","",IF($C5="Positive",1,-1)*((N($D5)+N($E5))/(2*5))*IF($C5="Positive",Actors!$C$7,Actors!$D$7)*Actors!$E$7*$S5) -> -0.864 | K5: =IF($A5="","",IF($C5="Positive",1,-1)*((N($D5)+N($E5))/(2*5))*IF($C5="Positive",Actors!$C$8,Actors!$D$8)*Actors!$E$8*$T5) -> -0.72 | L5: =IF($A5="","",IF($C5="Positive",1,-1)*((N($D5)+N($E5))/(2*5))*IF($C5="Positive",Actors!$C$9,Actors!$D$9)*Actors!$E$9*$U5) -> 0.8512 | M5: =IF(A5="","",G5*Actors!$B$4+H5*Actors!$B$5+I5*Actors!$B$6+J5*Actors!$B$7+K5*Actors!$B$8+L5*Actors!$B$9) -> -0.67531251 | N5: =SignalRegister!E5 -> Field intelligence | O5: =SignalRegister!K5 -> Pulmonology / community | P5: =IF($A5="","",MIN(1.6,IFERROR(INDEX(PharmaLogic!$K$4:$K$15,MATCH($N5,PharmaLogic!$J$4:$J$15,0)),1)*(1+SUMPRODUCT(--ISNUMBER(SEARCH(PharmaLogic!$J$20:$J$41,LOWER($O5&" "&$B5))),PharmaLogic!$K$20:$K$41-1)))) -> 0.9975 | Q5: =IF($A5="","",MIN(1.6,IFERROR(INDEX(PharmaLogic!$L$4:$L$15,MATCH($N5,PharmaLogic!$J$4:$J$15,0)),1)*(1+SUMPRODUCT(--ISNUMBER(SEARCH(PharmaLogic!$J$20:$J$41,LOWER($O5&" "&$B5))),PharmaLogic!$L$20:$L$41-1)))) -> 1.4375 | R5: =IF($A5="","",MIN(1.6,IFERROR(INDEX(PharmaLogic!$M$4:$M$15,MATCH($N5,PharmaLogic!$J$4:$J$15,0)),1)*(1+SUMPRODUCT(--ISNUMBER(SEARCH(PharmaLogic!$J$20:$J$41,LOWER($O5&" "&$B5))),PharmaLogic!$M$20:$M$41-1)))) -> 0.95 | S5: =IF($A5="","",MIN(1.6,IFERROR(INDEX(PharmaLogic!$N$4:$N$15,MATCH($N5,PharmaLogic!$J$4:$J$15,0)),1)*(1+SUMPRODUCT(--ISNUMBER(SEARCH(PharmaLogic!$J$20:$J$41,LOWER($O5&" "&$B5))),PharmaLogic!$N$20:$N$41-1)))) -> 0.9 | T5: =IF($A5="","",MIN(1.6,IFERROR(INDEX(PharmaLogic!$O$4:$O$15,MATCH($N5,PharmaLogic!$J$4:$J$15,0)),1)*(1+SUMPRODUCT(--ISNUMBER(SEARCH(PharmaLogic!$J$20:$J$41,LOWER($O5&" "&$B5))),PharmaLogic!$O$20:$O$41-1)))) -> 1 | U5: =IF($A5="","",MIN(1.6,IFERROR(INDEX(PharmaLogic!$P$4:$P$15,MATCH($N5,PharmaLogic!$J$4:$J$15,0)),1)*(1+SUMPRODUCT(--ISNUMBER(SEARCH(PharmaLogic!$J$20:$J$41,LOWER($O5&" "&$B5))),PharmaLogic!$P$20:$P$41-1)))) -> 0.95
A6: =SignalRegister!A6 -> CS-003 | B6: =SignalRegister!D6 -> Emerging coverage shift could reduce reimbursement obstacles in target accounts. | C6: =SignalRegister!F6 -> Positive | D6: =SignalRegister!G6 -> 5 | E6: =SignalRegister!H6 -> 4 | F6: =SignalRegister!I6 -> 1.4 | G6: =IF($A6="","",IF($C6="Positive",1,-1)*((N($D6)+N($E6))/(2*5))*IF($C6="Positive",Actors!$C$4,Actors!$D$4)*Actors!$E$4*$P6) -> 1.02465 | H6: =IF($A6="","",IF($C6="Positive",1,-1)*((N($D6)+N($E6))/(2*5))*IF($C6="Positive",Actors!$C$5,Actors!$D$5)*Actors!$E$5*$Q6) -> 0.81021937 | I6: =IF($A6="","",IF($C6="Positive",1,-1)*((N($D6)+N($E6))/(2*5))*IF($C6="Positive",Actors!$C$6,Actors!$D$6)*Actors!$E$6*$R6) -> 0.9084375 | J6: =IF($A6="","",IF($C6="Positive",1,-1)*((N($D6)+N($E6))/(2*5))*IF($C6="Positive",Actors!$C$7,Actors!$D$7)*Actors!$E$7*$S6) -> 0.7182 | K6: =IF($A6="","",IF($C6="Positive",1,-1)*((N($D6)+N($E6))/(2*5))*IF($C6="Positive",Actors!$C$8,Actors!$D$8)*Actors!$E$8*$T6) -> 1.18125 | L6: =IF($A6="","",IF($C6="Positive",1,-1)*((N($D6)+N($E6))/(2*5))*IF($C6="Positive",Actors!$C$9,Actors!$D$9)*Actors!$E$9*$U6) -> -0.7695 | M6: =IF(A6="","",G6*Actors!$B$4+H6*Actors!$B$5+I6*Actors!$B$6+J6*Actors!$B$7+K6*Actors!$B$8+L6*Actors!$B$9) -> 0.67820157 | N6: =SignalRegister!E6 -> Access / commercial | O6: =SignalRegister!K6 -> Pulmonology / general | P6: =IF($A6="","",MIN(1.6,IFERROR(INDEX(PharmaLogic!$K$4:$K$15,MATCH($N6,PharmaLogic!$J$4:$J$15,0)),1)*(1+SUMPRODUCT(--ISNUMBER(SEARCH(PharmaLogic!$J$20:$J$41,LOWER($O6&" "&$B6))),PharmaLogic!$K$20:$K$41-1)))) -> 0.99 | Q6: =IF($A6="","",MIN(1.6,IFERROR(INDEX(PharmaLogic!$L$4:$L$15,MATCH($N6,PharmaLogic!$J$4:$J$15,0)),1)*(1+SUMPRODUCT(--ISNUMBER(SEARCH(PharmaLogic!$J$20:$J$41,LOWER($O6&" "&$B6))),PharmaLogic!$L$20:$L$41-1)))) -> 0.9975 | R6: =IF($A6="","",MIN(1.6,IFERROR(INDEX(PharmaLogic!$M$4:$M$15,MATCH($N6,PharmaLogic!$J$4:$J$15,0)),1)*(1+SUMPRODUCT(--ISNUMBER(SEARCH(PharmaLogic!$J$20:$J$41,LOWER($O6&" "&$B6))),PharmaLogic!$M$20:$M$41-1)))) -> 1.1875 | S6: =IF($A6="","",MIN(1.6,IFERROR(INDEX(PharmaLogic!$N$4:$N$15,MATCH($N6,PharmaLogic!$J$4:$J$15,0)),1)*(1+SUMPRODUCT(--ISNUMBER(SEARCH(PharmaLogic!$J$20:$J$41,LOWER($O6&" "&$B6))),PharmaLogic!$N$20:$N$41-1)))) -> 0.9975 | T6: =IF($A6="","",MIN(1.6,IFERROR(INDEX(PharmaLogic!$O$4:$O$15,MATCH($N6,PharmaLogic!$J$4:$J$15,0)),1)*(1+SUMPRODUCT(--ISNUMBER(SEARCH(PharmaLogic!$J$20:$J$41,LOWER($O6&" "&$B6))),PharmaLogic!$O$20:$O$41-1)))) -> 1.05 | U6: =IF($A6="","",MIN(1.6,IFERROR(INDEX(PharmaLogic!$P$4:$P$15,MATCH($N6,PharmaLogic!$J$4:$J$15,0)),1)*(1+SUMPRODUCT(--ISNUMBER(SEARCH(PharmaLogic!$J$20:$J$41,LOWER($O6&" "&$B6))),PharmaLogic!$P$20:$P$41-1)))) -> 0.95
A7: =SignalRegister!A7 -> 0 | B7: =SignalRegister!D7 | C7: =SignalRegister!F7 | D7: =SignalRegister!G7 | E7: =SignalRegister!H7 | F7: =SignalRegister!I7 | G7: =IF($A7="","",IF($C7="Positive",1,-1)*((N($D7)+N($E7))/(2*5))*IF($C7="Positive",Actors!$C$4,Actors!$D$4)*Actors!$E$4*$P7) -> 0 | H7: =IF($A7="","",IF($C7="Positive",1,-1)*((N($D7)+N($E7))/(2*5))*IF($C7="Positive",Actors!$C$5,Actors!$D$5)*Actors!$E$5*$Q7) -> 0 | I7: =IF($A7="","",IF($C7="Positive",1,-1)*((N($D7)+N($E7))/(2*5))*IF($C7="Positive",Actors!$C$6,Actors!$D$6)*Actors!$E$6*$R7) -> 0 | J7: =IF($A7="","",IF($C7="Positive",1,-1)*((N($D7)+N($E7))/(2*5))*IF($C7="Positive",Actors!$C$7,Actors!$D$7)*Actors!$E$7*$S7) -> 0 | K7: =IF($A7="","",IF($C7="Positive",1,-1)*((N($D7)+N($E7))/(2*5))*IF($C7="Positive",Actors!$C$8,Actors!$D$8)*Actors!$E$8*$T7) -> 0 | L7: =IF($A7="","",IF($C7="Positive",1,-1)*((N($D7)+N($E7))/(2*5))*IF($C7="Positive",Actors!$C$9,Actors!$D$9)*Actors!$E$9*$U7) -> 0 | M7: =IF(A7="","",G7*Actors!$B$4+H7*Actors!$B$5+I7*Actors!$B$6+J7*Actors!$B$7+K7*Actors!$B$8+L7*Actors!$B$9) -> 0 | N7: =SignalRegister!E7 | O7: =SignalRegister!K7 | P7: =IF($A7="","",MIN(1.6,IFERROR(INDEX(PharmaLogic!$K$4:$K$15,MATCH($N7,PharmaLogic!$J$4:$J$15,0)),1)*(1+SUMPRODUCT(--ISNUMBER(SEARCH(PharmaLogic!$J$20:$J$41,LOWER($O7&" "&$B7))),PharmaLogic!$K$20:$K$41-1)))) -> 1 | Q7: =IF($A7="","",MIN(1.6,IFERROR(INDEX(PharmaLogic!$L$4:$L$15,MATCH($N7,PharmaLogic!$J$4:$J$15,0)),1)*(1+SUMPRODUCT(--ISNUMBER(SEARCH(PharmaLogic!$J$20:$J$41,LOWER($O7&" "&$B7))),PharmaLogic!$L$20:$L$41-1)))) -> 1 | R7: =IF($A7="","",MIN(1.6,IFERROR(INDEX(PharmaLogic!$M$4:$M$15,MATCH($N7,PharmaLogic!$J$4:$J$15,0)),1)*(1+SUMPRODUCT(--ISNUMBER(SEARCH(PharmaLogic!$J$20:$J$41,LOWER($O7&" "&$B7))),PharmaLogic!$M$20:$M$41-1)))) -> 1 | S7: =IF($A7="","",MIN(1.6,IFERROR(INDEX(PharmaLogic!$N$4:$N$15,MATCH($N7,PharmaLogic!$J$4:$J$15,0)),1)*(1+SUMPRODUCT(--ISNUMBER(SEARCH(PharmaLogic!$J$20:$J$41,LOWER($O7&" "&$B7))),PharmaLogic!$N$20:$N$41-1)))) -> 1 | T7: =IF($A7="","",MIN(1.6,IFERROR(INDEX(PharmaLogic!$O$4:$O$15,MATCH($N7,PharmaLogic!$J$4:$J$15,0)),1)*(1+SUMPRODUCT(--ISNUMBER(SEARCH(PharmaLogic!$J$20:$J$41,LOWER($O7&" "&$B7))),PharmaLogic!$O$20:$O$41-1)))) -> 1 | U7: =IF($A7="","",MIN(1.6,IFERROR(INDEX(PharmaLogic!$P$4:$P$15,MATCH($N7,PharmaLogic!$J$4:$J$15,0)),1)*(1+SUMPRODUCT(--ISNUMBER(SEARCH(PharmaLogic!$J$20:$J$41,LOWER($O7&" "&$B7))),PharmaLogic!$P$20:$P$41-1)))) -> 1
A8: =SignalRegister!A8 -> 0 | B8: =SignalRegister!D8 | C8: =SignalRegister!F8 | D8: =SignalRegister!G8 | E8: =SignalRegister!H8 | F8: =SignalRegister!I8 | G8: =IF($A8="","",IF($C8="Positive",1,-1)*((N($D8)+N($E8))/(2*5))*IF($C8="Positive",Actors!$C$4,Actors!$D$4)*Actors!$E$4*$P8) -> 0 | H8: =IF($A8="","",IF($C8="Positive",1,-1)*((N($D8)+N($E8))/(2*5))*IF($C8="Positive",Actors!$C$5,Actors!$D$5)*Actors!$E$5*$Q8) -> 0 | I8: =IF($A8="","",IF($C8="Positive",1,-1)*((N($D8)+N($E8))/(2*5))*IF($C8="Positive",Actors!$C$6,Actors!$D$6)*Actors!$E$6*$R8) -> 0 | J8: =IF($A8="","",IF($C8="Positive",1,-1)*((N($D8)+N($E8))/(2*5))*IF($C8="Positive",Actors!$C$7,Actors!$D$7)*Actors!$E$7*$S8) -> 0 | K8: =IF($A8="","",IF($C8="Positive",1,-1)*((N($D8)+N($E8))/(2*5))*IF($C8="Positive",Actors!$C$8,Actors!$D$8)*Actors!$E$8*$T8) -> 0 | L8: =IF($A8="","",IF($C8="Positive",1,-1)*((N($D8)+N($E8))/(2*5))*IF($C8="Positive",Actors!$C$9,Actors!$D$9)*Actors!$E$9*$U8) -> 0 | M8: =IF(A8="","",G8*Actors!$B$4+H8*Actors!$B$5+I8*Actors!$B$6+J8*Actors!$B$7+K8*Actors!$B$8+L8*Actors!$B$9) -> 0 | N8: =SignalRegister!E8 | O8: =SignalRegister!K8 | P8: =IF($A8="","",MIN(1.6,IFERROR(INDEX(PharmaLogic!$K$4:$K$15,MATCH($N8,PharmaLogic!$J$4:$J$15,0)),1)*(1+SUMPRODUCT(--ISNUMBER(SEARCH(PharmaLogic!$J$20:$J$41,LOWER($O8&" "&$B8))),PharmaLogic!$K$20:$K$41-1)))) -> 1 | Q8: =IF($A8="","",MIN(1.6,IFERROR(INDEX(PharmaLogic!$L$4:$L$15,MATCH($N8,PharmaLogic!$J$4:$J$15,0)),1)*(1+SUMPRODUCT(--ISNUMBER(SEARCH(PharmaLogic!$J$20:$J$41,LOWER($O8&" "&$B8))),PharmaLogic!$L$20:$L$41-1)))) -> 1 | R8: =IF($A8="","",MIN(1.6,IFERROR(INDEX(PharmaLogic!$M$4:$M$15,MATCH($N8,PharmaLogic!$J$4:$J$15,0)),1)*(1+SUMPRODUCT(--ISNUMBER(SEARCH(PharmaLogic!$J$20:$J$41,LOWER($O8&" "&$B8))),PharmaLogic!$M$20:$M$41-1)))) -> 1 | S8: =IF($A8="","",MIN(1.6,IFERROR(INDEX(PharmaLogic!$N$4:$N$15,MATCH($N8,PharmaLogic!$J$4:$J$15,0)),1)*(1+SUMPRODUCT(--ISNUMBER(SEARCH(PharmaLogic!$J$20:$J$41,LOWER($O8&" "&$B8))),PharmaLogic!$N$20:$N$41-1)))) -> 1 | T8: =IF($A8="","",MIN(1.6,IFERROR(INDEX(PharmaLogic!$O$4:$O$15,MATCH($N8,PharmaLogic!$J$4:$J$15,0)),1)*(1+SUMPRODUCT(--ISNUMBER(SEARCH(PharmaLogic!$J$20:$J$41,LOWER($O8&" "&$B8))),PharmaLogic!$O$20:$O$41-1)))) -> 1 | U8: =IF($A8="","",MIN(1.6,IFERROR(INDEX(PharmaLogic!$P$4:$P$15,MATCH($N8,PharmaLogic!$J$4:$J$15,0)),1)*(1+SUMPRODUCT(--ISNUMBER(SEARCH(PharmaLogic!$J$20:$J$41,LOWER($O8&" "&$B8))),PharmaLogic!$P$20:$P$41-1)))) -> 1
A9: =SignalRegister!A9 -> 0 | B9: =SignalRegister!D9 | C9: =SignalRegister!F9 | D9: =SignalRegister!G9 | E9: =SignalRegister!H9 | F9: =SignalRegister!I9 | G9: =IF($A9="","",IF($C9="Positive",1,-1)*((N($D9)+N($E9))/(2*5))*IF($C9="Positive",Actors!$C$4,Actors!$D$4)*Actors!$E$4*$P9) -> 0 | H9: =IF($A9="","",IF($C9="Positive",1,-1)*((N($D9)+N($E9))/(2*5))*IF($C9="Positive",Actors!$C$5,Actors!$D$5)*Actors!$E$5*$Q9) -> 0 | I9: =IF($A9="","",IF($C9="Positive",1,-1)*((N($D9)+N($E9))/(2*5))*IF($C9="Positive",Actors!$C$6,Actors!$D$6)*Actors!$E$6*$R9) -> 0 | J9: =IF($A9="","",IF($C9="Positive",1,-1)*((N($D9)+N($E9))/(2*5))*IF($C9="Positive",Actors!$C$7,Actors!$D$7)*Actors!$E$7*$S9) -> 0 | K9: =IF($A9="","",IF($C9="Positive",1,-1)*((N($D9)+N($E9))/(2*5))*IF($C9="Positive",Actors!$C$8,Actors!$D$8)*Actors!$E$8*$T9) -> 0 | L9: =IF($A9="","",IF($C9="Positive",1,-1)*((N($D9)+N($E9))/(2*5))*IF($C9="Positive",Actors!$C$9,Actors!$D$9)*Actors!$E$9*$U9) -> 0 | M9: =IF(A9="","",G9*Actors!$B$4+H9*Actors!$B$5+I9*Actors!$B$6+J9*Actors!$B$7+K9*Actors!$B$8+L9*Actors!$B$9) -> 0 | N9: =SignalRegister!E9 | O9: =SignalRegister!K9 | P9: =IF($A9="","",MIN(1.6,IFERROR(INDEX(PharmaLogic!$K$4:$K$15,MATCH($N9,PharmaLogic!$J$4:$J$15,0)),1)*(1+SUMPRODUCT(--ISNUMBER(SEARCH(PharmaLogic!$J$20:$J$41,LOWER($O9&" "&$B9))),PharmaLogic!$K$20:$K$41-1)))) -> 1 | Q9: =IF($A9="","",MIN(1.6,IFERROR(INDEX(PharmaLogic!$L$4:$L$15,MATCH($N9,PharmaLogic!$J$4:$J$15,0)),1)*(1+SUMPRODUCT(--ISNUMBER(SEARCH(PharmaLogic!$J$20:$J$41,LOWER($O9&" "&$B9))),PharmaLogic!$L$20:$L$41-1)))) -> 1 | R9: =IF($A9="","",MIN(1.6,IFERROR(INDEX(PharmaLogic!$M$4:$M$15,MATCH($N9,PharmaLogic!$J$4:$J$15,0)),1)*(1+SUMPRODUCT(--ISNUMBER(SEARCH(PharmaLogic!$J$20:$J$41,LOWER($O9&" "&$B9))),PharmaLogic!$M$20:$M$41-1)))) -> 1 | S9: =IF($A9="","",MIN(1.6,IFERROR(INDEX(PharmaLogic!$N$4:$N$15,MATCH($N9,PharmaLogic!$J$4:$J$15,0)),1)*(1+SUMPRODUCT(--ISNUMBER(SEARCH(PharmaLogic!$J$20:$J$41,LOWER($O9&" "&$B9))),PharmaLogic!$N$20:$N$41-1)))) -> 1 | T9: =IF($A9="","",MIN(1.6,IFERROR(INDEX(PharmaLogic!$O$4:$O$15,MATCH($N9,PharmaLogic!$J$4:$J$15,0)),1)*(1+SUMPRODUCT(--ISNUMBER(SEARCH(PharmaLogic!$J$20:$J$41,LOWER($O9&" "&$B9))),PharmaLogic!$O$20:$O$41-1)))) -> 1 | U9: =IF($A9="","",MIN(1.6,IFERROR(INDEX(PharmaLogic!$P$4:$P$15,MATCH($N9,PharmaLogic!$J$4:$J$15,0)),1)*(1+SUMPRODUCT(--ISNUMBER(SEARCH(PharmaLogic!$J$20:$J$41,LOWER($O9&" "&$B9))),PharmaLogic!$P$20:$P$41-1)))) -> 1
A10: =SignalRegister!A10 -> 0 | B10: =SignalRegister!D10 | C10: =SignalRegister!F10 | D10: =SignalRegister!G10 | E10: =SignalRegister!H10 | F10: =SignalRegister!I10 | G10: =IF($A10="","",IF($C10="Positive",1,-1)*((N($D10)+N($E10))/(2*5))*IF($C10="Positive",Actors!$C$4,Actors!$D$4)*Actors!$E$4*$P10) -> 0 | H10: =IF($A10="","",IF($C10="Positive",1,-1)*((N($D10)+N($E10))/(2*5))*IF($C10="Positive",Actors!$C$5,Actors!$D$5)*Actors!$E$5*$Q10) -> 0 | I10: =IF($A10="","",IF($C10="Positive",1,-1)*((N($D10)+N($E10))/(2*5))*IF($C10="Positive",Actors!$C$6,Actors!$D$6)*Actors!$E$6*$R10) -> 0 | J10: =IF($A10="","",IF($C10="Positive",1,-1)*((N($D10)+N($E10))/(2*5))*IF($C10="Positive",Actors!$C$7,Actors!$D$7)*Actors!$E$7*$S10) -> 0 | K10: =IF($A10="","",IF($C10="Positive",1,-1)*((N($D10)+N($E10))/(2*5))*IF($C10="Positive",Actors!$C$8,Actors!$D$8)*Actors!$E$8*$T10) -> 0 | L10: =IF($A10="","",IF($C10="Positive",1,-1)*((N($D10)+N($E10))/(2*5))*IF($C10="Positive",Actors!$C$9,Actors!$D$9)*Actors!$E$9*$U10) -> 0 | M10: =IF(A10="","",G10*Actors!$B$4+H10*Actors!$B$5+I10*Actors!$B$6+J10*Actors!$B$7+K10*Actors!$B$8+L10*Actors!$B$9) -> 0 | N10: =SignalRegister!E10 | O10: =SignalRegister!K10 | P10: =IF($A10="","",MIN(1.6,IFERROR(INDEX(PharmaLogic!$K$4:$K$15,MATCH($N10,PharmaLogic!$J$4:$J$15,0)),1)*(1+SUMPRODUCT(--ISNUMBER(SEARCH(PharmaLogic!$J$20:$J$41,LOWER($O10&" "&$B10))),PharmaLogic!$K$20:$K$41-1)))) -> 1 | Q10: =IF($A10="","",MIN(1.6,IFERROR(INDEX(PharmaLogic!$L$4:$L$15,MATCH($N10,PharmaLogic!$J$4:$J$15,0)),1)*(1+SUMPRODUCT(--ISNUMBER(SEARCH(PharmaLogic!$J$20:$J$41,LOWER($O10&" "&$B10))),PharmaLogic!$L$20:$L$41-1)))) -> 1 | R10: =IF($A10="","",MIN(1.6,IFERROR(INDEX(PharmaLogic!$M$4:$M$15,MATCH($N10,PharmaLogic!$J$4:$J$15,0)),1)*(1+SUMPRODUCT(--ISNUMBER(SEARCH(PharmaLogic!$J$20:$J$41,LOWER($O10&" "&$B10))),PharmaLogic!$M$20:$M$41-1)))) -> 1 | S10: =IF($A10="","",MIN(1.6,IFERROR(INDEX(PharmaLogic!$N$4:$N$15,MATCH($N10,PharmaLogic!$J$4:$J$15,0)),1)*(1+SUMPRODUCT(--ISNUMBER(SEARCH(PharmaLogic!$J$20:$J$41,LOWER($O10&" "&$B10))),PharmaLogic!$N$20:$N$41-1)))) -> 1 | T10: =IF($A10="","",MIN(1.6,IFERROR(INDEX(PharmaLogic!$O$4:$O$15,MATCH($N10,PharmaLogic!$J$4:$J$15,0)),1)*(1+SUMPRODUCT(--ISNUMBER(SEARCH(PharmaLogic!$J$20:$J$41,LOWER($O10&" "&$B10))),PharmaLogic!$O$20:$O$41-1)))) -> 1 | U10: =IF($A10="","",MIN(1.6,IFERROR(INDEX(PharmaLogic!$P$4:$P$15,MATCH($N10,PharmaLogic!$J$4:$J$15,0)),1)*(1+SUMPRODUCT(--ISNUMBER(SEARCH(PharmaLogic!$J$20:$J$41,LOWER($O10&" "&$B10))),PharmaLogic!$P$20:$P$41-1)))) -> 1
A11: =SignalRegister!A11 -> 0 | B11: =SignalRegister!D11 | C11: =SignalRegister!F11 | D11: =SignalRegister!G11 | E11: =SignalRegister!H11 | F11: =SignalRegister!I11 | G11: =IF($A11="","",IF($C11="Positive",1,-1)*((N($D11)+N($E11))/(2*5))*IF($C11="Positive",Actors!$C$4,Actors!$D$4)*Actors!$E$4*$P11) -> 0 | H11: =IF($A11="","",IF($C11="Positive",1,-1)*((N($D11)+N($E11))/(2*5))*IF($C11="Positive",Actors!$C$5,Actors!$D$5)*Actors!$E$5*$Q11) -> 0 | I11: =IF($A11="","",IF($C11="Positive",1,-1)*((N($D11)+N($E11))/(2*5))*IF($C11="Positive",Actors!$C$6,Actors!$D$6)*Actors!$E$6*$R11) -> 0 | J11: =IF($A11="","",IF($C11="Positive",1,-1)*((N($D11)+N($E11))/(2*5))*IF($C11="Positive",Actors!$C$7,Actors!$D$7)*Actors!$E$7*$S11) -> 0 | K11: =IF($A11="","",IF($C11="Positive",1,-1)*((N($D11)+N($E11))/(2*5))*IF($C11="Positive",Actors!$C$8,Actors!$D$8)*Actors!$E$8*$T11) -> 0 | L11: =IF($A11="","",IF($C11="Positive",1,-1)*((N($D11)+N($E11))/(2*5))*IF($C11="Positive",Actors!$C$9,Actors!$D$9)*Actors!$E$9*$U11) -> 0 | M11: =IF(A11="","",G11*Actors!$B$4+H11*Actors!$B$5+I11*Actors!$B$6+J11*Actors!$B$7+K11*Actors!$B$8+L11*Actors!$B$9) -> 0 | N11: =SignalRegister!E11 | O11: =SignalRegister!K11 | P11: =IF($A11="","",MIN(1.6,IFERROR(INDEX(PharmaLogic!$K$4:$K$15,MATCH($N11,PharmaLogic!$J$4:$J$15,0)),1)*(1+SUMPRODUCT(--ISNUMBER(SEARCH(PharmaLogic!$J$20:$J$41,LOWER($O11&" "&$B11))),PharmaLogic!$K$20:$K$41-1)))) -> 1 | Q11: =IF($A11="","",MIN(1.6,IFERROR(INDEX(PharmaLogic!$L$4:$L$15,MATCH($N11,PharmaLogic!$J$4:$J$15,0)),1)*(1+SUMPRODUCT(--ISNUMBER(SEARCH(PharmaLogic!$J$20:$J$41,LOWER($O11&" "&$B11))),PharmaLogic!$L$20:$L$41-1)))) -> 1 | R11: =IF($A11="","",MIN(1.6,IFERROR(INDEX(PharmaLogic!$M$4:$M$15,MATCH($N11,PharmaLogic!$J$4:$J$15,0)),1)*(1+SUMPRODUCT(--ISNUMBER(SEARCH(PharmaLogic!$J$20:$J$41,LOWER($O11&" "&$B11))),PharmaLogic!$M$20:$M$41-1)))) -> 1 | S11: =IF($A11="","",MIN(1.6,IFERROR(INDEX(PharmaLogic!$N$4:$N$15,MATCH($N11,PharmaLogic!$J$4:$J$15,0)),1)*(1+SUMPRODUCT(--ISNUMBER(SEARCH(PharmaLogic!$J$20:$J$41,LOWER($O11&" "&$B11))),PharmaLogic!$N$20:$N$41-1)))) -> 1 | T11: =IF($A11="","",MIN(1.6,IFERROR(INDEX(PharmaLogic!$O$4:$O$15,MATCH($N11,PharmaLogic!$J$4:$J$15,0)),1)*(1+SUMPRODUCT(--ISNUMBER(SEARCH(PharmaLogic!$J$20:$J$41,LOWER($O11&" "&$B11))),PharmaLogic!$O$20:$O$41-1)))) -> 1 | U11: =IF($A11="","",MIN(1.6,IFERROR(INDEX(PharmaLogic!$P$4:$P$15,MATCH($N11,PharmaLogic!$J$4:$J$15,0)),1)*(1+SUMPRODUCT(--ISNUMBER(SEARCH(PharmaLogic!$J$20:$J$41,LOWER($O11&" "&$B11))),PharmaLogic!$P$20:$P$41-1)))) -> 1
A12: =SignalRegister!A12 -> 0 | B12: =SignalRegister!D12 | C12: =SignalRegister!F12 | D12: =SignalRegister!G12 | E12: =SignalRegister!H12 | F12: =SignalRegister!I12 | G12: =IF($A12="","",IF($C12="Positive",1,-1)*((N($D12)+N($E12))/(2*5))*IF($C12="Positive",Actors!$C$4,Actors!$D$4)*Actors!$E$4*$P12) -> 0 | H12: =IF($A12="","",IF($C12="Positive",1,-1)*((N($D12)+N($E12))/(2*5))*IF($C12="Positive",Actors!$C$5,Actors!$D$5)*Actors!$E$5*$Q12) -> 0 | I12: =IF($A12="","",IF($C12="Positive",1,-1)*((N($D12)+N($E12))/(2*5))*IF($C12="Positive",Actors!$C$6,Actors!$D$6)*Actors!$E$6*$R12) -> 0 | J12: =IF($A12="","",IF($C12="Positive",1,-1)*((N($D12)+N($E12))/(2*5))*IF($C12="Positive",Actors!$C$7,Actors!$D$7)*Actors!$E$7*$S12) -> 0 | K12: =IF($A12="","",IF($C12="Positive",1,-1)*((N($D12)+N($E12))/(2*5))*IF($C12="Positive",Actors!$C$8,Actors!$D$8)*Actors!$E$8*$T12) -> 0 | L12: =IF($A12="","",IF($C12="Positive",1,-1)*((N($D12)+N($E12))/(2*5))*IF($C12="Positive",Actors!$C$9,Actors!$D$9)*Actors!$E$9*$U12) -> 0 | M12: =IF(A12="","",G12*Actors!$B$4+H12*Actors!$B$5+I12*Actors!$B$6+J12*Actors!$B$7+K12*Actors!$B$8+L12*Actors!$B$9) -> 0 | N12: =SignalRegister!E12 | O12: =SignalRegister!K12 | P12: =IF($A12="","",MIN(1.6,IFERROR(INDEX(PharmaLogic!$K$4:$K$15,MATCH($N12,PharmaLogic!$J$4:$J$15,0)),1)*(1+SUMPRODUCT(--ISNUMBER(SEARCH(PharmaLogic!$J$20:$J$41,LOWER($O12&" "&$B12))),PharmaLogic!$K$20:$K$41-1)))) -> 1 | Q12: =IF($A12="","",MIN(1.6,IFERROR(INDEX(PharmaLogic!$L$4:$L$15,MATCH($N12,PharmaLogic!$J$4:$J$15,0)),1)*(1+SUMPRODUCT(--ISNUMBER(SEARCH(PharmaLogic!$J$20:$J$41,LOWER($O12&" "&$B12))),PharmaLogic!$L$20:$L$41-1)))) -> 1 | R12: =IF($A12="","",MIN(1.6,IFERROR(INDEX(PharmaLogic!$M$4:$M$15,MATCH($N12,PharmaLogic!$J$4:$J$15,0)),1)*(1+SUMPRODUCT(--ISNUMBER(SEARCH(PharmaLogic!$J$20:$J$41,LOWER($O12&" "&$B12))),PharmaLogic!$M$20:$M$41-1)))) -> 1 | S12: =IF($A12="","",MIN(1.6,IFERROR(INDEX(PharmaLogic!$N$4:$N$15,MATCH($N12,PharmaLogic!$J$4:$J$15,0)),1)*(1+SUMPRODUCT(--ISNUMBER(SEARCH(PharmaLogic!$J$20:$J$41,LOWER($O12&" "&$B12))),PharmaLogic!$N$20:$N$41-1)))) -> 1 | T12: =IF($A12="","",MIN(1.6,IFERROR(INDEX(PharmaLogic!$O$4:$O$15,MATCH($N12,PharmaLogic!$J$4:$J$15,0)),1)*(1+SUMPRODUCT(--ISNUMBER(SEARCH(PharmaLogic!$J$20:$J$41,LOWER($O12&" "&$B12))),PharmaLogic!$O$20:$O$41-1)))) -> 1 | U12: =IF($A12="","",MIN(1.6,IFERROR(INDEX(PharmaLogic!$P$4:$P$15,MATCH($N12,PharmaLogic!$J$4:$J$15,0)),1)*(1+SUMPRODUCT(--ISNUMBER(SEARCH(PharmaLogic!$J$20:$J$41,LOWER($O12&" "&$B12))),PharmaLogic!$P$20:$P$41-1)))) -> 1
A13: =SignalRegister!A13 -> 0 | B13: =SignalRegister!D13 | C13: =SignalRegister!F13 | D13: =SignalRegister!G13 | E13: =SignalRegister!H13 | F13: =SignalRegister!I13 | G13: =IF($A13="","",IF($C13="Positive",1,-1)*((N($D13)+N($E13))/(2*5))*IF($C13="Positive",Actors!$C$4,Actors!$D$4)*Actors!$E$4*$P13) -> 0 | H13: =IF($A13="","",IF($C13="Positive",1,-1)*((N($D13)+N($E13))/(2*5))*IF($C13="Positive",Actors!$C$5,Actors!$D$5)*Actors!$E$5*$Q13) -> 0 | I13: =IF($A13="","",IF($C13="Positive",1,-1)*((N($D13)+N($E13))/(2*5))*IF($C13="Positive",Actors!$C$6,Actors!$D$6)*Actors!$E$6*$R13) -> 0 | J13: =IF($A13="","",IF($C13="Positive",1,-1)*((N($D13)+N($E13))/(2*5))*IF($C13="Positive",Actors!$C$7,Actors!$D$7)*Actors!$E$7*$S13) -> 0 | K13: =IF($A13="","",IF($C13="Positive",1,-1)*((N($D13)+N($E13))/(2*5))*IF($C13="Positive",Actors!$C$8,Actors!$D$8)*Actors!$E$8*$T13) -> 0 | L13: =IF($A13="","",IF($C13="Positive",1,-1)*((N($D13)+N($E13))/(2*5))*IF($C13="Positive",Actors!$C$9,Actors!$D$9)*Actors!$E$9*$U13) -> 0 | M13: =IF(A13="","",G13*Actors!$B$4+H13*Actors!$B$5+I13*Actors!$B$6+J13*Actors!$B$7+K13*Actors!$B$8+L13*Actors!$B$9) -> 0 | N13: =SignalRegister!E13 | O13: =SignalRegister!K13 | P13: =IF($A13="","",MIN(1.6,IFERROR(INDEX(PharmaLogic!$K$4:$K$15,MATCH($N13,PharmaLogic!$J$4:$J$15,0)),1)*(1+SUMPRODUCT(--ISNUMBER(SEARCH(PharmaLogic!$J$20:$J$41,LOWER($O13&" "&$B13))),PharmaLogic!$K$20:$K$41-1)))) -> 1 | Q13: =IF($A13="","",MIN(1.6,IFERROR(INDEX(PharmaLogic!$L$4:$L$15,MATCH($N13,PharmaLogic!$J$4:$J$15,0)),1)*(1+SUMPRODUCT(--ISNUMBER(SEARCH(PharmaLogic!$J$20:$J$41,LOWER($O13&" "&$B13))),PharmaLogic!$L$20:$L$41-1)))) -> 1 | R13: =IF($A13="","",MIN(1.6,IFERROR(INDEX(PharmaLogic!$M$4:$M$15,MATCH($N13,PharmaLogic!$J$4:$J$15,0)),1)*(1+SUMPRODUCT(--ISNUMBER(SEARCH(PharmaLogic!$J$20:$J$41,LOWER($O13&" "&$B13))),PharmaLogic!$M$20:$M$41-1)))) -> 1 | S13: =IF($A13="","",MIN(1.6,IFERROR(INDEX(PharmaLogic!$N$4:$N$15,MATCH($N13,PharmaLogic!$J$4:$J$15,0)),1)*(1+SUMPRODUCT(--ISNUMBER(SEARCH(PharmaLogic!$J$20:$J$41,LOWER($O13&" "&$B13))),PharmaLogic!$N$20:$N$41-1)))) -> 1 | T13: =IF($A13="","",MIN(1.6,IFERROR(INDEX(PharmaLogic!$O$4:$O$15,MATCH($N13,PharmaLogic!$J$4:$J$15,0)),1)*(1+SUMPRODUCT(--ISNUMBER(SEARCH(PharmaLogic!$J$20:$J$41,LOWER($O13&" "&$B13))),PharmaLogic!$O$20:$O$41-1)))) -> 1 | U13: =IF($A13="","",MIN(1.6,IFERROR(INDEX(PharmaLogic!$P$4:$P$15,MATCH($N13,PharmaLogic!$J$4:$J$15,0)),1)*(1+SUMPRODUCT(--ISNUMBER(SEARCH(PharmaLogic!$J$20:$J$41,LOWER($O13&" "&$B13))),PharmaLogic!$P$20:$P$41-1)))) -> 1
A14: =SignalRegister!A14 | B14: =SignalRegister!D14 | C14: =SignalRegister!F14 | D14: =SignalRegister!G14 | E14: =SignalRegister!H14 | F14: =SignalRegister!I14 | G14: =IF($A14="","",IF($C14="Positive",1,-1)*((N($D14)+N($E14))/(2*5))*IF($C14="Positive",Actors!$C$4,Actors!$D$4)*Actors!$E$4*$P14) | H14: =IF($A14="","",IF($C14="Positive",1,-1)*((N($D14)+N($E14))/(2*5))*IF($C14="Positive",Actors!$C$5,Actors!$D$5)*Actors!$E$5*$Q14) | I14: =IF($A14="","",IF($C14="Positive",1,-1)*((N($D14)+N($E14))/(2*5))*IF($C14="Positive",Actors!$C$6,Actors!$D$6)*Actors!$E$6*$R14) | J14: =IF($A14="","",IF($C14="Positive",1,-1)*((N($D14)+N($E14))/(2*5))*IF($C14="Positive",Actors!$C$7,Actors!$D$7)*Actors!$E$7*$S14) | K14: =IF($A14="","",IF($C14="Positive",1,-1)*((N($D14)+N($E14))/(2*5))*IF($C14="Positive",Actors!$C$8,Actors!$D$8)*Actors!$E$8*$T14) | L14: =IF($A14="","",IF($C14="Positive",1,-1)*((N($D14)+N($E14))/(2*5))*IF($C14="Positive",Actors!$C$9,Actors!$D$9)*Actors!$E$9*$U14) | M14: =IF(A14="","",G14*Actors!$B$4+H14*Actors!$B$5+I14*Actors!$B$6+J14*Actors!$B$7+K14*Actors!$B$8+L14*Actors!$B$9) | N14: =SignalRegister!E14 | O14: =SignalRegister!K14 | P14: =IF($A14="","",MIN(1.6,IFERROR(INDEX(PharmaLogic!$K$4:$K$15,MATCH($N14,PharmaLogic!$J$4:$J$15,0)),1)*(1+SUMPRODUCT(--ISNUMBER(SEARCH(PharmaLogic!$J$20:$J$41,LOWER($O14&" "&$B14))),PharmaLogic!$K$20:$K$41-1)))) | Q14: =IF($A14="","",MIN(1.6,IFERROR(INDEX(PharmaLogic!$L$4:$L$15,MATCH($N14,PharmaLogic!$J$4:$J$15,0)),1)*(1+SUMPRODUCT(--ISNUMBER(SEARCH(PharmaLogic!$J$20:$J$41,LOWER($O14&" "&$B14))),PharmaLogic!$L$20:$L$41-1)))) | R14: =IF($A14="","",MIN(1.6,IFERROR(INDEX(PharmaLogic!$M$4:$M$15,MATCH($N14,PharmaLogic!$J$4:$J$15,0)),1)*(1+SUMPRODUCT(--ISNUMBER(SEARCH(PharmaLogic!$J$20:$J$41,LOWER($O14&" "&$B14))),PharmaLogic!$M$20:$M$41-1)))) | S14: =IF($A14="","",MIN(1.6,IFERROR(INDEX(PharmaLogic!$N$4:$N$15,MATCH($N14,PharmaLogic!$J$4:$J$15,0)),1)*(1+SUMPRODUCT(--ISNUMBER(SEARCH(PharmaLogic!$J$20:$J$41,LOWER($O14&" "&$B14))),PharmaLogic!$N$20:$N$41-1)))) | T14: =IF($A14="","",MIN(1.6,IFERROR(INDEX(PharmaLogic!$O$4:$O$15,MATCH($N14,PharmaLogic!$J$4:$J$15,0)),1)*(1+SUMPRODUCT(--ISNUMBER(SEARCH(PharmaLogic!$J$20:$J$41,LOWER($O14&" "&$B14))),PharmaLogic!$O$20:$O$41-1)))) | U14: =IF($A14="","",MIN(1.6,IFERROR(INDEX(PharmaLogic!$P$4:$P$15,MATCH($N14,PharmaLogic!$J$4:$J$15,0)),1)*(1+SUMPRODUCT(--ISNUMBER(SEARCH(PharmaLogic!$J$20:$J$41,LOWER($O14&" "&$B14))),PharmaLogic!$P$20:$P$41-1))))
A15: =SignalRegister!A15 | B15: =SignalRegister!D15 | C15: =SignalRegister!F15 | D15: =SignalRegister!G15 | E15: =SignalRegister!H15 | F15: =SignalRegister!I15 | G15: =IF($A15="","",IF($C15="Positive",1,-1)*((N($D15)+N($E15))/(2*5))*IF($C15="Positive",Actors!$C$4,Actors!$D$4)*Actors!$E$4*$P15) | H15: =IF($A15="","",IF($C15="Positive",1,-1)*((N($D15)+N($E15))/(2*5))*IF($C15="Positive",Actors!$C$5,Actors!$D$5)*Actors!$E$5*$Q15) | I15: =IF($A15="","",IF($C15="Positive",1,-1)*((N($D15)+N($E15))/(2*5))*IF($C15="Positive",Actors!$C$6,Actors!$D$6)*Actors!$E$6*$R15) | J15: =IF($A15="","",IF($C15="Positive",1,-1)*((N($D15)+N($E15))/(2*5))*IF($C15="Positive",Actors!$C$7,Actors!$D$7)*Actors!$E$7*$S15) | K15: =IF($A15="","",IF($C15="Positive",1,-1)*((N($D15)+N($E15))/(2*5))*IF($C15="Positive",Actors!$C$8,Actors!$D$8)*Actors!$E$8*$T15) | L15: =IF($A15="","",IF($C15="Positive",1,-1)*((N($D15)+N($E15))/(2*5))*IF($C15="Positive",Actors!$C$9,Actors!$D$9)*Actors!$E$9*$U15) | M15: =IF(A15="","",G15*Actors!$B$4+H15*Actors!$B$5+I15*Actors!$B$6+J15*Actors!$B$7+K15*Actors!$B$8+L15*Actors!$B$9) | N15: =SignalRegister!E15 | O15: =SignalRegister!K15 | P15: =IF($A15="","",MIN(1.6,IFERROR(INDEX(PharmaLogic!$K$4:$K$15,MATCH($N15,PharmaLogic!$J$4:$J$15,0)),1)*(1+SUMPRODUCT(--ISNUMBER(SEARCH(PharmaLogic!$J$20:$J$41,LOWER($O15&" "&$B15))),PharmaLogic!$K$20:$K$41-1)))) | Q15: =IF($A15="","",MIN(1.6,IFERROR(INDEX(PharmaLogic!$L$4:$L$15,MATCH($N15,PharmaLogic!$J$4:$J$15,0)),1)*(1+SUMPRODUCT(--ISNUMBER(SEARCH(PharmaLogic!$J$20:$J$41,LOWER($O15&" "&$B15))),PharmaLogic!$L$20:$L$41-1)))) | R15: =IF($A15="","",MIN(1.6,IFERROR(INDEX(PharmaLogic!$M$4:$M$15,MATCH($N15,PharmaLogic!$J$4:$J$15,0)),1)*(1+SUMPRODUCT(--ISNUMBER(SEARCH(PharmaLogic!$J$20:$J$41,LOWER($O15&" "&$B15))),PharmaLogic!$M$20:$M$41-1)))) | S15: =IF($A15="","",MIN(1.6,IFERROR(INDEX(PharmaLogic!$N$4:$N$15,MATCH($N15,PharmaLogic!$J$4:$J$15,0)),1)*(1+SUMPRODUCT(--ISNUMBER(SEARCH(PharmaLogic!$J$20:$J$41,LOWER($O15&" "&$B15))),PharmaLogic!$N$20:$N$41-1)))) | T15: =IF($A15="","",MIN(1.6,IFERROR(INDEX(PharmaLogic!$O$4:$O$15,MATCH($N15,PharmaLogic!$J$4:$J$15,0)),1)*(1+SUMPRODUCT(--ISNUMBER(SEARCH(PharmaLogic!$J$20:$J$41,LOWER($O15&" "&$B15))),PharmaLogic!$O$20:$O$41-1)))) | U15: =IF($A15="","",MIN(1.6,IFERROR(INDEX(PharmaLogic!$P$4:$P$15,MATCH($N15,PharmaLogic!$J$4:$J$15,0)),1)*(1+SUMPRODUCT(--ISNUMBER(SEARCH(PharmaLogic!$J$20:$J$41,LOWER($O15&" "&$B15))),PharmaLogic!$P$20:$P$41-1))))
... A33: =SignalRegister!A33 | B33: =SignalRegister!D33 | C33: =SignalRegister!F33 | D33: =SignalRegister!G33 | E33: =SignalRegister!H33 | F33: =SignalRegister!I33 | G33: =IF($A33="","",IF($C33="Positive",1,-1)*((N($D33)+N($E33))/(2*5))*IF($C33="Positive",Actors!$C$4,Actors!$D$4)*Actors!$E$4*$P33) | H33: =IF($A33="","",IF($C33="Positive",1,-1)*((N($D33)+N($E33))/(2*5))*IF($C33="Positive",Actors!$C$5,Actors!$D$5)*Actors!$E$5*$Q33) | I33: =IF($A33="","",IF($C33="Positive",1,-1)*((N($D33)+N($E33))/(2*5))*IF($C33="Positive",Actors!$C$6,Actors!$D$6)*Actors!$E$6*$R33) | J33: =IF($A33="","",IF($C33="Positive",1,-1)*((N($D33)+N($E33))/(2*5))*IF($C33="Positive",Actors!$C$7,Actors!$D$7)*Actors!$E$7*$S33) | K33: =IF($A33="","",IF($C33="Positive",1,-1)*((N($D33)+N($E33))/(2*5))*IF($C33="Positive",Actors!$C$8,Actors!$D$8)*Actors!$E$8*$T33) | L33: =IF($A33="","",IF($C33="Positive",1,-1)*((N($D33)+N($E33))/(2*5))*IF($C33="Positive",Actors!$C$9,Actors!$D$9)*Actors!$E$9*$U33) | M33: =IF(A33="","",G33*Actors!$B$4+H33*Actors!$B$5+I33*Actors!$B$6+J33*Actors!$B$7+K33*Actors!$B$8+L33*Actors!$B$9) | N33: =SignalRegister!E33 | O33: =SignalRegister!K33 | P33: =IF($A33="","",MIN(1.6,IFERROR(INDEX(PharmaLogic!$K$4:$K$15,MATCH($N33,PharmaLogic!$J$4:$J$15,0)),1)*(1+SUMPRODUCT(--ISNUMBER(SEARCH(PharmaLogic!$J$20:$J$41,LOWER($O33&" "&$B33))),PharmaLogic!$K$20:$K$41-1)))) | Q33: =IF($A33="","",MIN(1.6,IFERROR(INDEX(PharmaLogic!$L$4:$L$15,MATCH($N33,PharmaLogic!$J$4:$J$15,0)),1)*(1+SUMPRODUCT(--ISNUMBER(SEARCH(PharmaLogic!$J$20:$J$41,LOWER($O33&" "&$B33))),PharmaLogic!$L$20:$L$41-1)))) | R33: =IF($A33="","",MIN(1.6,IFERROR(INDEX(PharmaLogic!$M$4:$M$15,MATCH($N33,PharmaLogic!$J$4:$J$15,0)),1)*(1+SUMPRODUCT(--ISNUMBER(SEARCH(PharmaLogic!$J$20:$J$41,LOWER($O33&" "&$B33))),PharmaLogic!$M$20:$M$41-1)))) | S33: =IF($A33="","",MIN(1.6,IFERROR(INDEX(PharmaLogic!$N$4:$N$15,MATCH($N33,PharmaLogic!$J$4:$J$15,0)),1)*(1+SUMPRODUCT(--ISNUMBER(SEARCH(PharmaLogic!$J$20:$J$41,LOWER($O33&" "&$B33))),PharmaLogic!$N$20:$N$41-1)))) | T33: =IF($A33="","",MIN(1.6,IFERROR(INDEX(PharmaLogic!$O$4:$O$15,MATCH($N33,PharmaLogic!$J$4:$J$15,0)),1)*(1+SUMPRODUCT(--ISNUMBER(SEARCH(PharmaLogic!$J$20:$J$41,LOWER($O33&" "&$B33))),PharmaLogic!$O$20:$O$41-1)))) | U33: =IF($A33="","",MIN(1.6,IFERROR(INDEX(PharmaLogic!$P$4:$P$15,MATCH($N33,PharmaLogic!$J$4:$J$15,0)),1)*(1+SUMPRODUCT(--ISNUMBER(SEARCH(PharmaLogic!$J$20:$J$41,LOWER($O33&" "&$B33))),PharmaLogic!$P$20:$P$41-1))))

Sheet ActorAggregation
A1: CIOS V19 Actor Aggregation
A3: Actor | B3: NetActorEffect | C3: Interpretation
A4: =Actors!A4 -> Academic KOLs | B4: =SUM(ActorReactionMatrix!G4:G33)*Actors!B4 -> 0.34394578 | C4: =IF(B4="","",IF(B4>0.25,"Strong support",IF(B4>0.05,"Moderate support",IF(B4< -0.25,"Strong constraint",IF(B4< -0.05,"Moderate constraint","Neutral / mixed"))))) -> Strong support
A5: =Actors!A5 -> Community Physicians | B5: =SUM(ActorReactionMatrix!H4:H33)*Actors!B5 -> 0.0656538 | C5: =IF(B5="","",IF(B5>0.25,"Strong support",IF(B5>0.05,"Moderate support",IF(B5< -0.25,"Strong constraint",IF(B5< -0.05,"Moderate constraint","Neutral / mixed"))))) -> Moderate support
A6: =Actors!A6 -> Specialty Extenders / PCPs | B6: =SUM(ActorReactionMatrix!I4:I33)*Actors!B6 -> 0.093212415 | C6: =IF(B6="","",IF(B6>0.25,"Strong support",IF(B6>0.05,"Moderate support",IF(B6< -0.25,"Strong constraint",IF(B6< -0.05,"Moderate constraint","Neutral / mixed"))))) -> Moderate support
A7: =Actors!A7 -> Payers / Access | B7: =SUM(ActorReactionMatrix!J4:J33)*Actors!B7 -> 0.12571891 | C7: =IF(B7="","",IF(B7>0.25,"Strong support",IF(B7>0.05,"Moderate support",IF(B7< -0.25,"Strong constraint",IF(B7< -0.05,"Moderate constraint","Neutral / mixed"))))) -> Moderate support
A8: =Actors!A8 -> Guideline / Society Bodies | B8: =SUM(ActorReactionMatrix!K4:K33)*Actors!B8 -> 0.20775946 | C8: =IF(B8="","",IF(B8>0.25,"Strong support",IF(B8>0.05,"Moderate support",IF(B8< -0.25,"Strong constraint",IF(B8< -0.05,"Moderate constraint","Neutral / mixed"))))) -> Moderate support
A9: =Actors!A9 -> Competitor Counteraction | B9: =SUM(ActorReactionMatrix!L4:L33)*Actors!B9 -> -0.085317556 | C9: =IF(B9="","",IF(B9>0.25,"Strong support",IF(B9>0.05,"Moderate support",IF(B9< -0.25,"Strong constraint",IF(B9< -0.05,"Moderate constraint","Neutral / mixed"))))) -> Moderate constraint
A10: Top supportive actor | B10: =INDEX(A4:A9,MATCH(MAX(B4:B9),B4:B9,0)) -> Academic KOLs
A11: Top constraining actor | B11: =INDEX(A4:A9,MATCH(MIN(B4:B9),B4:B9,0)) -> Competitor Counteraction
A12: Net actor translation | B12: =SUM(B4:B9) -> 0.75097281

Sheet ProbabilityEngine
A1: CIOS V18 Probability Engine
A3: Metric | B3: Value | C3: Logic
A4: Prior probability | B4: 0.45 | C4: User-set baseline prior for the focal case.
A5: Prior odds | B5: =IF(B4>=1,"",B4/(1-B4)) -> 0.81818182 | C5: Converts prior probability to odds.
A6: Signal LR product | B6: =IF(COUNTIF(SignalRegister!A4:A33,"<>")=0,1,PRODUCT(SignalRegister!P4:P33)) -> 1.25664 | C6: Multiplicative effect of validated likelihood ratios.
A7: Actor adjustment factor | B7: =EXP(ActorAggregation!B12/2) -> 1.4556993 | C7: Behavioral translation from signals into actor-mediated effect.
A8: Posterior odds | B8: =B5*B6*B7 -> 1.4966918 | C8: Core updated odds after signals and actor layer.
A9: Current probability | B9: =IF(B8="","",B8/(1+B8)) -> 0.59946999 | C9: Converted final probability.
A10: Confidence level | B10: =IF(COUNTIF(SignalRegister!A4:A33,"<>")=0,"Low",IF(COUNTIF(SignalRegister!A4:A33,"<>")<3,"Developing",IF(ABS(ActorAggregation!B12)<0.15,"Moderate","High"))) -> High | C10: Heuristic confidence based on evidence count and actor coherence.
A11: Net actor translation | B11: =ActorAggregation!B12 -> 0.75097281 | C11: Sum of weighted actor effects.

Sheet InterpretationLayer
A1: CIOS V19 Interpretation Layer
A3: InterpretationField | B3: Output
A4: Primary forecast statement | B4: =IF(ProbabilityEngine!B9="","",IF(ProbabilityEngine!B9>=0.7,"High-likelihood case with strong actor support",IF(ProbabilityEngine!B9>=0.55,"Moderately favorable case requiring monitoring","Probability remains constrained; message and objection refinement still needed"))) -> Moderately favorable case requiring monitoring
A5: Top supportive actor | B5: =ActorAggregation!B10 -> Academic KOLs
A6: Top constraining actor | B6: =ActorAggregation!B11 -> Competitor Counteraction
A7: Highest-impact signal | B7: =IFERROR(INDEX(SignalRegister!D4:D33,MATCH(MAX(SignalRegister!Q4:Q33),SignalRegister!Q4:Q33,0)),"") -> A new publication appears to strengthen the bridge between microbiology and function.
A8: Recommended action | B8: =IF(ProbabilityEngine!B9>=0.7,"Scale deployment and reinforce winning messages",IF(ProbabilityEngine!B9>=0.55,"Target supportive actors and close remaining objections","Re-route weak points to MIOS/OHOS before broader scale-up")) -> Target supportive actors and close remaining objections
A9: MIOS routing check | B9: =IF(COUNTIF(SignalRegister!L4:L33,"Yes")>0,"Yes","No") -> Yes
A10: OHOS routing check | B10: =IF(COUNTIF(SignalRegister!M4:M33,"Yes")>0,"Yes","No") -> Yes
A11: Behavioral summary | B11: =IF(ProbabilityEngine!B9="","",IF(AND(CaseHeader!B16<>"",CaseHeader!B17<>""),"Active actor set: "&CaseHeader!B16&". Tuned for "&CaseHeader!B17&", "&CaseHeader!B18&" guideline leverage, and "&CaseHeader!B19&".","")) -> Active actor set: General. Tuned for Balanced, Medium guideline leverage, and Entrenched standard of care.
A12: Top actor rationale | B12: =IFERROR(INDEX(Actors!$F$4:$F$9,MATCH(B5,Actors!$A$4:$A$9,0)),"") -> Cross-specialty scientific validators and early adopters.

Sheet CalibrationLog
A1: CIOS V18 Calibration Log
A3: ForecastID | B3: CaseID | C3: PredictionDate | D3: PredictedProbability | E3: ObservedOutcome | F3: BrierComponent | G3: Notes
A4: FCAST-001 | B4: =CaseHeader!B4 -> CASE-001 | C4: =TODAY() -> 46096 | D4: =ProbabilityEngine!B9 -> 0.59946999 | F4: =IF(OR(E4="",D4=""),"", (D4-E4)^2 ) | G4: Initial V18 forecast record.

Sheet DriverPanel
A1: SignalID | B1: SignalDescription | C1: Direction | D1: StrengthScore | E1: ReliabilityScore | F1: LikelihoodRatio | G1: ImpactRank
A2: =SignalRegister!A4 -> CS-001 | B2: =SignalRegister!D4 -> A new publication appears to strengthen the bridge between microbiology and function. | C2: =SignalRegister!F4 -> Positive | D2: =SignalRegister!G4 -> 4 | E2: =SignalRegister!H4 -> 5 | F2: =SignalRegister!I4 -> 1.32 | G2: =IF(A2="","",RANK(ABS(SignalRegister!O4),ABS(SignalRegister!$O$4:$O$33),0)) -> #VALUE!
A3: =SignalRegister!A5 -> CS-002 | B3: =SignalRegister!D5 -> Multiple accounts continue to ask for a simpler identification and referral story. | C3: =SignalRegister!F5 -> Negative | D3: =SignalRegister!G5 -> 4 | E3: =SignalRegister!H5 -> 4 | F3: =SignalRegister!I5 -> 0.68 | G3: =IF(A3="","",RANK(ABS(SignalRegister!O5),ABS(SignalRegister!$O$4:$O$33),0)) -> #VALUE!
A4: =SignalRegister!A6 -> CS-003 | B4: =SignalRegister!D6 -> Emerging coverage shift could reduce reimbursement obstacles in target accounts. | C4: =SignalRegister!F6 -> Positive | D4: =SignalRegister!G6 -> 5 | E4: =SignalRegister!H6 -> 4 | F4: =SignalRegister!I6 -> 1.4 | G4: =IF(A4="","",RANK(ABS(SignalRegister!O6),ABS(SignalRegister!$O$4:$O$33),0)) -> #N/A
A5: =SignalRegister!A7 -> 0 | B5: =SignalRegister!D7 | C5: =SignalRegister!F7 | D5: =SignalRegister!G7 | E5: =SignalRegister!H7 | F5: =SignalRegister!I7 | G5: =IF(A5="","",RANK(ABS(SignalRegister!O7),ABS(SignalRegister!$O$4:$O$33),0)) -> #N/A
A6: =SignalRegister!A8 -> 0 | B6: =SignalRegister!D8 | C6: =SignalRegister!F8 | D6: =SignalRegister!G8 | E6: =SignalRegister!H8 | F6: =SignalRegister!I8 | G6: =IF(A6="","",RANK(ABS(SignalRegister!O8),ABS(SignalRegister!$O$4:$O$33),0)) -> #N/A
A7: =SignalRegister!A9 -> 0 | B7: =SignalRegister!D9 | C7: =SignalRegister!F9 | D7: =SignalRegister!G9 | E7: =SignalRegister!H9 | F7: =SignalRegister!I9 | G7: =IF(A7="","",RANK(ABS(SignalRegister!O9),ABS(SignalRegister!$O$4:$O$33),0)) -> 1
A8: =SignalRegister!A10 -> 0 | B8: =SignalRegister!D10 | C8: =SignalRegister!F10 | D8: =SignalRegister!G10 | E8: =SignalRegister!H10 | F8: =SignalRegister!I10 | G8: =IF(A8="","",RANK(ABS(SignalRegister!O10),ABS(SignalRegister!$O$4:$O$33),0)) -> 1
A9: =SignalRegister!A11 -> 0 | B9: =SignalRegister!D11 | C9: =SignalRegister!F11 | D9: =SignalRegister!G11 | E9: =SignalRegister!H11 | F9: =SignalRegister!I11 | G9: =IF(A9="","",RANK(ABS(SignalRegister!O11),ABS(SignalRegister!$O$4:$O$33),0)) -> 1
A10: =SignalRegister!A12 -> 0 | B10: =SignalRegister!D12 | C10: =SignalRegister!F12 | D10: =SignalRegister!G12 | E10: =SignalRegister!H12 | F10: =SignalRegister!I12 | G10: =IF(A10="","",RANK(ABS(SignalRegister!O12),ABS(SignalRegister!$O$4:$O$33),0)) -> 1
A11: =SignalRegister!A13 -> 0 | B11: =SignalRegister!D13 | C11: =SignalRegister!F13 | D11: =SignalRegister!G13 | E11: =SignalRegister!H13 | F11: =SignalRegister!I13 | G11: =IF(A11="","",RANK(ABS(SignalRegister!O13),ABS(SignalRegister!$O$4:$O$33),0)) -> 1

Sheet ScenarioSimulator
A1: ScenarioID | B1: HypotheticalSignal | C1: Direction | D1: EstimatedImpact | E1: NewProbability | F1: Notes
A2: SCN-001 | B2: Single positive high-strength signal | C2: Positive | D2: 0.15 | E2: =MIN(0.99,ProbabilityEngine!B9+0.15) -> 0.74946999 | F2: Illustrative upside sensitivity
A3: SCN-002 | B3: Single negative high-strength signal | C3: Negative | D3: -0.15 | E3: =MAX(0.01,ProbabilityEngine!B9-0.15) -> 0.44946999 | F3: Illustrative downside sensitivity

Sheet SignalRadar
A1: EventID | B1: EventName | C1: EventType | D1: ExpectedDate | E1: PotentialSignalDirection | F1: ImpactRange | G1: MonitoringStatus | H1: Source
A2: =CandidateSignalQueue!A4 -> CS-001 | B2: =CandidateSignalQueue!G4 -> New publication emphasizes patient-relevant outcomes linkage | C2: =CandidateSignalQueue!I4 -> Clinical evidence | D2: =CandidateSignalQueue!B4 -> 2026-03-13 | E2: =CandidateSignalQueue!J4 -> Positive | F2: =CandidateSignalQueue!N4 -> 4 | G2: =CandidateSignalQueue!R4 -> Queued | H2: =CandidateSignalQueue!D4 -> PubMed
A3: =CandidateSignalQueue!A5 -> CS-002 | B3: =CandidateSignalQueue!G5 -> Community pulmonologists still unclear on patient-fit | C3: =CandidateSignalQueue!I5 -> Field intelligence | D3: =CandidateSignalQueue!B5 -> 2026-03-13 | E3: =CandidateSignalQueue!J5 -> Negative | F3: =CandidateSignalQueue!N5 -> 4 | G3: =CandidateSignalQueue!R5 -> Queued | H3: =CandidateSignalQueue!D5 -> Field notes
A4: =CandidateSignalQueue!A6 -> CS-003 | B4: =CandidateSignalQueue!G6 -> Coverage update may lower access friction in selected plans | C4: =CandidateSignalQueue!I6 -> Access / commercial | D4: =CandidateSignalQueue!B6 -> 2026-03-13 | E4: =CandidateSignalQueue!J6 -> Positive | F4: =CandidateSignalQueue!N6 -> 5 | G4: =CandidateSignalQueue!R6 -> Queued | H4: =CandidateSignalQueue!D6 -> Payer bulletin
A5: =CandidateSignalQueue!A7 -> 0 | B5: =CandidateSignalQueue!G7 -> 0 | C5: =CandidateSignalQueue!I7 -> 0 | D5: =CandidateSignalQueue!B7 -> 0 | E5: =CandidateSignalQueue!J7 -> 0 | F5: =CandidateSignalQueue!N7 -> 0 | G5: =CandidateSignalQueue!R7 -> 0 | H5: =CandidateSignalQueue!D7 -> 0
A6: =CandidateSignalQueue!A8 -> 0 | B6: =CandidateSignalQueue!G8 -> 0 | C6: =CandidateSignalQueue!I8 -> 0 | D6: =CandidateSignalQueue!B8 -> 0 | E6: =CandidateSignalQueue!J8 -> 0 | F6: =CandidateSignalQueue!N8 -> 0 | G6: =CandidateSignalQueue!R8 -> 0 | H6: =CandidateSignalQueue!D8 -> 0

Sheet StrategicGuidance
A1: GuidanceID | B1: KeyRiskDriver | C1: RecommendedAction | D1: TargetAudience | E1: PriorityLevel | F1: LinkedSignalID
A2: GUID-001 | B2: =ActorAggregation!B10 -> Academic KOLs | C2: =InterpretationLayer!B8 -> Target supportive actors and close remaining objections | D2: Leadership / field | E2: High | F2: =SignalRegister!A4 -> CS-001
A3: GUID-002 | B3: =ActorAggregation!B11 -> Competitor Counteraction | C3: =IF(InterpretationLayer!B9="Yes","Route constraining objections to OHOS","Monitor") -> Route constraining objections to OHOS | D3: Field strategy | E3: High | F3: =SignalRegister!A5 -> CS-002
A4: GUID-003 | B4: Validated signals | C4: =IF(InterpretationLayer!B8="Yes","Refresh MIOS message architecture where flagged","No MIOS routing needed") -> No MIOS routing needed | D4: Medical strategy | E4: Medium | F4: =SignalRegister!A6 -> CS-003

Sheet ForecastLedger
A1: ForecastID | B1: CaseID | C1: PredictionDate | D1: PredictedProbability | E1: EventOutcome | F1: CalibrationScore | G1: Notes
A2: FCAST-001 | B2: =CaseHeader!B4 -> CASE-001 | C2: =TODAY() -> 46096 | D2: =ProbabilityEngine!B9 -> 0.59946999 | F2: =IF(E2="","", (D2-E2)^2 ) | G2: Initial V18 forecast from actor-reaction engine

Sheet ProbabilityTimeline
A1: CaseID | B1: Date | C1: Probability | D1: SignalChange | E1: Notes
A2: =CaseHeader!B4 -> CASE-001 | B2: =TODAY() -> 46096 | C2: =ProbabilityEngine!B9 -> 0.59946999 | D2: V18 actor translation added | E2: Initial upgraded engine output
